Workbook

Sheet JO#1
A1: Municipal P A Y R O L L
A2: WE HEREBY ACKNOWLEDGE TO HAVE RECEIVED FROM MINERVA L. BOONGALING, TREASURER OF PAGSANJAN, LAGUNA THE SUMS HEREIN SPECIFIED OPPOSITES OUR RESPECTIVE NAMES, THE SAME BEING FULL COMPENSATION FOR OUR SERVICES RENDERED DURING THE PERIOD STATED BELOW, TO THE CORRECTNESS OF WHICH WE HEREBY SEVERALLY
A4: NO. | B4: NAME | C4: DESIGNATION | D4: PERIOD OF SERVICE (INCLUSIVE DATES) | H4: AMOUNT ACCRUED FOR THE PERIOD | I4: D E D U C T I O N S
D5: FROM | E5: TO | I5: Hazard Pay | J5: SOS | K5: ESL | N5: GOVERNMENT SERVICE INSURANCE SYSTEM | AC5: AMOUNT PAID IN CASH (CR.A-1) | AD5: NO.
M6: EL | O6: POLICY LOAN | P6: MEDICARE | R6: LIFE/RETIREMENT | X6: GLOBE | Y6: RBP | AE6: SIGNATURE OF PAYEE | AF6: REMARKS
P7: PERSONAL SHARE | Q7: GOV'T. SHARE | R7: INSURANCE PREMIUM | V7: CAL | W7: UOLI | AB7: STATE. INSURANCE
F8: Daily Rate | G8: No. of | R8: PERSONAL SHARE | S8: GOV'T. SHARE | T8: OPTIONAL | U8: UOLI
G9: Days | Q9: Hazard
A10: 1 | B10: 2 | C10: 3 | D10: 4 | E10: 5 | F10: 6 | H10: 7 | I10: 8 | J10: 9 | K10: 10 | L10: 11 | M10: 12 | N10: 13 | O10: 12 | P10: 13 | Q10: 14 | R10: 15 | S10: 16 | T10: 17 | U10: 18 | V10: 21 | W10: 22 | X10: 23 | Y10: 24 | Z10: 19 | AA10: 20 | AB10: 21 | AC10: 22 | AD10: 23 | AE10: 24 | AF10: 25
A11: 1 | B11: 1031 | D11: Mar. 1-15, 2017 | AD11: 1
A12: 2 | B12: BON-TAG ANI-QUISMUNDO | C12: Admin Aide I | D12: - d | E12: o- | F12: 344.63 | G12: 11 | H12: =F12*G12 -> 3790.93 | AC12: =SUM(H12:AB12) -> 3790.93 | AD12: 2
A13: 3 | B13: 1041 | AD13: 3
A14: 4 | B14: MARIZ TORRES | C14: Admin Aide I | D14: - d | E14: o- | F14: 344.63 | G14: 11 | H14: =F14*G14 -> 3790.93 | AC14: =SUM(H14:AB14) -> 3790.93 | AD14: 4
A15: 5 | B15: JERICO CALCETAS | C15: Admin Aide I | D15: - d | E15: o- | F15: 344.63 | G15: 13 | H15: =F15*G15 -> 4480.19 | AC15: =SUM(H15:AB15) -> 4480.19 | AD15: 5
A16: 6 | B16: CANDY LOU DEL ROSARIO | C16: Admin Aide I | D16: - d | E16: o- | F16: 344.63 | G16: 13 | H16: =F16*G16 -> 4480.19 | AC16: =SUM(H16:AB16) -> 4480.19 | AD16: 6
A17: 7 | AD17: 7
A18: 8 | B18: 1061 | AD18: 8
A19: 9 | B19: JAIME PANGUITO | C19: Admin Aide I | D19: - d | E19: o- | F19: 344.63 | G19: 12 | H19: =F19*G19 -> 4135.56 | AC19: =SUM(H19:AB19) -> 4135.56 | AD19: 9
A20: 10 | B20: JOANNA ELIAZAR | C20: Admin Aide I | D20: - d | E20: o- | F20: 344.63 | G20: 12 | H20: =F20*G20 -> 4135.56 | AC20: =SUM(H20:AB20) -> 4135.56 | AD20: 10
A21: 11 | B21: 1081 | AD21: 11
A22: 12 | B22: HERLYN CABALLES | C22: Admin Aide I | D22: - d | E22: o- | F22: 344.63 | G22: 11 | H22: =F22*G22 -> 3790.93 | AC22: =SUM(H22:AB22) -> 3790.93 | AD22: 12
A23: 13 | B23: 7611 | AD23: 13
A24: 14 | B24: JOHN CHRISTIAM ABARQUEZ | C24: Admin Aide I | D24: - d | E24: o- | F24: 344.63 | G24: 11 | H24: =F24*G24 -> 3790.93 | AC24: =SUM(H24:AB24) -> 3790.93 | AD24: 14
A25: 15 | B25: DORIE LERON | C25: Admin Aide I | D25: - d | E25: o- | F25: 344.63 | G25: 11 | H25: =F25*G25 -> 3790.93 | AC25: =SUM(H25:AB25) -> 3790.93 | AD25: 15
A26: 16 | B26: ROGELIO CONTEGINO | C26: Admin Aide I | D26: - d | E26: o- | F26: 344.63 | G26: 11 | H26: =F26*G26 -> 3790.93 | AC26: =SUM(H26:AB26) -> 3790.93 | AD26: 16
A27: 17 | B27: 8711 | AD27: 17
A28: 18 | B28: TENNESEE WYLIE BALETE | C28: Admin Aide I | D28: - d | E28: o- | F28: 344.63 | G28: 15 | H28: =F28*G28 -> 5169.45 | AC28: =SUM(H28:AB28) -> 5169.45 | AD28: 18
A29: 19 | B29: 8731 | AD29: 19
A30: 20 | B30: ALFREDO GONZALES | C30: Admin Aide I | D30: - d | E30: o- | F30: 344.63 | G30: 14 | H30: =F30*G30 -> 4824.82 | AC30: =SUM(H30:AB30) -> 4824.82 | AD30: 20
A31: 21 | B31: RODANTE LORENZANA | C31: Admin Aide I | D31: - d | E31: o- | F31: 344.63 | G31: 13 | H31: =F31*G31 -> 4480.19 | AC31: =SUM(H31:AB31) -> 4480.19 | AD31: 21
A32: 22 | B32: ROBERTO BRECINIO | C32: Admin Aide I | D32: - d | E32: o- | F32: 344.63 | G32: 15 | H32: =F32*G32 -> 5169.45 | AC32: =SUM(H32:AB32) -> 5169.45 | AD32: 22
A33: 23 | B33: 8811 | AD33: 23
A34: 24 | B34: ALDRIN BUENA | C34: Admin Aide I | D34: - d | E34: o- | F34: 344.63 | G34: 13 | H34: =F34*G34 -> 4480.19 | AC34: =SUM(H34:AB34) -> 4480.19 | AD34: 24
A35: 25 | B35: JONATHAN AZULA | C35: Admin Aide I | D35: - d | E35: o- | F35: 344.63 | G35: 13 | H35: =F35*G35 -> 4480.19 | AC35: =SUM(H35:AB35) -> 4480.19 | AD35: 25
A36: 26 | B36: 8852 | AD36: 26
A37: 27 | B37: ROMANO ALMERA | C37: Admin Aide I | D37: - d | E37: o- | F37: 344.63 | G37: 12 | H37: =F37*G37 -> 4135.56 | AC37: =SUM(H37:AB37) -> 4135.56 | AD37: 27
A38: 28 | B38: NESTOR GABALENO | C38: Admin Aide I | D38: - d | E38: o- | F38: 344.63 | G38: 13 | H38: =F38*G38 -> 4480.19 | AC38: =SUM(H38:AB38) -> 4480.19 | AD38: 28
A39: 29 | B39: ERIK JAVIER | C39: Admin Aide I | D39: - d | E39: o- | F39: 344.63 | G39: 13 | H39: =F39*G39 -> 4480.19 | AC39: =SUM(H39:AB39) -> 4480.19 | AD39: 29
A40: 30 | B40: LED VENI PENIDO | C40: Admin Aide I | D40: - d | E40: o- | F40: 344.63 | G40: 13 | H40: =F40*G40 -> 4480.19 | AC40: =SUM(H40:AB40) -> 4480.19 | AD40: 30
A41: 31 | H41: =SUM(H12:H40) -> 86157.5 | AC41: =SUM(AC12:AC40)+I41 -> 86157.5 | AD41: 31
A42: (1) I HEREBY CERTIFY on my official oath that the above PAYROLL is correct, and that services above stated have been duly rendered. Payment for such services is also hereby approved from the appropriation indicated. | I42: (4) APPROVED | AB42: (5) I HEREBY CERTIFY on my official oath that I have paid in cash to each official and employee whose name appears on the above roll the amount set opposite his name, under column 22, he having signed or marked his name under column 24 above, in my presence and at the time that payment was made to him, in acknowledgement of receipt of the money paid him.
J44: GIRLIE JAVIER EJERCITO
J45: Municipal Mayor
C46: FLORANTE C. SALVADOR JR. | J46: Chief of Office
D47: Municipal Administrator
A49: (2) APPROVED for payment subject to preaudit:
E51: Treasurer | AB51: (6) I HEREBY CERTIFY on my official oath that each employee whose name appears on the above roll has been paid in cash or in check, and in no other mode, the amount shown under column 22 above, opposite his name. The total of the payments made by means this payroll amount to
A53: (3) Preaudited and approved for payment in the month of
C55: (P ) | E55: pesos only.
C56: Provincial Auditor | AF56: Treasurer

Sheet JOmto
A1: Municipal P A Y R O L L
A2: WE HEREBY ACKNOWLEDGE TO HAVE RECEIVED FROM MINERVA L. BOONGALING, TREASURER OF PAGSANJAN, LAGUNA THE SUMS HEREIN SPECIFIED OPPOSITES OUR RESPECTIVE NAMES, THE SAME BEING FULL COMPENSATION FOR OUR SERVICES RENDERED DURING THE PERIOD STATED BELOW, TO THE CORRECTNESS OF WHICH WE HEREBY SEVERALLY
A4: NO. | B4: NAME | C4: DESIGNATION | D4: PERIOD OF SERVICE (INCLUSIVE DATES) | H4: AMOUNT ACCRUED FOR THE PERIOD | I4: D E D U C T I O N S
D5: FROM | E5: TO | I5: Hazard Pay | J5: SOS | K5: ESL | N5: GOVERNMENT SERVICE INSURANCE SYSTEM | AC5: AMOUNT PAID IN CASH (CR.A-1) | AD5: NO.
M6: EL | O6: POLICY LOAN | P6: MEDICARE | R6: LIFE/RETIREMENT | X6: GLOBE | Y6: RBP | AE6: SIGNATURE OF PAYEE | AF6: REMARKS
P7: PERSONAL SHARE | Q7: GOV'T. SHARE | R7: INSURANCE PREMIUM | V7: CAL | W7: UOLI | AB7: STATE. INSURANCE
F8: Daily Rate | G8: No. of | R8: PERSONAL SHARE | S8: GOV'T. SHARE | T8: OPTIONAL | U8: UOLI
G9: Days | Q9: Hazard
A10: 1 | B10: 2 | C10: 3 | D10: 4 | E10: 5 | F10: 6 | H10: 7 | I10: 8 | J10: 9 | K10: 10 | L10: 11 | M10: 12 | N10: 13 | O10: 12 | P10: 13 | Q10: 14 | R10: 15 | S10: 16 | T10: 17 | U10: 18 | V10: 21 | W10: 22 | X10: 23 | Y10: 24 | Z10: 19 | AA10: 20 | AB10: 21 | AC10: 22 | AD10: 23 | AE10: 24 | AF10: 25
A11: 26 | B11: 8852 | AD11: 26
A12: 27 | B12: ROMANO ALMERA | C12: Admin Aide I | D12: Mar. 16-31, 2017 | F12: 344.63 | G12: 13 | H12: =F12*G12 -> 4480.19 | AC12: =SUM(H12:AB12) -> 4480.19 | AD12: 27
A13: 28 | B13: NESTOR GABALENO | C13: Admin Aide I | D13: - d | E13: o- | F13: 344.63 | G13: 14 | H13: =F13*G13 -> 4824.82 | AC13: =SUM(H13:AB13) -> 4824.82 | AD13: 28
A14: 29 | B14: ERIK JAVIER | C14: Admin Aide I | D14: - d | E14: o- | F14: 344.63 | G14: 14 | H14: =F14*G14 -> 4824.82 | AC14: =SUM(H14:AB14) -> 4824.82 | AD14: 29
A15: 30 | B15: LED VENI PENIDO | C15: Admin Aide I | D15: - d | E15: o- | F15: 344.63 | G15: 14 | H15: =F15*G15 -> 4824.82 | AC15: =SUM(H15:AB15) -> 4824.82 | AD15: 30
A27: 31 | H27: =SUM(H11:H26) -> 18954.65 | AC27: =SUM(AC11:AC26)+I27 -> 18954.65 | AD27: 31
A28: (1) I HEREBY CERTIFY on my official oath that the above PAYROLL is correct, and that services above stated have been duly rendered. Payment for such services is also hereby approved from the appropriation indicated. | I28: (4) APPROVED | AB28: (5) I HEREBY CERTIFY on my official oath that I have paid in cash to each official and employee whose name appears on the above roll the amount set opposite his name, under column 22, he having signed or marked his name under column 24 above, in my presence and at the time that payment was made to him, in acknowledgement of receipt of the money paid him.
J30: GIRLIE JAVIER EJERCITO
J31: Municipal Mayor
C32: ARCH. MANSLEY G. KIMHOKO | J32: Chief of Office
D33: Municipal Tourism Officer
A35: (2) APPROVED for payment subject to preaudit:
E37: Treasurer | AB37: (6) I HEREBY CERTIFY on my official oath that each employee whose name appears on the above roll has been paid in cash or in check, and in no other mode, the amount shown under column 22 above, opposite his name. The total of the payments made by means this payroll amount to
A39: (3) Preaudited and approved for payment in the month of
C41: (P ) | E41: pesos only.
C42: Provincial Auditor | AF42: Treasurer

Sheet JO#02
A1: Municipal P A Y R O L L
A2: WE HEREBY ACKNOWLEDGE TO HAVE RECEIVED FROM MINERVA L. BOONGALING, TREASURER OF PAGSANJAN, LAGUNA THE SUMS HEREIN SPECIFIED OPPOSITES OUR RESPECTIVE NAMES, THE SAME BEING FULL COMPENSATION FOR OUR SERVICES RENDERED DURING THE PERIOD STATED BELOW, TO THE CORRECTNESS OF WHICH WE HEREBY SEVERALLY
A4: NO. | B4: NAME | C4: DESIGNATION | D4: PERIOD OF SERVICE (INCLUSIVE DATES) | H4: AMOUNT ACCRUED FOR THE PERIOD | I4: D E D U C T I O N S
D5: FROM | E5: TO | I5: Hazard Pay | J5: SOS | K5: ESL | N5: GOVERNMENT SERVICE INSURANCE SYSTEM | AC5: AMOUNT PAID IN CASH (CR.A-1) | AD5: N U M B E R
G6: Mothly Rate | M6: EL | O6: POLICY LOAN | P6: MEDICARE | R6: LIFE/RETIREMENT | X6: GLOBE | Y6: RBP | AE6: SIGNATURE OF PAYEE | AF6: REMARKS
P7: PERSONAL SHARE | Q7: GOV'T. SHARE | R7: INSURANCE PREMIUM | V7: CAL | W7: UOLI | AB7: STATE. INSURANCE
G8: Daily Rate | R8: PERSONAL SHARE | S8: GOV'T. SHARE | T8: OPTIONAL | U8: UOLI
Q9: Hazard
A10: 1 | B10: 2 | C10: 3 | D10: 4 | E10: 5 | G10: 6 | H10: 7 | I10: 8 | J10: 9 | K10: 10 | L10: 11 | M10: 12 | N10: 13 | O10: 12 | P10: 13 | Q10: 14 | R10: 15 | S10: 16 | T10: 17 | U10: 18 | V10: 21 | W10: 22 | X10: 23 | Y10: 24 | Z10: 19 | AA10: 20 | AB10: 21 | AC10: 22 | AD10: 23 | AE10: 24 | AF10: 25
A11: 1 | B11: 1031 | AD11: 1
A12: 2 | B12: BON-TAG ANI-QUISMUNDO | C12: Admin Aide I | D12: Mar. 16-31 | F12: 12 | G12: 344.63 | H12: =G12*F12 -> 4135.56 | AC12: =SUM(H12:AB12) -> 4135.56 | AD12: 2
A13: 3 | B13: 1041 | AD13: 3
A14: 4 | B14: MARIZ TORRES | C14: Admin Aide I | D14: - d | E14: o- | F14: 11 | G14: 344.63 | H14: =G14*F14 -> 3790.93 | AC14: =SUM(H14:AB14) -> 3790.93 | AD14: 4
A15: 5 | B15: JERICO CALCETAS | C15: Admin Aide I | D15: - d | E15: o- | F15: 14 | G15: 344.63 | H15: =G15*F15 -> 4824.82 | AC15: =SUM(H15:AB15) -> 4824.82 | AD15: 5
A16: 6 | B16: CANDY LOU DEL ROSARIO | C16: Admin Aide I | D16: - d | E16: o- | F16: 17.5 | G16: 344.63 | H16: =G16*F16 -> 6031.025 | AC16: =SUM(H16:AB16) -> 6031.025 | AD16: 6
A17: 7 | B17: 1061 | AD17: 7
A18: 8 | B18: JAIME PANGUITO | C18: Admin Aide I | D18: - d | E18: o- | F18: 12 | G18: 344.63 | H18: =G18*F18 -> 4135.56 | AC18: =SUM(H18:AB18) -> 4135.56 | AD18: 8
A19: 9 | B19: JOANNA ELIAZAR | C19: Admin Aide I | D19: - d | E19: o- | F19: 11 | G19: 344.63 | H19: =G19*F19 -> 3790.93 | AC19: =SUM(H19:AB19) -> 3790.93 | AD19: 9
A20: 10 | B20: 1081 | AD20: 10
A21: 11 | B21: HERLYN CABALLES | C21: Admin Aide I | D21: - d | E21: o- | F21: 12 | G21: 344.63 | H21: =G21*F21 -> 4135.56 | AC21: =SUM(H21:AB21) -> 4135.56 | AD21: 11
A22: 20 | B22: 7611 | AD22: 20
A23: 21 | B23: JOHN CHRISTIAM ABARQUEZ | C23: Admin Aide I | D23: - d | E23: o- | F23: 11 | G23: 344.63 | H23: =G23*F23 -> 3790.93 | AC23: =SUM(H23:AB23) -> 3790.93 | AD23: 21
A24: 22 | B24: DORIE LERON | C24: Admin Aide I | D24: - d | E24: o- | F24: 12 | G24: 344.63 | H24: =G24*F24 -> 4135.56 | AC24: =SUM(H24:AB24) -> 4135.56 | AD24: 22
A25: 23 | B25: ROGELIO CONTEGINO | C25: Admin Aide I | D25: - d | E25: o- | F25: 12 | G25: 344.63 | H25: =G25*F25 -> 4135.56 | AC25: =SUM(H25:AB25) -> 4135.56 | AD25: 23
A26: 24 | B26: 8711 | AD26: 24
A27: 25 | B27: TENNESEE WYLIE BALETE | C27: Admin Aide I | D27: - d | E27: o- | F27: 13 | G27: 344.63 | H27: =G27*F27 -> 4480.19 | AC27: =SUM(H27:AB27) -> 4480.19 | AD27: 25
A28: 26 | B28: 8731 | AD28: 26
A29: 27 | B29: ALFREDO GONZALES | C29: Admin Aide I | D29: - d | E29: o- | F29: 12 | G29: 344.63 | H29: =G29*F29 -> 4135.56 | AC29: =SUM(H29:AB29) -> 4135.56 | AD29: 27
A30: 28 | B30: RODANTE LORENZANA | C30: Admin Aide I | D30: - d | E30: o- | F30: 11 | G30: 344.63 | H30: =G30*F30 -> 3790.93 | AC30: =SUM(H30:AB30) -> 3790.93 | AD30: 28
A31: 29 | B31: ROBERTO BRECINIO | C31: Admin Aide I | D31: - d | E31: o- | F31: 11 | G31: 344.63 | H31: =G31*F31 -> 3790.93 | AC31: =SUM(H31:AB31) -> 3790.93 | AD31: 29
A32: 30 | B32: 8751 | AD32: 30
A33: 31 | B33: MARK JOSEPH BALOTA | C33: Admin Aide I | D33: - d | E33: o- | F33: 12 | G33: 344.63 | H33: =G33*F33 -> 4135.56 | AC33: =SUM(H33:AB33) -> 4135.56 | AD33: 31
A34: 33 | B34: 8811 | AD34: 33
A35: 34 | B35: ALDRIN BUENA | C35: Admin Aide I | D35: - d | E35: o- | F35: 13 | G35: 344.63 | H35: =G35*F35 -> 4480.19 | AC35: =SUM(H35:AB35) -> 4480.19 | AD35: 34
A36: 35 | B36: JONATHAN AZULA | C36: Admin Aide I | D36: - d | E36: o- | F36: 12 | G36: 344.63 | H36: =G36*F36 -> 4135.56 | AC36: =SUM(H36:AB36) -> 4135.56 | AD36: 35
A37: 36 | B37: 8852 | AD37: 36
A38: 37 | B38: ROMANO ALMERA | C38: Admin Aide I | D38: - d | E38: o- | F38: 14 | G38: 344.63 | H38: =G38*F38 -> 4824.82 | AC38: =SUM(H38:AB38) -> 4824.82 | AD38: 37
A39: 38 | B39: NESTOR GABALENO | C39: Admin Aide I | D39: - d | E39: o- | F39: 13 | G39: 344.63 | H39: =G39*F39 -> 4480.19 | AC39: =SUM(H39:AB39) -> 4480.19 | AD39: 38
A40: 39 | B40: ERIK JAVIER | C40: Admin Aide I | D40: - d | E40: o- | F40: 14 | G40: 344.63 | H40: =G40*F40 -> 4824.82 | AC40: =SUM(H40:AB40) -> 4824.82 | AD40: 39
A41: 40 | B41: LED VENI PENIDO | C41: Admin Aide I | D41: - d | E41: o- | F41: 13 | G41: 344.63 | H41: =G41*F41 -> 4480.19 | AC41: =SUM(H41:AB41) -> 4480.19 | AD41: 40
A42: 43 | AD42: 43
A43: 44 | H43: =SUM(H11:H42) -> 90465.375 | I43: =SUM(I11:I42) -> 0 | AC43: =SUM(AC11:AC42) -> 90465.375 | AD43: 44
B45: (1) I HEREBY CERTIFY on my official oath that the above PAYROLL is correct, and that services above stated have been duly rendered. Payment for such services is also hereby approved from the appropriation indicated.
I46: (4) APPROVED | AB46: (5) I HEREBY CERTIFY on my official oath that I have paid in cash to each official and employee whose name appears on the above roll the amount set opposite his name, under column 22, he having signed or marked his name under column 24 above, in my presence and at the time that payment was made to him, in acknowledgement of receipt of the money paid him.
J47: GIRLIE JAVIER EJERCITO
C48: FLORANTE C. SALVADOR JR. | J48: Municipal Mayor
D49: Municipal Administrator | J49: Chief of Office
A51: (2) APPROVED for payment subject to preaudit:
E53: Treasurer | AB53: (6) I HEREBY CERTIFY on my official oath that each employee whose name appears on the above roll has been paid in cash or in check, and in no other mode, the amount shown under column 22 above, opposite his name. The total of the payments made by means this payroll amount to
A55: (3) Preaudited and approved for payment in the month of
C57: (P ) | E57: pesos only.
C58: Provincial Auditor | AF58: Treasurer

Sheet JO#LDRRM
A1: Municipal P A Y R O L L
A2: WE HEREBY ACKNOWLEDGE TO HAVE RECEIVED FROM MINERVA L. BOONGALING, TREASURER OF PAGSANJAN, LAGUNA THE SUMS HEREIN SPECIFIED OPPOSITES OUR RESPECTIVE NAMES, THE SAME BEING FULL COMPENSATION FOR OUR SERVICES RENDERED DURING THE PERIOD STATED BELOW, TO THE CORRECTNESS OF WHICH WE HEREBY SEVERALLY
A4: NO. | B4: NAME | C4: DESIGNATION | D4: PERIOD OF SERVICE (INCLUSIVE DATES) | H4: AMOUNT ACCRUED FOR THE PERIOD | I4: D E D U C T I O N S
D5: FROM | E5: TO | I5: Hazard Pay | J5: SOS | K5: ESL | N5: GOVERNMENT SERVICE INSURANCE SYSTEM | AC5: AMOUNT PAID IN CASH (CR.A-1) | AD5: N U M B E R
F6: Mothly Rate | M6: EL | O6: POLICY LOAN | P6: MEDICARE | R6: LIFE/RETIREMENT | X6: GLOBE | Y6: RBP | AE6: SIGNATURE OF PAYEE | AF6: REMARKS
P7: PERSONAL SHARE | Q7: GOV'T. SHARE | R7: INSURANCE PREMIUM | V7: CAL | W7: UOLI | AB7: STATE. INSURANCE
F8: Daily Rate | G8: No. of | R8: PERSONAL SHARE | S8: GOV'T. SHARE | T8: OPTIONAL | U8: UOLI
G9: Days | I9: Nov. 2016 | Q9: Hazard
A10: 1 | B10: 2 | C10: 3 | D10: 4 | E10: 5 | F10: 6 | H10: 7 | I10: 8 | J10: 9 | K10: 10 | L10: 11 | M10: 12 | N10: 13 | O10: 12 | P10: 13 | Q10: 14 | R10: 15 | S10: 16 | T10: 17 | U10: 18 | V10: 21 | W10: 22 | X10: 23 | Y10: 24 | Z10: 19 | AA10: 20 | AB10: 21 | AC10: 22 | AD10: 23 | AE10: 24 | AF10: 25
B11: 9941 LDRRMO
A12: 1 | B12: Jerome Lava | C12: Admin Aide I | D12: March 1-15, 2017 | F12: 344.63 | G12: 13 | H12: =F12*G12 -> 4480.19 | AC12: =SUM(H12:K12) -> 4480.19 | AD12: 1
A13: 2 | B13: Rhonnie Cosio | C13: Admin Aide I | D13: - d | E13: o- | F13: 344.63 | G13: 14 | H13: =F13*G13 -> 4824.82 | AC13: =SUM(H13:K13) -> 4824.82 | AD13: 2
A14: 3 | B14: Mark Paul Monteiro | C14: Admin Aide I | D14: - d | E14: o- | F14: 344.63 | G14: 14 | H14: =F14*G14 -> 4824.82 | AC14: =SUM(H14:K14) -> 4824.82 | AD14: 3
A15: 4 | B15: Hercules Glodoveza | C15: Admin Aide I | D15: - d | E15: o- | F15: 344.63 | G15: 13 | H15: =F15*G15 -> 4480.19 | AC15: =SUM(H15:K15) -> 4480.19 | AD15: 4
A16: 6 | AD16: 6
A17: 7 | AD17: 7
A18: 8 | AD18: 8
A19: 9 | AD19: 9
A20: 10 | AD20: 10
A21: 11 | AD21: 11
A22: 12 | AD22: 12
A23: 13 | AD23: 13
A24: 14 | AD24: 14
A25: 15 | AD25: 15
A26: 16 | AD26: 16
A27: 17 | AD27: 17
A28: 18 | AD28: 18
A29: 19 | B29: TOTAL | H29: =SUM(H11:H28) -> 18610.02 | AC29: =SUM(AC11:AC28) -> 18610.02 | AD29: 19
A30: (1) I HEREBY CERTIFY on my official oath that the above PAYROLL is correct, and that services above stated have been duly rendered. Payment for such services is also hereby approved from the appropriation indicated. | I30: (4) APPROVED | AB30: (5) I HEREBY CERTIFY on my official oath that I have paid in cash to each official and employee whose name appears on the above roll the amount set opposite his name, under column 22, he having signed or marked his name under column 24 above, in my presence and at the time that payment was made to him, in acknowledgement of receipt of the money paid him.
J32: GIRLIE JAVIER EJERCITO
J33: Municipal Mayor
D34: JAY KEENSON C. ACEBUCHE | J34: Chief of Office
D35: Municipal Planning & Devt. Coordinator
A37: (2) APPROVED for payment subject to preaudit:
E39: Treasurer | AB39: (6) I HEREBY CERTIFY on my official oath that each employee whose name appears on the above roll has been paid in cash or in check, and in no other mode, the amount shown under column 22 above, opposite his name. The total of the payments made by means this payroll amount to
A41: (3) Preaudited and approved for payment in the month of
C43: (P ) | E43: pesos only.
C44: Provincial Auditor | AF44: Treasurer

Sheet JO#5%DP
A1: Municipal P A Y R O L L
A2: WE HEREBY ACKNOWLEDGE TO HAVE RECEIVED FROM MINERVA L. BOONGALING, TREASURER OF PAGSANJAN, LAGUNA THE SUMS HEREIN SPECIFIED OPPOSITES OUR RESPECTIVE NAMES, THE SAME BEING FULL COMPENSATION FOR OUR SERVICES RENDERED DURING THE PERIOD STATED BELOW, TO THE CORRECTNESS OF WHICH WE HEREBY SEVERALLY
A4: NO. | B4: NAME | C4: DESIGNATION | D4: PERIOD OF SERVICE (INCLUSIVE DATES) | H4: AMOUNT ACCRUED FOR THE PERIOD | I4: D E D U C T I O N S
D5: FROM | E5: TO | I5: Hazard Pay | J5: SOS | K5: ESL | N5: GOVERNMENT SERVICE INSURANCE SYSTEM | AC5: AMOUNT PAID IN CASH (CR.A-1) | AD5: N U M B E R
G6: Mothly Rate | M6: EL | O6: POLICY LOAN | P6: MEDICARE | R6: LIFE/RETIREMENT | X6: GLOBE | Y6: RBP | AE6: SIGNATURE OF PAYEE | AF6: REMARKS
P7: PERSONAL SHARE | Q7: GOV'T. SHARE | R7: INSURANCE PREMIUM | V7: CAL | W7: UOLI | AB7: STATE. INSURANCE
G8: Daily Rate | R8: PERSONAL SHARE | S8: GOV'T. SHARE | T8: OPTIONAL | U8: UOLI
I9: Nov. 2016 | Q9: Hazard
A10: 1 | B10: 2 | C10: 3 | D10: 4 | E10: 5 | G10: 6 | H10: 7 | I10: 8 | J10: 9 | K10: 10 | L10: 11 | M10: 12 | N10: 13 | O10: 12 | P10: 13 | Q10: 14 | R10: 15 | S10: 16 | T10: 17 | U10: 18 | V10: 21 | W10: 22 | X10: 23 | Y10: 24 | Z10: 19 | AA10: 20 | AB10: 21 | AC10: 22 | AD10: 23 | AE10: 24 | AF10: 25
A11: 2 | B11: 5% DISASTER PREPAREDNESS-Mobilization of Emergency Response Team | AD11: 2
A12: 3 | B12: RONEL CABREZA | C12: Admin Aide I | D12: March 1-15, 2017 | F12: 12 | G12: 344.63 | H12: =G12*F12 -> 4135.56 | AC12: =SUM(H12:AB12) -> 4135.56 | AD12: 3
A13: 4 | B13: VICTOR MIRANDO | C13: Admin Aide I | D13: - d | E13: o- | F13: 13 | G13: 344.63 | H13: =G13*F13 -> 4480.19 | AC13: =SUM(H13:AB13) -> 4480.19 | AD13: 4
A14: 5 | B14: RODERICK TOBIAS | C14: Admin Aide I | D14: - d | E14: o- | F14: 13 | G14: 344.63 | H14: =G14*F14 -> 4480.19 | AC14: =SUM(H14:AB14) -> 4480.19 | AD14: 5
A15: 6 | B15: NIÑO VALDELLON | C15: Admin Aide I | D15: - d | E15: o- | F15: 13 | G15: 344.63 | H15: =G15*F15 -> 4480.19 | AC15: =SUM(H15:AB15) -> 4480.19 | AD15: 6
A16: 7 | B16: JAYSON AZULA | C16: Admin Aide I | D16: - d | E16: o- | F16: 13 | G16: 344.63 | H16: =G16*F16 -> 4480.19 | AC16: =SUM(H16:AB16) -> 4480.19 | AD16: 7
A17: 9 | AD17: 9
A18: 10 | AD18: 10
A19: 11 | AD19: 11
A20: 12 | AD20: 12
A21: 13 | AD21: 13
A22: 15 | AD22: 15
A23: 17 | AD23: 17
A24: 19 | AD24: 19
A25: 20 | AD25: 20
A26: 21 | AD26: 21
A27: 22 | AD27: 22
A28: 23 | B28: Grand Total | H28: =SUM(H12:H16) -> 22056.32 | AC28: =SUM(AC12:AC16) -> 22056.32 | AD28: 23
A29: (1) I HEREBY CERTIFY on my official oath that the above PAYROLL is correct, and that services above stated have been duly rendered. Payment for such services is also hereby approved from the appropriation indicated. | I29: (4) APPROVED | AB29: (5) I HEREBY CERTIFY on my official oath that I have paid in cash to each official and employee whose name appears on the above roll the amount set opposite his name, under column 22, he having signed or marked his name under column 24 above, in my presence and at the time that payment was made to him, in acknowledgement of receipt of the money paid him.
J31: GIRLIE JAVIER EJERCITO
J32: Municipal Mayor
D33: JAY KEENSON C. ACEBUCHE | J33: Chief of Office
D34: Municipal Planning & Devt. Coordinator
A36: (2) APPROVED for payment subject to preaudit:
E38: Treasurer | AB38: (6) I HEREBY CERTIFY on my official oath that each employee whose name appears on the above roll has been paid in cash or in check, and in no other mode, the amount shown under column 22 above, opposite his name. The total of the payments made by means this payroll amount to
A40: (3) Preaudited and approved for payment in the month of
C42: (P ) | E42: pesos only.
C43: Provincial Auditor | AF43: Treasurer

Sheet JO#20%LDC
A1: Municipal P A Y R O L L
A2: WE HEREBY ACKNOWLEDGE TO HAVE RECEIVED FROM MINERVA L. BOONGALING, TREASURER OF PAGSANJAN, LAGUNA THE SUMS HEREIN SPECIFIED OPPOSITES OUR RESPECTIVE NAMES, THE SAME BEING FULL COMPENSATION FOR OUR SERVICES RENDERED DURING THE PERIOD STATED BELOW, TO THE CORRECTNESS OF WHICH WE HEREBY SEVERALLY
A4: NO. | B4: NAME | C4: DESIGNATION | D4: PERIOD OF SERVICE (INCLUSIVE DATES) | H4: AMOUNT ACCRUED FOR THE PERIOD | I4: D E D U C T I O N S
D5: FROM | E5: TO | I5: Hazard Pay | J5: SOS | K5: ESL | N5: GOVERNMENT SERVICE INSURANCE SYSTEM | AC5: AMOUNT PAID IN CASH (CR.A-1) | AD5: N U M B E R
F6: Mothly Rate | M6: EL | O6: POLICY LOAN | P6: MEDICARE | R6: LIFE/RETIREMENT | X6: GLOBE | Y6: RBP | AE6: SIGNATURE OF PAYEE | AF6: REMARKS
P7: PERSONAL SHARE | Q7: GOV'T. SHARE | R7: INSURANCE PREMIUM | V7: CAL | W7: UOLI | AB7: STATE. INSURANCE
F8: Daily Rate | G8: No. of | R8: PERSONAL SHARE | S8: GOV'T. SHARE | T8: OPTIONAL | U8: UOLI
G9: Days | I9: Nov. 2016 | Q9: Hazard
A10: 1 | B10: 2 | C10: 3 | D10: 4 | E10: 5 | F10: 6 | H10: 7 | I10: 8 | J10: 9 | K10: 10 | L10: 11 | M10: 12 | N10: 13 | O10: 12 | P10: 13 | Q10: 14 | R10: 15 | S10: 16 | T10: 17 | U10: 18 | V10: 21 | W10: 22 | X10: 23 | Y10: 24 | Z10: 19 | AA10: 20 | AB10: 21 | AC10: 22 | AD10: 23 | AE10: 24 | AF10: 25
B11: 20% LDC
B12: ALFREDO GONZALES | C12: Admin Aide I | D12: March 1-15, 2017 | F12: 344.63 | G12: 14 | H12: =F12*14 -> 4824.82 | AC12: =SUM(H12:AB12) -> 4824.82
B13: RODANTE LORENZANA | C13: Admin Aide I | D13: - d | E13: o- | F13: 344.63 | G13: 14 | H13: =F13*14 -> 4824.82 | AC13: =SUM(H13:AB13) -> 4824.82
B14: RAMON WAPERINA | C14: Admin Aide I | D14: - d | E14: o- | F14: 344.63 | G14: 14 | H14: =F14*14 -> 4824.82 | AC14: =SUM(H14:AB14) -> 4824.82
B15: ROBERTO BRECINIO | C15: Admin Aide I | D15: - d | E15: o- | F15: 344.63 | G15: 10 | H15: =F15*10 -> 3446.3 | AC15: =SUM(H15:AB15) -> 3446.3
A23: 13 | AD23: 13
A24: 14 | AD24: 14
A25: 15 | AD25: 15
A26: 16 | AD26: 16
A27: 17 | AD27: 17
A28: 18 | AD28: 18
A29: 19 | AD29: 19
A30: 20 | AD30: 20
A31: 21 | AD31: 21
A32: 22 | AD32: 22
A33: 23 | AD33: 23
A34: 24 | AD34: 24
A35: 25 | AD35: 25
A36: 26 | B36: TOTAL | H36: =SUM(H11:H35) -> 17920.76 | AC36: =SUM(AC11:AC34) -> 17920.76 | AD36: 26
A37: (1) I HEREBY CERTIFY on my official oath that the above PAYROLL is correct, and that services above stated have been duly rendered. Payment for such services is also hereby approved from the appropriation indicated. | I37: (4) APPROVED | AB37: (5) I HEREBY CERTIFY on my official oath that I have paid in cash to each official and employee whose name appears on the above roll the amount set opposite his name, under column 22, he having signed or marked his name under column 24 above, in my presence and at the time that payment was made to him, in acknowledgement of receipt of the money paid him.
J39: GIRLIE JAVIER EJERCITO
J40: Municipal Mayor
D41: FLORANTE C. SALVADOR JR. | J41: Chief of Office
D42: Municipal Administrator
A44: (2) APPROVED for payment subject to preaudit:
E46: Treasurer | AB46: (6) I HEREBY CERTIFY on my official oath that each employee whose name appears on the above roll has been paid in cash or in check, and in no other mode, the amount shown under column 22 above, opposite his name. The total of the payments made by means this payroll amount to
A48: (3) Preaudited and approved for payment in the month of
C50: (P ) | E50: pesos only.
C51: Provincial Auditor | AF51: Treasurer

Sheet JO#20%DF
A1: Municipal P A Y R O L L
A2: WE HEREBY ACKNOWLEDGE TO HAVE RECEIVED FROM MINERVA L. BOONGALING, TREASURER OF PAGSANJAN, LAGUNA THE SUMS HEREIN SPECIFIED OPPOSITES OUR RESPECTIVE NAMES, THE SAME BEING FULL COMPENSATION FOR OUR SERVICES RENDERED DURING THE PERIOD STATED BELOW, TO THE CORRECTNESS OF WHICH WE HEREBY SEVERALLY
A4: NO. | B4: NAME | C4: DESIGNATION | D4: PERIOD OF SERVICE (INCLUSIVE DATES) | H4: AMOUNT ACCRUED FOR THE PERIOD | I4: D E D U C T I O N S
D5: FROM | E5: TO | I5: Hazard Pay | J5: SOS | K5: ESL | N5: GOVERNMENT SERVICE INSURANCE SYSTEM | AC5: AMOUNT PAID IN CASH (CR.A-1) | AD5: N U M B E R
F6: Mothly Rate | M6: EL | O6: POLICY LOAN | P6: MEDICARE | R6: LIFE/RETIREMENT | X6: GLOBE | Y6: RBP | AE6: SIGNATURE OF PAYEE | AF6: REMARKS
P7: PERSONAL SHARE | Q7: GOV'T. SHARE | R7: INSURANCE PREMIUM | V7: CAL | W7: UOLI | AB7: STATE. INSURANCE
F8: Daily Rate | G8: No. of | R8: PERSONAL SHARE | S8: GOV'T. SHARE | T8: OPTIONAL | U8: UOLI
G9: Days | I9: Nov. 2016 | Q9: Hazard
A10: 1 | B10: 2 | C10: 3 | D10: 4 | E10: 5 | F10: 6 | H10: 7 | I10: 8 | J10: 9 | K10: 10 | L10: 11 | M10: 12 | N10: 13 | O10: 12 | P10: 13 | Q10: 14 | R10: 15 | S10: 16 | T10: 17 | U10: 18 | V10: 21 | W10: 22 | X10: 23 | Y10: 24 | Z10: 19 | AA10: 20 | AB10: 21 | AC10: 22 | AD10: 23 | AE10: 24 | AF10: 25
B11: 20% DEVELOPMENT FUND-Solid Waste Management Environmental Services
A12: 1 | B12: ALBERT ELCA | C12: Admin Aide I | D12: March 1-15, 2017 | F12: 344.63 | G12: 13 | H12: =F12*G12 -> 4480.19 | AC12: =SUM(H12:K12) -> 4480.19 | AD12: 1
A13: 2 | B13: RICHARD MONTESUR | C13: Admin Aide I | D13: - d | E13: o- | F13: 344.63 | G13: 11 | H13: =F13*G13 -> 3790.93 | AC13: =SUM(H13:K13) -> 3790.93 | AD13: 2
A14: 3 | B14: RAMON WAPERINA | C14: Admin Aide I | D14: - d | E14: o- | F14: 344.63 | G14: 15 | H14: =F14*G14 -> 5169.45 | AC14: =SUM(H14:K14) -> 5169.45 | AD14: 3
A15: 4 | B15: RIVERA ANGELO | C15: Admin Aide I | D15: - d | E15: o- | F15: 344.63 | G15: 13 | H15: =F15*G15 -> 4480.19 | AC15: =SUM(H15:K15) -> 4480.19 | AD15: 4
A16: 5 | B16: NOEL ABEGONZA | C16: Admin Aide I | D16: - d | E16: o- | F16: 344.63 | G16: 13 | H16: =F16*G16 -> 4480.19 | AC16: =SUM(H16:K16) -> 4480.19 | AD16: 5
A17: 6 | AD17: 6
A18: 7 | AD18: 7
A19: 8 | AD19: 8
A20: 9 | AD20: 9
A21: 10 | AD21: 10
A22: 11 | AD22: 11
A23: 12 | AD23: 12
A24: 13 | AD24: 13
A25: 14 | AD25: 14
A26: 15 | AD26: 15
A27: 16 | AD27: 16
A28: 17 | AD28: 17
A29: 18 | AD29: 18
A30: 19 | B30: TOTAL | H30: =SUM(H11:H29) -> 22400.95 | AC30: =SUM(AC11:AC29) -> 22400.95 | AD30: 19
A31: (1) I HEREBY CERTIFY on my official oath that the above PAYROLL is correct, and that services above stated have been duly rendered. Payment for such services is also hereby approved from the appropriation indicated. | I31: (4) APPROVED | AB31: (5) I HEREBY CERTIFY on my official oath that I have paid in cash to each official and employee whose name appears on the above roll the amount set opposite his name, under column 22, he having signed or marked his name under column 24 above, in my presence and at the time that payment was made to him, in acknowledgement of receipt of the money paid him.
J33: GIRLIE JAVIER EJERCITO
J34: Municipal Mayor
D35: JAY KEENSON C. ACEBUCHE | J35: Chief of Office
D36: Municipal Planning & Devt. Coordinator
A38: (2) APPROVED for payment subject to preaudit:
E40: Treasurer | AB40: (6) I HEREBY CERTIFY on my official oath that each employee whose name appears on the above roll has been paid in cash or in check, and in no other mode, the amount shown under column 22 above, opposite his name. The total of the payments made by means this payroll amount to
A42: (3) Preaudited and approved for payment in the month of
C44: (P ) | E44: pesos only.
C45: Provincial Auditor | AF45: Treasurer

Sheet JO#MHO
A1: Municipal P A Y R O L L
A2: WE HEREBY ACKNOWLEDGE TO HAVE RECEIVED FROM MINERVA L. BOONGALING, TREASURER OF PAGSANJAN, LAGUNA THE SUMS HEREIN SPECIFIED OPPOSITES OUR RESPECTIVE NAMES, THE SAME BEING FULL COMPENSATION FOR OUR SERVICES RENDERED DURING THE PERIOD STATED BELOW, TO THE CORRECTNESS OF WHICH WE HEREBY SEVERALLY
A4: NO. | B4: NAME | C4: DESIGNATION | D4: PERIOD OF SERVICE (INCLUSIVE DATES) | H4: AMOUNT ACCRUED FOR THE PERIOD | I4: D E D U C T I O N S
D5: FROM | E5: TO | I5: Hazard Pay | J5: SOS | K5: ESL | N5: GOVERNMENT SERVICE INSURANCE SYSTEM | AC5: AMOUNT PAID IN CASH (CR.A-1) | AD5: N U M B E R
F6: Mothly Rate | M6: EL | O6: POLICY LOAN | P6: MEDICARE | R6: LIFE/RETIREMENT | X6: GLOBE | Y6: RBP | AE6: SIGNATURE OF PAYEE | AF6: REMARKS
P7: PERSONAL SHARE | Q7: GOV'T. SHARE | R7: INSURANCE PREMIUM | V7: CAL | W7: UOLI | AB7: STATE. INSURANCE
F8: Daily Rate | G8: No. of | R8: PERSONAL SHARE | S8: GOV'T. SHARE | T8: OPTIONAL | U8: UOLI
G9: Days | I9: Mar | Q9: Hazard
A10: 1 | B10: 2 | C10: 3 | D10: 4 | E10: 5 | F10: 6 | H10: 7 | I10: 8 | J10: 9 | K10: 10 | L10: 11 | M10: 12 | N10: 13 | O10: 12 | P10: 13 | Q10: 14 | R10: 15 | S10: 16 | T10: 17 | U10: 18 | V10: 21 | W10: 22 | X10: 23 | Y10: 24 | Z10: 19 | AA10: 20 | AB10: 21 | AC10: 22 | AD10: 23 | AE10: 24 | AF10: 25
A11: 1 | B11: 4411 | D11: Mar. 1-15, 2017 | AD11: 1
A12: 2 | B12: REGGIE PACHECO | C12: Admin Aide I | D12: - d | E12: o- | F12: 430.82 | G12: 12 | H12: =F12*G12 -> 5169.84 | AC12: =SUM(H12:K12) -> 5169.84 | AD12: 2
A13: 3 | B13: GLORIANA ELIS B. GOMA | C13: Admin Aide I | D13: - d | E13: o- | F13: 430.82 | G13: 12 | H13: =F13*G13 -> 5169.84 | I13: 1270.5 | AC13: =SUM(H13:K13) -> 6440.34 | AD13: 3
A14: 4 | B14: ZHALEE MARIE BALETE | C14: Admin Aide I | D14: - d | E14: o- | F14: 430.82 | G14: 14 | H14: =F14*G14 -> 6031.48 | I14: 1270.5 | AC14: =SUM(H14:K14) -> 7301.98 | AD14: 4
A15: 5 | B15: SNOOKY ENSINAS | C15: Admin Aide I | D15: - d | E15: o- | F15: 430.82 | G15: 13 | H15: =F15*G15 -> 5600.66 | I15: 1270.5 | AC15: =SUM(H15:K15) -> 6871.16 | AD15: 5
A16: 6 | B16: MARIA YSOBELLE CABALLES | C16: Admin Aide I | D16: - d | E16: o- | F16: 430.82 | G16: 12 | H16: =F16*G16 -> 5169.84 | I16: 1270.5 | AC16: =SUM(H16:K16) -> 6440.34 | AD16: 6
A17: 7 | B17: MARY JANE ONGSANSOY | C17: Admin Aide I | D17: - d | E17: o- | F17: 430.82 | G17: 13 | H17: =F17*G17 -> 5600.66 | I17: 1270.5 | AC17: =SUM(H17:K17) -> 6871.16 | AD17: 7
A18: 8 | B18: RAMIL ABLIR | C18: Admin Aide I | D18: - d | E18: o- | F18: 430.82 | G18: 12 | H18: =F18*G18 -> 5169.84 | AC18: =SUM(H18:K18) -> 5169.84 | AD18: 8
A19: 9 | AD19: 9
A20: 10 | AD20: 10
A21: 11 | AD21: 11
A22: 13 | AD22: 13
A23: 14 | AD23: 14
A24: 15 | AD24: 15
A25: 23 | AD25: 23
A26: 24 | AD26: 24
A27: 26 | B27: TOTAL | H27: =SUM(H12:H26) -> 37912.16 | I27: =SUM(I12:I26) -> 6352.5 | AC27: =SUM(AC11:AC26) -> 44264.66 | AD27: 26
A28: (1) I HEREBY CERTIFY on my official oath that the above PAYROLL is correct, and that services above stated have been duly rendered. Payment for such services is also hereby approved from the appropriation indicated. | I28: (4) APPROVED | AB28: (5) I HEREBY CERTIFY on my official oath that I have paid in cash to each official and employee whose name appears on the above roll the amount set opposite his name, under column 22, he having signed or marked his name under column 24 above, in my presence and at the time that payment was made to him, in acknowledgement of receipt of the money paid him.
J30: GIRLIE JAVIER EJERCITO
J31: Municipal Mayor
D32: DR. LYRA LERON TORRES | J32: Chief of Office
D33: Municipal Health Officer
A35: (2) APPROVED for payment subject to preaudit:
E37: Treasurer | AB37: (6) I HEREBY CERTIFY on my official oath that each employee whose name appears on the above roll has been paid in cash or in check, and in no other mode, the amount shown under column 22 above, opposite his name. The total of the payments made by means this payroll amount to
A39: (3) Preaudited and approved for payment in the month of
C41: (P ) | E41: pesos only.
C42: Provincial Auditor | AF42: Treasurer

Sheet JO#SB
A1: Municipal P A Y R O L L
A2: WE HEREBY ACKNOWLEDGE TO HAVE RECEIVED FROM MINERVA L. BOONGALING, TREASURER OF PAGSANJAN, LAGUNA THE SUMS HEREIN SPECIFIED OPPOSITES OUR RESPECTIVE NAMES, THE SAME BEING FULL COMPENSATION FOR OUR SERVICES RENDERED DURING THE PERIOD STATED BELOW, TO THE CORRECTNESS OF WHICH WE HEREBY SEVERALLY
A4: NO. | B4: NAME | C4: DESIGNATION | D4: PERIOD OF SERVICE (INCLUSIVE DATES) | H4: AMOUNT ACCRUED FOR THE PERIOD | I4: D E D U C T I O N S
D5: FROM | E5: TO | I5: Hazard Pay | J5: SOS | K5: ESL | N5: GOVERNMENT SERVICE INSURANCE SYSTEM | AC5: AMOUNT PAID IN CASH (CR.A-1) | AD5: N U M B E R
F6: Mothly Rate | M6: EL | O6: POLICY LOAN | P6: MEDICARE | R6: LIFE/RETIREMENT | X6: GLOBE | Y6: RBP | AE6: SIGNATURE OF PAYEE | AF6: REMARKS
P7: PERSONAL SHARE | Q7: GOV'T. SHARE | R7: INSURANCE PREMIUM | V7: CAL | W7: UOLI | AB7: STATE. INSURANCE
F8: Daily Rate | G8: No. of | R8: PERSONAL SHARE | S8: GOV'T. SHARE | T8: OPTIONAL | U8: UOLI
G9: Days | I9: Nov. 2016 | Q9: Hazard
A10: 1 | B10: 2 | C10: 3 | D10: 4 | E10: 5 | F10: 6 | H10: 7 | I10: 8 | J10: 9 | K10: 10 | L10: 11 | M10: 12 | N10: 13 | O10: 12 | P10: 13 | Q10: 14 | R10: 15 | S10: 16 | T10: 17 | U10: 18 | V10: 21 | W10: 22 | X10: 23 | Y10: 24 | Z10: 19 | AA10: 20 | AB10: 21 | AC10: 22 | AD10: 23 | AE10: 24 | AF10: 25
B11: 1016
A12: 1 | B12: NORMAN V. NICANDRO | C12: Admin Aide I | D12: March 1-15, 2017 | F12: 344.63 | G12: 12 | H12: =F12*G12 -> 4135.56 | AC12: =SUM(H12:AB12) -> 4135.56
A13: 2 | B13: MARILIZ M. TRINIDAD | C13: Admin Aide I | D13: - d | E13: o- | F13: 344.63 | G13: 7 | H13: =F13*G13 -> 2412.41 | AC13: =SUM(H13:AB13) -> 2412.41
B14: 1021
A15: 3 | B15: ANDRES H. SIERRAS | C15: Admin Aide I | D15: - d | E15: o- | F15: 344.63 | G15: 12 | H15: =F15*G15 -> 4135.56 | AC15: =SUM(H15:AB15) -> 4135.56
B29: TOTAL | H29: =SUM(H11:H28) -> 10683.53 | AC29: =SUM(AC11:AC28) -> 10683.53
A30: (1) I HEREBY CERTIFY on my official oath that the above PAYROLL is correct, and that services above stated have been duly rendered. Payment for such services is also hereby approved from the appropriation indicated. | I30: (4) APPROVED | AB30: (5) I HEREBY CERTIFY on my official oath that I have paid in cash to each official and employee whose name appears on the above roll the amount set opposite his name, under column 22, he having signed or marked his name under column 24 above, in my presence and at the time that payment was made to him, in acknowledgement of receipt of the money paid him.
J32: DR. PETER CASIUS M. TRINIDAD
J33: Municipal Vice Mayor
D34: DR. PETER CASIUS M. TRINIDAD | J34: Chief of Office
D35: Municipal Vice Mayor
A37: (2) APPROVED for payment subject to preaudit:
E39: Treasurer | AB39: (6) I HEREBY CERTIFY on my official oath that each employee whose name appears on the above roll has been paid in cash or in check, and in no other mode, the amount shown under column 22 above, opposite his name. The total of the payments made by means this payroll amount to
A41: (3) Preaudited and approved for payment in the month of
C43: (P ) | E43: pesos only.
C44: Provincial Auditor | AF44: Treasurer

Sheet Casual allow SB
A1: Municipal P A Y R O L L
A2: WE HEREBY ACKNOWLEDGE TO HAVE RECEIVED FROM MINERVA L. BOONGALING, TREASURER OF PAGSANJAN, LAGUNA THE SUMS HEREIN SPECIFIED OPPOSITES OUR RESPECTIVE NAMES, THE SAME BEING FULL COMPENSATION FOR OUR SERVICES RENDERED DURING THE PERIOD STATED BELOW, TO THE CORRECTNESS OF WHICH WE HEREBY SEVERALLY
A4: NO. | B4: NAME | C4: DESIGNATION | D4: PERIOD OF SERVICE (INCLUSIVE DATES) | G4: AMOUNT ACCRUED FOR THE PERIOD | H4: D E D U C T I O N S
D5: FROM | E5: TO | H5: LAUNDRY | I5: HAZARD PAY | J5: SUBSISTENCE | K5: EL | L5: GOVERNMENT SERVICE INSURANCE SYSTEM | X5: Pag Ibig | AA5: AMOUNT PAID IN CASH (CR.A-1) | AB5: N U M B E R
F6: MONTLY RATE OF PAY | L6: CONSOL | M6: POLICY LOAN | N6: PHILHEALTH | P6: LIFE/RETIREMENT | V6: GLOBE | W6: RBP | AC6: SIGNATURE OF PAYEE | AD6: REMARKS
N7: PERSONAL SHARE | O7: GOV'T. SHARE | P7: INSURANCE PREMIUM | T7: CAL | U7: EDU. CHILD | Z7: STATE. INSURANCE
P8: PERSONAL SHARE | Q8: GOVERNMENT SHARE | R8: OPTIONAL | S8: Educ
X9: MPL | Y9: CALAMITY
A10: 1 | B10: 2 | C10: 3 | D10: 4 | E10: 5 | F10: 6 | G10: 7 | H10: 8 | I10: 8 | J10: 9 | K10: 10 | L10: 11 | M10: 12 | N10: 13 | O10: 14 | P10: 15 | Q10: 17 | R10: 18 | S10: 20 | T10: 21 | U10: 22 | V10: 23 | W10: 24 | X10: 25 | Y10: 26 | Z10: 19 | AA10: 20 | AB10: 21 | AC10: 22 | AD10: 23
A11: 1 | AB11: 1
A12: 2 | B12: 1016-1021-1022 | AB12: 2
A13: 3 | B13: JOWEL PALACOL | C13: Admin Aide I | D13: March 2017 | G13: 2000 | AA13: =G13 -> 2000 | AB13: 3
A14: 4 | B14: MARVIN PINILI | C14: Admin Aide I | D14: -do- | G14: 2000 | AA14: =G14 -> 2000 | AB14: 4
A15: 5 | B15: NOWEL LERON | C15: Admin Aide I | D15: -do- | G15: 2000 | AA15: =G15 -> 2000 | AB15: 5
A16: 6 | AB16: 6
A17: 7 | AB17: 7
A18: 8 | AB18: 8
A19: 9 | AB19: 9
A20: 10 | AB20: 10
A21: 11 | AB21: 11
A22: 12 | AB22: 12
A23: 13 | AB23: 13
A24: 14 | AB24: 14
A25: 15 | AB25: 15
A26: 16 | AB26: 16
A27: 17 | G27: =SUM(G13:G26) -> 6000 | I27: =#REF! -> #REF! | AA27: =SUM(AA13:AA26) -> 6000 | AB27: 17
A29: (1) I HEREBY CERTIFY on my official oath that the above PAYROLL is correct, and that services above stated have been duly rendered. Payment for such services is also hereby approved from the appropriation indicated. | M29: APPROVED:
Z30: (5) I HEREBY CERTIFY on my official oath that I have paid in cash to each official and employee whose name appears on the above roll the amount set opposite his name, under column 28, he having signed or marked his name under column 30 above, in my presence and at the time that payment was made to him, in acknowledgement of receipt of the money paid him.
K31: (4) APPROVED
N32: PETER CASIUS M. TRINIDAD
N33: Municipal Vice Mayor
D34: PETER CASIUS M. TRINIDAD | N34: Chief of Office
D35: Municipal Vice Mayor
A37: (2) APPROVED for payment subject to preaudit: | Z37: (6) I HEREBY CERTIFY on my official oath that each employee whose name appears on the above roll has been paid in cash or in check, and in no other mode, the amount shown under column 21 above, opposite his name. The total of the payments made by means this payroll amount to
E39: Treasurer
A40: (3) Preaudited and approved for payment in the month of
C41: (P ) | E41: pesos only. | AD41: Treasurer

Sheet Casual allow
A1: Municipal P A Y R O L L
A2: WE HEREBY ACKNOWLEDGE TO HAVE RECEIVED FROM MINERVA L. BOONGALING, TREASURER OF PAGSANJAN, LAGUNA THE SUMS HEREIN SPECIFIED OPPOSITES OUR RESPECTIVE NAMES, THE SAME BEING FULL COMPENSATION FOR OUR SERVICES RENDERED DURING THE PERIOD STATED BELOW, TO THE CORRECTNESS OF WHICH WE HEREBY SEVERALLY
A4: NO. | B4: NAME | C4: DESIGNATION | D4: PERIOD OF SERVICE (INCLUSIVE DATES) | G4: AMOUNT ACCRUED FOR THE PERIOD | H4: D E D U C T I O N S
D5: FROM | E5: TO | H5: LAUNDRY | I5: HAZARD PAY | J5: SUBSISTENCE | K5: EL | M5: GOVERNMENT SERVICE INSURANCE SYSTEM | Y5: Pag Ibig | AB5: AMOUNT PAID IN CASH (CR.A-1) | AC5: N U M B E R
F6: MONTLY RATE OF PAY | M6: CONSOL | N6: POLICY LOAN | O6: PHILHEALTH | Q6: LIFE/RETIREMENT | W6: GLOBE | X6: RBP | AD6: SIGNATURE OF PAYEE | AE6: REMARKS
O7: PERSONAL SHARE | P7: GOV'T. SHARE | Q7: INSURANCE PREMIUM | U7: CAL | V7: EDU. CHILD | AA7: STATE. INSURANCE
Q8: PERSONAL SHARE | R8: GOVERNMENT SHARE | S8: OPTIONAL | T8: Educ
Y9: MPL | Z9: CALAMITY
A10: 1 | B10: 2 | C10: 3 | D10: 4 | E10: 5 | F10: 6 | G10: 7 | H10: 8 | I10: 9 | J10: 10 | K10: 11 | L10: 12 | M10: 13 | N10: 14 | O10: 15 | P10: 16 | Q10: 17 | R10: 18 | S10: 19 | T10: 20 | U10: 21 | V10: 22 | W10: 23 | X10: 24 | Y10: 25 | Z10: 26 | AA10: 27 | AB10: 28 | AC10: 29 | AD10: 30 | AE10: 31
A11: 1 | B11: 1011 | AC11: 1
A12: 2 | B12: LORELIE G. LAZARO | C12: Admin Aide I | D12: 42736 | G12: 2000 | AB12: =G12 -> 2000 | AC12: 2
A13: 3 | B13: MICHAEL FRANCIS PAILAN | C13: Admin Aide I | D13: -do- | G13: 2000 | AB13: =G13 -> 2000 | AC13: 3
A14: 4 | B14: DANIEL BUNGABONG | C14: Admin Aide I | D14: -do- | G14: 2000 | AB14: =G14 -> 2000 | AC14: 4
A15: 5 | B15: JUVY GRACE DB ABARQUEZ | C15: Admin Aide I | D15: -do- | G15: 2000 | AB15: =G15 -> 2000 | AC15: 5
A16: 6 | G16: =SUM(G12:G15) -> 8000 | H16: 0 | I16: 0 | J16: 0 | K16: 0 | L16: 0 | M16: 0 | N16: 0 | O16: 0 | P16: 0 | Q16: 0 | R16: 0 | S16: 0 | T16: 0 | U16: 0 | V16: 0 | W16: 0 | X16: 0 | Y16: 0 | Z16: 0 | AA16: 0 | AB16: =SUM(AB12:AB15) -> 8000 | AC16: 6
A17: 7 | B17: 1031 | AC17: 7
A18: 8 | B18: MELAROSE PABILONIA | C18: Admin Aide I | D18: -do- | G18: 2000 | H18: 0 | K18: 0 | AB18: =G18 -> 2000 | AC18: 8
A19: 9 | G19: 2000 | H19: 0 | I19: 0 | J19: 0 | K19: 0 | L19: 0 | M19: 0 | N19: 0 | O19: 0 | P19: 0 | Q19: 0 | R19: 0 | S19: 0 | T19: 0 | U19: 0 | V19: 0 | W19: 0 | X19: 0 | Y19: 0 | Z19: 0 | AA19: 0 | AB19: 2000 | AC19: 9
A20: 10 | B20: 1032 | AC20: 10
A21: 11 | C21: Admin Aide I | D21: -do- | G21: 0 | H21: 0 | K21: 0 | M21: 0 | N21: 0 | AB21: =G21 -> 0 | AC21: 11
A22: 12 | G22: 0 | H22: 0 | I22: 0 | J22: 0 | K22: 0 | L22: 0 | M22: 0 | N22: 0 | O22: 0 | P22: 0 | Q22: 0 | R22: 0 | S22: 0 | T22: 0 | U22: 0 | V22: 0 | W22: 0 | X22: 0 | Y22: 0 | Z22: 0 | AA22: 0 | AB22: 0 | AC22: 12
A23: 13 | B23: 1071 | AC23: 13
A24: 14 | B24: MICHELLE CASTILLO | C24: Admin Aide I | D24: -do- | G24: 2000 | H24: 0 | AB24: =G24 -> 2000 | AC24: 14
A25: 15 | B25: ALVIN VILLANUEVA | C25: Admin Aide I | D25: -do- | G25: 2000 | H25: 0 | K25: 0 | M25: 0 | N25: 0 | AB25: =G25 -> 2000 | AC25: 15
A26: 16 | G26: =SUM(G24:G25) -> 4000 | H26: 0 | I26: 0 | J26: 0 | K26: 0 | L26: 0 | M26: 0 | N26: 0 | O26: 0 | P26: 0 | Q26: 0 | R26: 0 | S26: 0 | T26: 0 | U26: 0 | V26: 0 | W26: 0 | X26: 0 | Y26: 0 | Z26: 0 | AA26: 0 | AB26: =SUM(AB24:AB25) -> 4000 | AC26: 16
A27: 17 | B27: 1081 | AC27: 17
A28: 18 | B28: JOANA PATRIZHA MERAMBEL | C28: Admin Aide I | D28: -do- | G28: 2000 | H28: 0 | AB28: =G28 -> 2000 | AC28: 18
A29: 19 | B29: FELVIC Z. QUIZON | C29: Admin Aide I | D29: -do- | G29: 2000 | H29: 0 | AB29: =G29 -> 2000 | AC29: 19
A30: 20 | B30: TAMMY O. BENELADA | C30: Admin Aide I | D30: -do- | G30: 2000 | AB30: =G30 -> 2000 | AC30: 20
A31: 21 | B31: RIZALINO DE CASTRO | C31: Admin Aide I | D31: -do- | G31: 2000 | H31: 0 | AB31: =G31 -> 2000 | AC31: 21
A32: 22 | B32: FRENZIE GARANTUZA | C32: Admin Aide I | D32: -do- | G32: 2000 | H32: 0 | AB32: =G32 -> 2000 | AC32: 22
A33: 23 | G33: =SUM(G28:G32) -> 10000 | H33: 0 | I33: 0 | J33: 0 | K33: 0 | L33: 0 | M33: 0 | N33: 0 | O33: 0 | P33: 0 | Q33: 0 | R33: 0 | S33: 0 | T33: 0 | U33: 0 | V33: 0 | W33: 0 | X33: 0 | Y33: 0 | Z33: 0 | AA33: 0 | AB33: =SUM(AB28:AB32) -> 10000 | AC33: 23
A34: 24 | B34: 1091 | AC34: 24
A35: 25 | B35: JACQUILOU DIMARANAN | C35: Admin Aide I | D35: -do- | G35: 2000 | H35: 0 | AB35: =G35 -> 2000 | AC35: 25
A36: 26 | B36: NIÑO LAGRIMAS | C36: Admin Aide I | D36: -do- | G36: 2000 | H36: 0 | AB36: =G36 -> 2000 | AC36: 26
A37: 27 | B37: CHRISTIAN ABRANTES | C37: Admin Aide I | D37: -do- | G37: 2000 | H37: 0 | AB37: =G37 -> 2000 | AC37: 27
A38: 28 | B38: ARLENE JAVIER | C38: Admin Aide I | D38: -do- | G38: 2000 | H38: 0 | AB38: =G38 -> 2000 | AC38: 28
A39: 29 | G39: =SUM(G35:G38) -> 8000 | H39: 0 | I39: 0 | J39: 0 | K39: 0 | L39: 0 | M39: 0 | N39: 0 | O39: 0 | P39: 0 | Q39: 0 | R39: 0 | S39: 0 | T39: 0 | U39: 0 | V39: 0 | W39: 0 | X39: 0 | Y39: 0 | Z39: 0 | AA39: 0 | AB39: =SUM(AB35:AB38) -> 8000 | AC39: 29
A40: 30 | B40: 1101 | AC40: 30
A41: 31 | B41: ARLENE RIVERA | C41: Admin Aide I | D41: -do- | G41: 2000 | H41: 0 | K41: 0 | AB41: =G41 -> 2000 | AC41: 31
A42: 32 | B42: GELSON SAMPANG | C42: Admin Aide I | D42: -do- | G42: 2000 | H42: 0 | M42: 0 | AB42: =G42 -> 2000 | AC42: 32
A43: 33 | G43: =SUM(G41:G42) -> 4000 | H43: 0 | I43: 0 | J43: 0 | K43: 0 | L43: 0 | M43: 0 | N43: 0 | O43: 0 | P43: 0 | Q43: 0 | R43: 0 | S43: 0 | T43: 0 | U43: 0 | V43: 0 | W43: 0 | X43: 0 | Y43: 0 | Z43: 0 | AA43: 0 | AB43: =SUM(AB41:AB42) -> 4000 | AC43: 33
A44: 34 | B44: 4411 | AC44: 34
A45: 35 | B45: LYKA NADERA | C45: Admin Aide I | D45: -do- | G45: 2000 | H45: 150 | I45: 1270.5 | J45: 950 | AB45: =G45+H45+I45+J45 -> 4370.5 | AC45: 35
A46: 36 | B46: HERMINIO WATSON | C46: Admin Aide I | D46: -do- | G46: 2000 | N46: 0 | AB46: =G46 -> 2000 | AC46: 36
A47: 37 | G47: =SUM(G45:G46) -> 4000 | H47: =SUM(H45:H46) -> 150 | I47: =SUM(I45:I46) -> 1270.5 | J47: =SUM(J45:J46) -> 950 | K47: 0 | L47: 0 | M47: 0 | N47: 0 | O47: 0 | P47: 0 | Q47: 0 | R47: 0 | S47: 0 | T47: 0 | U47: 0 | V47: 0 | W47: 0 | X47: 0 | Y47: 0 | Z47: 0 | AA47: 0 | AB47: =SUM(AB45:AB46) -> 6370.5 | AC47: 37
A48: 38 | B48: 6531 | AC48: 38
A49: 39 | B49: RONALD FULLEROS | C49: Admin Aide I | D49: -do- | G49: 2000 | H49: 0 | AB49: =G49 -> 2000 | AC49: 39
A50: 40 | G50: 2000 | H50: 0 | I50: 0 | J50: 0 | K50: 0 | L50: 0 | M50: 0 | N50: 0 | O50: 0 | P50: 0 | Q50: 0 | R50: 0 | S50: 0 | T50: 0 | U50: 0 | V50: 0 | W50: 0 | X50: 0 | Y50: 0 | Z50: 0 | AA50: 0 | AB50: 2000 | AC50: 40
A51: 41 | B51: 7611 | AC51: 41
A52: 42 | B52: RUTH GRACE WALO | C52: Admin Aide I | D52: -do- | G52: 2000 | H52: 0 | I52: 0 | J52: 0 | K52: 0 | M52: 0 | N52: 0 | AB52: =G52 -> 2000 | AC52: 42
A53: 43 | B53: ARGELYN DAVAC | C53: Admin Aide I | D53: -do- | G53: 2000 | H53: 0 | I53: 0 | J53: 0 | K53: 0 | M53: 0 | N53: 0 | AB53: =G53 -> 2000 | AC53: 43
A54: 44 | G54: =SUM(G52:G53) -> 4000 | H54: 0 | I54: 0 | J54: 0 | K54: 0 | L54: 0 | M54: 0 | N54: 0 | O54: 0 | P54: 0 | Q54: 0 | R54: 0 | S54: 0 | T54: 0 | U54: 0 | V54: 0 | W54: 0 | X54: 0 | Y54: 0 | Z54: 0 | AA54: 0 | AB54: =SUM(AB52:AB53) -> 4000 | AC54: 44
A55: 45 | B55: 8711 | AC55: 45
A56: 46 | B56: JOSEPH WARREN COLADILLA | C56: Admin Aide I | D56: -do- | G56: 2000 | K56: 0 | M56: 0 | N56: 0 | AB56: =G56 -> 2000 | AC56: 46
A57: 47 | B57: LANIE VILLA | C57: Admin Aide I | D57: -do- | G57: 2000 | M57: 0 | N57: 0 | AB57: =G57 -> 2000 | AC57: 47
A58: 48 | G58: =SUM(G56:G57) -> 4000 | H58: 0 | I58: 0 | J58: 0 | K58: 0 | L58: 0 | M58: 0 | N58: 0 | O58: 0 | P58: 0 | Q58: 0 | R58: 0 | S58: 0 | T58: 0 | U58: 0 | V58: 0 | W58: 0 | X58: 0 | Y58: 0 | Z58: 0 | AA58: 0 | AB58: =SUM(AB56:AB57) -> 4000 | AC58: 48
A59: 49 | B59: 8731 | AC59: 49
A60: 50 | B60: JAY ALMONTERO | C60: Admin Aide I | D60: -do- | G60: 2000 | H60: 0 | Q60: 0 | R60: 0 | S60: 0 | T60: 0 | U60: 0 | Z60: 0 | AB60: =G60 -> 2000 | AC60: 50
A61: 51 | B61: JAYRALD CABREGA | C61: Admin Aide I | D61: -do- | G61: 2000 | AB61: =G61 -> 2000 | AC61: 51
A62: 52 | B62: KELVIN ABAQUIN | C62: Admin Aide I | D62: -do- | G62: 2000 | H62: 0 | Q62: 0 | R62: 0 | S62: 0 | T62: 0 | U62: 0 | Z62: 0 | AB62: =G62 -> 2000 | AC62: 52
A63: 53 | G63: =SUM(G60:G62) -> 6000 | H63: 0 | I63: 0 | J63: 0 | K63: 0 | L63: 0 | M63: 0 | N63: 0 | O63: 0 | P63: 0 | Q63: 0 | R63: 0 | S63: 0 | T63: 0 | U63: 0 | V63: 0 | W63: 0 | X63: 0 | Y63: 0 | Z63: 0 | AA63: 0 | AB63: =SUM(AB60:AB62) -> 6000 | AC63: 53
A64: 54 | B64: 8751 | AC64: 54
A65: 55 | B65: JEFFERSON CABREZA | C65: Admin Aide I | D65: -do- | G65: 2000 | H65: 0 | K65: 0 | M65: 0 | N65: 0 | Q65: 0 | R65: 0 | S65: 0 | T65: 0 | U65: 0 | Y65: 0 | Z65: 0 | AB65: =G65 -> 2000 | AC65: 55
A66: 56 | B66: MARLON PAMATMAT | C66: Admin Aide I | D66: -do- | G66: 2000 | H66: 0 | K66: 0 | M66: 0 | N66: 0 | Q66: 0 | R66: 0 | S66: 0 | T66: 0 | U66: 0 | Y66: 0 | Z66: 0 | AB66: =G66 -> 2000 | AC66: 56
A67: 57 | G67: =SUM(G65:G66) -> 4000 | H67: 0 | I67: 0 | J67: 0 | K67: 0 | L67: 0 | M67: 0 | N67: 0 | O67: 0 | P67: 0 | Q67: 0 | R67: 0 | S67: 0 | T67: 0 | U67: 0 | V67: 0 | W67: 0 | X67: 0 | Y67: 0 | Z67: 0 | AA67: 0 | AB67: =SUM(AB65:AB66) -> 4000 | AC67: 57
A68: 58 | B68: 8841 | AC68: 58
A69: 59 | B69: FRANCISCO TOBIAS | C69: Admin Aide I | D69: -do- | G69: 2000 | H69: 0 | AB69: =G69 -> 2000 | AC69: 59
A70: 60 | G70: 2000 | H70: 0 | I70: 0 | J70: 0 | K70: 0 | L70: 0 | M70: 0 | N70: 0 | O70: 0 | P70: 0 | Q70: 0 | R70: 0 | S70: 0 | T70: 0 | U70: 0 | V70: 0 | W70: 0 | X70: 0 | Y70: 0 | Z70: 0 | AA70: 0 | AB70: 2000 | AC70: 60
A71: 61 | B71: 8852 | AC71: 61
A72: 62 | B72: JAY- ARR MANALO | C72: Admin Aide I | D72: -do- | G72: 2000 | H72: 0 | M72: 0 | Q72: 0 | R72: 0 | S72: 0 | U72: 0 | Z72: 0 | AB72: =G72 -> 2000 | AC72: 62
A73: 63 | B73: REGIE MANALO | C73: Admin Aide I | D73: -do- | G73: 2000 | H73: 0 | K73: 0 | M73: 0 | N73: 0 | Q73: 0 | R73: 0 | S73: 0 | T73: 0 | U73: 0 | Y73: 0 | Z73: 0 | AB73: =G73 -> 2000 | AC73: 63
A74: 64 | G74: =SUM(G72:G73) -> 4000 | H74: 0 | I74: 0 | J74: 0 | K74: 0 | L74: 0 | M74: 0 | N74: 0 | O74: 0 | P74: 0 | Q74: 0 | R74: 0 | S74: 0 | T74: 0 | U74: 0 | V74: 0 | W74: 0 | X74: 0 | Y74: 0 | Z74: 0 | AA74: 0 | AB74: =SUM(AB72:AB73) -> 4000 | AC74: 64
A75: 65 | H75: 0 | I75: 0 | J75: 0 | K75: 0 | L75: 0 | M75: 0 | N75: 0 | O75: 0 | P75: 0 | Q75: 0 | R75: 0 | S75: 0 | T75: 0 | U75: 0 | V75: 0 | W75: 0 | X75: 0 | Y75: 0 | Z75: 0 | AA75: 0 | AC75: 65
A76: 66 | G76: =+G75+G74+G70+G67+G63+G58+G54+G50+G47+G43+G39+G33+G26+G19+G16 -> 66000 | H76: =H47 -> 150 | I76: =I47 -> 1270.5 | J76: =J47 -> 950 | K76: 0 | L76: 0 | M76: 0 | N76: 0 | O76: 0 | P76: 0 | Q76: 0 | R76: 0 | S76: 0 | T76: 0 | U76: 0 | V76: 0 | W76: 0 | X76: 0 | Y76: 0 | Z76: 0 | AA76: 0 | AB76: =+AB75+AB74+AB70+AB67+AB63+AB58+AB54+AB50+AB47+AB43+AB39+AB33+AB26+AB19+AB16 -> 68370.5 | AC76: 66
A79: (1) I HEREBY CERTIFY on my official oath that the above PAYROLL is correct, and that services above stated have been duly rendered. Payment for such services is also hereby approved from the appropriation indicated. | AA79: (5) I HEREBY CERTIFY on my official oath that I have paid in cash to each official and employee whose name appears on the above roll the amount set opposite his name, under column 28, he having signed or marked his name under column 30 above, in my presence and at the time that payment was made to him, in acknowledgement of receipt of the money paid him.
K80: (4) APPROVED
D83: GIRLIE JAVIER EJERCITO | M83: GIRLIE JAVIER EJERCITO
D84: Municipal Mayor | M84: Municipal Mayor
M85: Chief of Office
A86: (2) APPROVED for payment subject to preaudit: | AA86: (6) I HEREBY CERTIFY on my official oath that each employee whose name appears on the above roll has been paid in cash or in check, and in no other mode, the amount shown under column 21 above, opposite his name. The total of the payments made by means this payroll amount to
E88: Treasurer
A89: (3) Preaudited and approved for payment in the month of
C90: (P ) | E90: pesos only. | AE90: Treasurer

Sheet CasualMHO1-15
A1: Municipal P A Y R O L L
A2: WE HEREBY ACKNOWLEDGE TO HAVE RECEIVED FROM MINERVA L. BOONGALING, TREASURER OF PAGSANJAN, LAGUNA THE SUMS HEREIN SPECIFIED OPPOSITES OUR RESPECTIVE NAMES, THE SAME BEING FULL COMPENSATION FOR OUR SERVICES RENDERED DURING THE PERIOD STATED BELOW, TO THE CORRECTNESS OF WHICH WE HEREBY SEVERALLY
A4: NO. | B4: NAME | C4: DESIGNATION | D4: PERIOD OF SERVICE (INCLUSIVE DATES) | H4: AMOUNT ACCRUED FOR THE PERIOD | I4: D E D U C T I O N S
D5: FROM | E5: TO | I5: HOUSING LOAN | J5: SOS | K5: ESL | L5: EL | N5: GOVERNMENT SERVICE INSURANCE SYSTEM | Z5: Pag Ibig | AC5: AMOUNT PAID IN CASH (CR.A-1) | AD5: N U M B E R
G6: MONTLY RATE OF PAY | N6: CONSOL | O6: POLICY LOAN | P6: PHILHEALTH | R6: LIFE/RETIREMENT | X6: GLOBE | Y6: RBP | AE6: SIGNATURE OF PAYEE | AF6: REMARKS
F7: No. of days | P7: PERSONAL SHARE | Q7: GOV'T. SHARE | R7: INSURANCE PREMIUM | V7: CAL | W7: EDU. CHILD | AB7: STATE. INSURANCE
R8: PERSONAL SHARE | S8: GOVERNMENT SHARE | T8: OPTIONAL | U8: Educ
Z9: MPL | AA9: CALAMITY
A10: 1 | B10: 2 | C10: 3 | D10: 4 | E10: 5 | G10: 6 | H10: 7 | I10: 8 | J10: 9 | K10: 10 | L10: 11 | M10: 12 | N10: 13 | O10: 14 | P10: 15 | Q10: 16 | R10: 17 | S10: 18 | T10: 19 | U10: 20 | V10: 21 | W10: 22 | X10: 23 | Y10: 24 | Z10: 25 | AA10: 26 | AB10: 27 | AC10: 28 | AD10: 29 | AE10: 30 | AF10: 31
B12: 4411
A13: 1 | B13: LYKA NADERA | C13: Admin Aide I | D13: Mar. 1-15, 2017 | F13: 12 | G13: 430.82 | H13: =G13*F13 -> 5169.84 | I13: 0 | L13: 0 | N13: 0 | O13: 0 | P13: 112.5 | Q13: =P13 -> 112.5 | R13: =ROUND((G13*22)*0.09,2) -> 853.02 | S13: =ROUND(G13*22*0.12,2) -> 1137.36 | AB13: 94.78 | AC13: =H13-(SUM(I13:P13)+R13+SUM(T13:AA13)) -> 4204.32 | AD13: 1
A14: 2 | B14: HERMINIO WATSHON | C14: Admin Aide I | D14: -do- | F14: 13 | G14: 430.82 | H14: =G14*F14 -> 5600.66 | I14: 0 | L14: 0 | N14: 0 | O14: 0 | P14: 112.5 | Q14: =P14 -> 112.5 | R14: =ROUND((G14*22)*0.09,2) -> 853.02 | S14: =ROUND(G14*22*0.12,2) -> 1137.36 | T14: 0 | U14: 0 | V14: 0 | Z14: 0 | AA14: 0 | AB14: 94.78 | AC14: =H14-(SUM(I14:P14)+R14+SUM(T14:AA14)) -> 4635.14 | AD14: 2
H25: =SUM(H13:H24) -> 10770.5 | P25: =SUM(P13:P24) -> 225 | Q25: =SUM(Q13:Q24) -> 225 | R25: =SUM(R13:R24) -> 1706.04 | S25: =SUM(S13:S24) -> 2274.72 | AB25: =SUM(AB13:AB24) -> 189.56 | AC25: =SUM(AC13:AC24) -> 8839.46
AB28: (5) I HEREBY CERTIFY on my official oath that I have paid in cash to each official and employee whose name appears on the above roll the amount set opposite his name, under column 28, he having signed or marked his name under column 30 above, in my presence and at the time that payment was made to him, in acknowledgement of receipt of the money paid him.
A29: (1) I HEREBY CERTIFY on my official oath that the above PAYROLL is correct, and that services above stated have been duly rendered. Payment for such services is also hereby approved from the appropriation indicated. | I29: (4) APPROVED
J31: GIRLIE JAVIER EJERCITO
J32: Municipal Mayor
D33: DR. LYRA LERON TORRES | J33: Chief of Office
D34: Municipal Health Officer
A36: (2) APPROVED for payment subject to preaudit: | AB36: (6) I HEREBY CERTIFY on my official oath that each employee whose name appears on the above roll has been paid in cash or in check, and in no other mode, the amount shown under column 21 above, opposite his name. The total of the payments made by means this payroll amount to
E38: Treasurer
A39: (3) Preaudited and approved for payment in the month of
C40: (P ) | E40: pesos only. | AF40: Treasurer

Sheet CasualMTO16-31
A1: Municipal P A Y R O L L
A2: WE HEREBY ACKNOWLEDGE TO HAVE RECEIVED FROM MINERVA L. BOONGALING, TREASURER OF PAGSANJAN, LAGUNA THE SUMS HEREIN SPECIFIED OPPOSITES OUR RESPECTIVE NAMES, THE SAME BEING FULL COMPENSATION FOR OUR SERVICES RENDERED DURING THE PERIOD STATED BELOW, TO THE CORRECTNESS OF WHICH WE HEREBY SEVERALLY
A4: NO. | B4: NAME | C4: DESIGNATION | D4: PERIOD OF SERVICE (INCLUSIVE DATES) | H4: AMOUNT ACCRUED FOR THE PERIOD | I4: D E D U C T I O N S
D5: FROM | E5: TO | I5: Withholding Tax | J5: SOS | K5: ESL | L5: EL | N5: GOVERNMENT SERVICE INSURANCE SYSTEM | AA5: PAG-IBIG | AE5: GSIS | AF5: AMOUNT PAID IN CASH (CR.A-1) | AG5: N U M B E R
G6: MONTLY RATE OF PAY | N6: CONSOL | O6: POLICY LOAN | R6: PAG-IBIG CONTRIBUTION | T6: LIFE/RETIREMENT | AH6: SIGNATURE OF PAYEE | AI6: REMARKS
R7: PERSONAL SHARE | S7: GOV'T. SHARE | T7: INSURANCE PREMIUM | Z7: EDUC
P8: GSIS contribution | T8: PS | U8: GS | V8: Philhleath Cont | X8: UOLI | AB8: CAL | AC8: MPL | AE8: STATE. INSURANCE
P9: PS | Q9: GS | V9: PS | W9: GS | Y9: Optional
A10: 1 | B10: 2 | C10: 3 | D10: 4 | E10: 5 | G10: 6 | H10: 7 | I10: 8 | J10: 9 | K10: 10 | L10: 9 | M10: 10 | N10: 11 | O10: 12 | R10: 13 | S10: 14 | T10: 15 | U10: 17 | X10: 18 | Y10: 19 | Z10: 20 | AA10: 21 | AB10: 22 | AC10: 22 | AD10: 26 | AF10: 24 | AG10: 25 | AH10: 26 | AI10: 27
B12: 8852
A13: 1 | B13: JAY - AR MANALO | C13: Admin Aide I | D13: Mar. 16-31, 2017 | F13: 9 | G13: =ROUND(7582/22,2) -> 344.64 | H13: =G13*F13 -> 3101.76 | R13: =ROUND(G13*22*0.02,2) -> 151.64 | S13: =R13 -> 151.64 | AF13: =H13-(SUM(I13:R13)+T13+SUM(V13:AD13)) -> 2950.12 | AG13: 1
A14: 2 | B14: REGIE MANALO | C14: Admin Aide I | D14: -do- | F14: 11 | G14: =ROUND(7582/22,2) -> 344.64 | H14: =G14*F14 -> 3791.04 | I14: 209.55 | L14: 0 | N14: 0 | O14: 0 | R14: =ROUND(G14*22*0.02,2) -> 151.64 | S14: =R14 -> 151.64 | T14: 0 | U14: 0 | X14: 0 | Y14: 0 | Z14: 0 | AB14: 0 | AC14: 0 | AF14: =H14-(SUM(I14:R14)+T14+SUM(V14:AD14)) -> 3429.85 | AG14: 2
H21: =SUM(H13:H15) -> 6892.8 | I21: =SUM(I13:I15) -> 209.55 | J21: =SUM(J13:J15) -> 0 | K21: =SUM(K13:K15) -> 0 | L21: =SUM(L13:L15) -> 0 | M21: =SUM(M13:M15) -> 0 | N21: =SUM(N13:N15) -> 0 | O21: =SUM(O13:O15) -> 0 | ... AF21: =SUM(AF13:AF15) -> 6379.97
A23: (1) I HEREBY CERTIFY on my official oath that the above PAYROLL is correct, and that services above stated have been duly rendered. Payment for such services is also hereby approved from the appropriation indicated. | R23: APPROVED:
AC24: (5) I HEREBY CERTIFY on my official oath that I have paid in cash to each official and employee whose name appears on the above roll the amount set opposite his name, under column 22, he having signed or marked his name under column 24 above, in my presence and at the time that payment was made to him, in acknowledgement of receipt of the money paid him.
R25: GIRLIE JAVIER EJERCITO
R26: Municipal Mayor
D27: ARCH. MANSLEY G. KIMHOKO | R27: Chief of Office
D28: Municipal Tourism Officer
A30: (2) APPROVED for payment subject to preaudit:
AC31: (6) I HEREBY CERTIFY on my official oath that each employee whose name appears on the above roll has been paid in cash or in check, and in no other mode, the amount shown under column 22 above, opposite his name. The total of the payments made by means this payroll amount to
E32: Treasurer
A33: (3) Preaudited and approved for payment in the month of
C34: (P ) | E34: pesos only. | AI34: Treasurer

Sheet CasualMHO16-31
A1: Municipal P A Y R O L L
A2: WE HEREBY ACKNOWLEDGE TO HAVE RECEIVED FROM MINERVA L. BOONGALING, TREASURER OF PAGSANJAN, LAGUNA THE SUMS HEREIN SPECIFIED OPPOSITES OUR RESPECTIVE NAMES, THE SAME BEING FULL COMPENSATION FOR OUR SERVICES RENDERED DURING THE PERIOD STATED BELOW, TO THE CORRECTNESS OF WHICH WE HEREBY SEVERALLY
A4: NO. | B4: NAME | C4: DESIGNATION | D4: PERIOD OF SERVICE (INCLUSIVE DATES) | H4: AMOUNT ACCRUED FOR THE PERIOD | I4: D E D U C T I O N S
D5: FROM | E5: TO | I5: Withholding Tax | J5: SOS | K5: ESL | L5: EL | Y5: PAG-IBIG | AD5: GSIS | AE5: AMOUNT PAID IN CASH (CR.A-1) | AF5: N U M B E R
G6: MONTLY RATE OF PAY | N6: CONSOL | O6: POLICY LOAN | P6: PAG-IBIG CONTRIBUTION | R6: LIFE/RETIREMENT | T6: Philhealth | AG6: SIGNATURE OF PAYEE | AH6: REMARKS
P7: PERSONAL SHARE | Q7: GOV'T. SHARE | R7: INSURANCE PREMIUM | X7: EDUC | AC7: STATE. INSURANCE
F8: No. of | R8: PERSONAL SHARE | S8: GOVERNMENT SHARE | T8: PERSONAL SHARE | U8: GOVERNMENT SHARE | Z8: CAL | AA8: MPL | AD8: STATE. INSURANCE
F9: days | V9: UOLI | W9: Optional
A10: 1 | B10: 2 | C10: 3 | D10: 4 | E10: 5 | G10: 6 | H10: 7 | I10: 8 | J10: 9 | K10: 10 | L10: 9 | M10: 10 | N10: 11 | O10: 12 | P10: 13 | Q10: 14 | R10: 15 | S10: 17 | U10: 17 | V10: 18 | W10: 19 | X10: 20 | Y10: 21 | Z10: 22 | AA10: 22 | AB10: 26 | AC10: 23 | AE10: 24 | AF10: 25 | AG10: 26 | AH10: 27
A11: 1 | B11: 4411 | AF11: 1
A12: 2 | B12: LYKA NADERA | C12: Admin Aide I | D12: Mar. 16-28, 2017 | F12: 14 | G12: 430.82 | H12: =G12*F12 -> 6031.48 | L12: 0 | O12: 0 | P12: =ROUND(G12*22*0.02,2) -> 189.56 | Q12: =P12 -> 189.56 | V12: 0 | X12: 0 | AE12: =H12-(SUM(I12:P12)+R12+SUM(U12:AB12)) -> 5841.92 | AF12: 2
A13: 3 | B13: HERMINIO WATSON | C13: Admin Aide I | D13: -do- | F13: 14 | G13: 430.82 | H13: =G13*F13 -> 6031.48 | I13: 246.16 | L13: 0 | O13: 0 | P13: =ROUND(G13*22*0.02,2) -> 189.56 | Q13: =P13 -> 189.56 | V13: 0 | X13: 0 | AE13: =H13-(SUM(I13:P13)+R13+SUM(U13:AB13)) -> 5595.76 | AF13: 3
A14: 4 | AF14: 4
A15: 5 | AF15: 5
A16: 6 | AF16: 6
A17: 7 | AF17: 7
A18: 8 | AF18: 8
A19: 9 | AF19: 9
A20: 10 | AF20: 10
A21: 11 | AF21: 11
A22: 12 | AF22: 12
A23: 13 | AF23: 13
A24: 14 | AF24: 14
A25: 15 | H25: =SUM(H12:H24) -> 12062.96 | I25: =SUM(I12:I24) -> 246.16 | J25: =SUM(J12:J24) -> 0 | K25: =SUM(K12:K24) -> 0 | P25: =SUM(P12:P24) -> 379.12 | Q25: =SUM(Q12:Q24) -> 379.12 | R25: =SUM(R12:R24) -> 0 | S25: =SUM(S12:S24) -> 0 | T25: =SUM(T12:T24) -> 0 | U25: =SUM(U12:U24) -> 0 | V25: =SUM(V12:V24) -> 0 | W25: =SUM(W12:W24) -> 0 | ... Y25: =SUM(Y12:Y24) -> 0 | AE25: =SUM(AE12:AE24) -> 11437.68 | AF25: 15
I27: APPROVED: | AC27: (5) I HEREBY CERTIFY on my official oath that I have paid in cash to each official and employee whose name appears on the above roll the amount set opposite his name, under column 22, he having signed or marked his name under column 24 above, in my presence and at the time that payment was made to him, in acknowledgement of receipt of the money paid him.
A28: (1) I HEREBY CERTIFY on my official oath that the above PAYROLL is correct, and that services above stated have been duly rendered. Payment for such services is also hereby approved from the appropriation indicated.
J30: GIRLIE JAVIER EJERCITO
J31: Municipal Mayor
D32: DR. LYRA LERON TORRES | J32: Chief of Office
D33: Municipal Health Officer
A35: (2) APPROVED for payment subject to preaudit:
AC36: (6) I HEREBY CERTIFY on my official oath that each employee whose name appears on the above roll has been paid in cash or in check, and in no other mode, the amount shown under column 22 above, opposite his name. The total of the payments made by means this payroll amount to
E37: Treasurer
A38: (3) Preaudited and approved for payment in the month of
C39: (P ) | E39: pesos only. | AH39: Treasurer

Sheet Casual 1-15 (SB)
A1: Municipal P A Y R O L L
A2: WE HEREBY ACKNOWLEDGE TO HAVE RECEIVED FROM MINERVA L. BOONGALING, TREASURER OF PAGSANJAN, LAGUNA THE SUMS HEREIN SPECIFIED OPPOSITES OUR RESPECTIVE NAMES, THE SAME BEING FULL COMPENSATION FOR OUR SERVICES RENDERED DURING THE PERIOD STATED BELOW, TO THE CORRECTNESS OF WHICH WE HEREBY SEVERALLY
A4: NO. | B4: NAME | C4: DESIGNATION | D4: PERIOD OF SERVICE (INCLUSIVE DATES) | H4: AMOUNT ACCRUED FOR THE PERIOD | I4: D E D U C T I O N S
D5: FROM | E5: TO | I5: HOUSING LOAN | J5: SOS | K5: ESL | L5: EL | N5: GOVERNMENT SERVICE INSURANCE SYSTEM | Z5: Pag Ibig | AC5: AMOUNT PAID IN CASH (CR.A-1) | AD5: N U M B E R
G6: MONTLY RATE OF PAY | N6: CONSOL | O6: POLICY LOAN | P6: PHILHEALTH | R6: LIFE/RETIREMENT | X6: GLOBE | Y6: RBP | AE6: SIGNATURE OF PAYEE | AF6: REMARKS
F7: No. of days | P7: PERSONAL SHARE | Q7: GOV'T. SHARE | R7: INSURANCE PREMIUM | V7: CAL | W7: EDU. CHILD | AB7: STATE. INSURANCE
R8: PERSONAL SHARE | S8: GOVERNMENT SHARE | T8: OPTIONAL | U8: Educ
Z9: MPL | AA9: CALAMITY
A10: 1 | B10: 2 | C10: 3 | D10: 4 | E10: 5 | G10: 6 | H10: 7 | I10: 8 | J10: 9 | K10: 10 | L10: 11 | M10: 12 | N10: 13 | O10: 14 | P10: 15 | Q10: 16 | R10: 17 | S10: 18 | T10: 19 | U10: 20 | V10: 21 | W10: 22 | X10: 23 | Y10: 24 | Z10: 25 | AA10: 26 | AB10: 27 | AC10: 28 | AD10: 29 | AE10: 30 | AF10: 31
B12: 1022
A13: 1 | B13: MARVIN PINILI | C13: Admin Aide I | D13: Mar. 1-15, 2017 | F13: 11 | G13: =ROUND(7582/22,2) -> 344.64 | H13: =F13*G13 -> 3791.04 | I13: 0 | L13: 0 | N13: 0 | O13: 0 | P13: 100 | Q13: =P13 -> 100 | R13: 682.38 | S13: 909.84 | AB13: 75.82 | AC13: =H13-(SUM(I13:P13)+R13+SUM(T13:AA13)) -> 3008.66 | AD13: 1
B14: 1021
A15: 2 | B15: NOWEL LERON | C15: Admin Aide I | D15: -do- | F15: 11 | G15: =ROUND(7582/22,2) -> 344.64 | H15: =F15*G15 -> 3791.04 | I15: 0 | L15: 0 | N15: 0 | O15: 0 | P15: 100 | Q15: =P15 -> 100 | R15: 682.38 | S15: 909.84 | T15: 0 | U15: 0 | V15: 0 | Z15: 0 | AA15: 0 | AB15: 75.82 | AC15: =H15-(SUM(I15:P15)+R15+SUM(T15:AA15)) -> 3008.66 | AD15: 2
H24: =SUM(H13:H23) -> 7582.08 | P24: =SUM(P13:P23) -> 200 | Q24: =SUM(Q13:Q23) -> 200 | R24: =SUM(R13:R23) -> 1364.76 | S24: =SUM(S13:S23) -> 1819.68 | AC24: =SUM(AC13:AC23) -> 6017.32
AB27: (5) I HEREBY CERTIFY on my official oath that I have paid in cash to each official and employee whose name appears on the above roll the amount set opposite his name, under column 28, he having signed or marked his name under column 30 above, in my presence and at the time that payment was made to him, in acknowledgement of receipt of the money paid him.
A28: (1) I HEREBY CERTIFY on my official oath that the above PAYROLL is correct, and that services above stated have been duly rendered. Payment for such services is also hereby approved from the appropriation indicated. | I28: (4) APPROVED
J30: DR. PETER CASIUS M. TRINIDAD
J31: Municipal Vice Mayor
D32: DR. PETER CASIUS M. TRINIDAD | J32: Chief of Office
D33: Municipal Vice Mayor
A35: (2) APPROVED for payment subject to preaudit: | AB35: (6) I HEREBY CERTIFY on my official oath that each employee whose name appears on the above roll has been paid in cash or in check, and in no other mode, the amount shown under column 21 above, opposite his name. The total of the payments made by means this payroll amount to
E37: Treasurer
A38: (3) Preaudited and approved for payment in the month of
C39: (P ) | E39: pesos only. | AF39: Treasurer

Sheet CasualSb16-31
A1: Municipal P A Y R O L L
A2: WE HEREBY ACKNOWLEDGE TO HAVE RECEIVED FROM MINERVA L. BOONGALING, TREASURER OF PAGSANJAN, LAGUNA THE SUMS HEREIN SPECIFIED OPPOSITES OUR RESPECTIVE NAMES, THE SAME BEING FULL COMPENSATION FOR OUR SERVICES RENDERED DURING THE PERIOD STATED BELOW, TO THE CORRECTNESS OF WHICH WE HEREBY SEVERALLY
A4: NO. | B4: NAME | C4: DESIGNATION | D4: PERIOD OF SERVICE (INCLUSIVE DATES) | I4: AMOUNT ACCRUED FOR THE PERIOD | J4: D E D U C T I O N S
D5: FROM | E5: TO | J5: Withholding Tax | K5: SOS | L5: ESL | M5: EL | Z5: PAG-IBIG | AE5: GSIS | AF5: AMOUNT PAID IN CASH (CR.A-1) | AG5: N U M B E R
H6: MONTLY RATE OF PAY | O6: CONSOL | P6: POLICY LOAN | Q6: PAG-IBIG CONTRIBUTION | S6: LIFE/RETIREMENT | U6: Philhealth | AH6: SIGNATURE OF PAYEE | AI6: REMARKS
F7: No. of Days | G7: Adjustment | Q7: PERSONAL SHARE | R7: GOV'T. SHARE | S7: INSURANCE PREMIUM | Y7: EDUC | AD7: STATE. INSURANCE
S8: PERSONAL SHARE | T8: GOVERNMENT SHARE | U8: PERSONAL SHARE | V8: GOVERNMENT SHARE | W8: UOLI | AA8: CAL | AB8: MPL | AE8: STATE. INSURANCE
X9: Optional
A10: 1 | B10: 2 | C10: 3 | D10: 4 | E10: 5 | H10: 6 | I10: 7 | J10: 8 | K10: 9 | L10: 10 | M10: 9 | N10: 10 | O10: 11 | P10: 12 | Q10: 13 | R10: 14 | S10: 15 | T10: 17 | V10: 17 | W10: 18 | X10: 19 | Y10: 20 | Z10: 21 | AA10: 22 | AB10: 22 | AC10: 26 | AD10: 23 | AF10: 24 | AG10: 25 | AH10: 26 | AI10: 27
B11: 1016-1021-1022
A12: 1 | B12: JOWEL PALACOL | C12: Admin Aide I | D12: Mar. 16-31, 2017 | F12: 11 | G12: 1 | H12: =ROUND(7582/22,2) -> 344.64 | I12: =H12*12 -> 4135.68 | M12: 0 | P12: 0 | Q12: =ROUND(H12*22*0.02,2) -> 151.64 | R12: =Q12 -> 151.64 | W12: 0 | Y12: 0 | AF12: =I12-(SUM(J12:Q12)+S12+SUM(V12:AC12)) -> 3984.04
A13: 2 | B13: MARVIN P. PINILI | C13: Admin Aide I | D13: -do- | F13: 12 | G13: 1 | H13: =ROUND(7582/22,2) -> 344.64 | I13: =H13*13 -> 4480.32 | J13: 209.55 | M13: 0 | O13: 0 | P13: 0 | Q13: =ROUND(H13*22*0.02,2) -> 151.64 | R13: =Q13 -> 151.64 | S13: 0 | T13: 0 | W13: 0 | X13: 0 | Y13: 0 | AA13: 0 | AB13: 0 | AF13: =I13-(SUM(J13:Q13)+S13+SUM(V13:AC13)) -> 4119.13
A14: 3 | B14: NOWEL LERON | C14: Admin Aide I | D14: -do- | F14: 12 | G14: 1 | H14: =ROUND(7582/22,2) -> 344.64 | I14: =H14*13 -> 4480.32 | J14: 198.35 | M14: 0 | P14: 0 | Q14: =ROUND(H14*22*0.02,2) -> 151.64 | R14: =Q14 -> 151.64 | W14: 0 | Y14: 0 | AF14: =I14-(SUM(J14:Q14)+S14+SUM(V14:AC14)) -> 4130.33
I23: =SUM(I12:I22) -> 13096.32 | J23: =SUM(J12:J22) -> 407.9 | K23: =SUM(K12:K22) -> 0 | L23: =SUM(L12:L22) -> 0 | M23: =SUM(M12:M22) -> 0 | Q23: =SUM(Q12:Q22) -> 454.92 | R23: =SUM(R12:R22) -> 454.92 | S23: =SUM(S12:S22) -> 0 | T23: =SUM(T12:T22) -> 0 | U23: =SUM(U12:U22) -> 0 | V23: =SUM(V12:V22) -> 0 | W23: =SUM(W12:W22) -> 0 | X23: =SUM(X12:X22) -> 0 | AF23: =SUM(AF12:AF22) -> 12233.5
J25: APPROVED: | AD25: (5) I HEREBY CERTIFY on my official oath that I have paid in cash to each official and employee whose name appears on the above roll the amount set opposite his name, under column 22, he having signed or marked his name under column 24 above, in my presence and at the time that payment was made to him, in acknowledgement of receipt of the money paid him.
A26: (1) I HEREBY CERTIFY on my official oath that the above PAYROLL is correct, and that services above stated have been duly rendered. Payment for such services is also hereby approved from the appropriation indicated.
K28: DR. PETER CASIUS M. TRINIDAD
K29: Municipal Vice Mayor
D30: DR. PETER CASIUS M. TRINIDAD | K30: Chief of Office
D31: Municipal Vice Mayor
A33: (2) APPROVED for payment subject to preaudit:
AD34: (6) I HEREBY CERTIFY on my official oath that each employee whose name appears on the above roll has been paid in cash or in check, and in no other mode, the amount shown under column 22 above, opposite his name. The total of the payments made by means this payroll amount to
E35: Treasurer
A36: (3) Preaudited and approved for payment in the month of
C37: (P ) | E37: pesos only. | AI37: Treasurer

Sheet Casual 1-15
A1: Municipal P A Y R O L L
A2: WE HEREBY ACKNOWLEDGE TO HAVE RECEIVED FROM MINERVA L. BOONGALING, TREASURER OF PAGSANJAN, LAGUNA THE SUMS HEREIN SPECIFIED OPPOSITES OUR RESPECTIVE NAMES, THE SAME BEING FULL COMPENSATION FOR OUR SERVICES RENDERED DURING THE PERIOD STATED BELOW, TO THE CORRECTNESS OF WHICH WE HEREBY SEVERALLY
A4: NO. | B4: NAME | C4: DESIGNATION | D4: PERIOD OF SERVICE (INCLUSIVE DATES) | H4: AMOUNT ACCRUED FOR THE PERIOD | I4: D E D U C T I O N S
I5: HOUSING LOAN | J5: SOS | K5: ESL | L5: EL | N5: GOVERNMENT SERVICE INSURANCE SYSTEM | Z5: Pag Ibig | AC5: AMOUNT PAID IN CASH (CR.A-1) | AD5: N U M B E R
D6: FROM | E6: TO | G6: MONTLY RATE OF PAY | N6: CONSOL | O6: POLICY LOAN | P6: PHILHEALTH | R6: LIFE/RETIREMENT | X6: GLOBE | Y6: RBP | AE6: SIGNATURE OF PAYEE | AF6: REMARKS
F7: No. | P7: PERSONAL SHARE | Q7: GOV'T. SHARE | R7: INSURANCE PREMIUM | V7: CAL | W7: EDU. CHILD | AB7: STATE. INSURANCE
F8: of days | R8: PERSONAL SHARE | S8: GOVERNMENT SHARE | T8: OPTIONAL | U8: Educ
Z9: MPL | AA9: CALAMITY
A10: 1 | B10: 2 | C10: 3 | D10: 4 | E10: 5 | G10: 6 | H10: 7 | I10: 8 | J10: 9 | K10: 10 | L10: 11 | M10: 12 | N10: 13 | O10: 14 | P10: 15 | Q10: 16 | R10: 17 | S10: 18 | T10: 19 | U10: 20 | V10: 21 | W10: 22 | X10: 23 | Y10: 24 | Z10: 25 | AA10: 26 | AB10: 27 | AC10: 28 | AD10: 29 | AE10: 30 | AF10: 31
A11: 1 | B11: 1011 | AD11: 1
A12: 2 | B12: LORELIE G. LAZARO | C12: Admin Aide I | D12: Mar. 1-15, 2017 | F12: 11 | G12: =ROUND(7582/22,2) -> 344.64 | H12: =G12*F12 -> 3791.04 | L12: 327.78 | P12: 100 | Q12: =P12 -> 100 | R12: 682.38 | S12: 909.84 | T12: 346.57 | U12: 20 | AB12: 75.82 | AC12: =H12-(SUM(I12:P12)+R12+SUM(T12:AA12)) -> 2314.31 | AD12: 2
A13: 3 | B13: MICHAEL FRANCIS PAILAN | C13: Admin Aide I | D13: -do- | F13: 12 | G13: =ROUND(7582/22,2) -> 344.64 | H13: =G13*F13 -> 4135.68 | I13: 0 | L13: 327.78 | N13: 0 | O13: 0 | P13: 100 | Q13: =P13 -> 100 | R13: 682.38 | S13: 909.84 | T13: 0 | U13: 0 | V13: 0 | Z13: 141.89 | AA13: 0 | AB13: 75.82 | AC13: =H13-(SUM(I13:P13)+R13+SUM(T13:AA13)) -> 2883.63 | AD13: 3
A14: 4 | B14: DANIEL BUNGABONG | C14: Admin Aide I | D14: -do- | F14: 11 | G14: =ROUND(7582/22,2) -> 344.64 | H14: =G14*F14 -> 3791.04 | I14: 0 | L14: 0 | O14: 0 | P14: 100 | Q14: =P14 -> 100 | R14: 682.38 | S14: 909.84 | T14: 0 | U14: 0 | V14: 0 | Z14: 0 | AA14: 0 | AB14: 75.82 | AC14: =H14-(SUM(I14:P14)+R14+SUM(T14:AA14)) -> 3008.66 | AD14: 4
A15: 5 | B15: JUVY GRACE DB ABARQUEZ | C15: Admin Aide I | D15: -do- | F15: 11 | G15: =ROUND(7582/22,2) -> 344.64 | H15: =G15*F15 -> 3791.04 | I15: 0 | L15: 0 | O15: 0 | P15: 100 | Q15: =P15 -> 100 | R15: 682.38 | S15: 909.84 | T15: 0 | U15: 0 | V15: 0 | Z15: 458.37 | AB15: 75.82 | AC15: =H15-(SUM(I15:P15)+R15+SUM(T15:AA15)) -> 2550.29 | AD15: 5
A16: 6 | B16: JOEMAR B. PANTONIA | C16: Admin Aide I | D16: -do- | F16: 11 | G16: =ROUND(7582/22,2) -> 344.64 | H16: =G16*F16 -> 3791.04 | I16: 0 | L16: 0 | O16: 0 | P16: 100 | Q16: =P16 -> 100 | R16: 682.38 | S16: 909.84 | T16: 0 | U16: 0 | V16: 0 | AB16: 75.82 | AC16: =H16-(SUM(I16:P16)+R16+SUM(T16:AA16)) -> 3008.66 | AD16: 6
A17: 7 | H17: =SUM(H12:H16) -> 19299.84 | I17: =SUM(I12:I16) -> 0 | J17: =SUM(J12:J16) -> 0 | K17: =SUM(K12:K16) -> 0 | L17: =SUM(L12:L16) -> 655.56 | M17: =SUM(M12:M16) -> 0 | N17: =SUM(N12:N16) -> 0 | O17: =SUM(O12:O16) -> 0 | ... AC17: =SUM(AC12:AC16) -> 13765.55 | AD17: 7
A18: 8 | B18: 1031 | AD18: 8
A19: 9 | B19: MELAROSE PABILONIA | C19: Admin Aide I | D19: -do- | F19: 11 | G19: =ROUND(7582/22,2) -> 344.64 | H19: =G19*F19 -> 3791.04 | I19: 0 | L19: 0 | N19: 678.06 | O19: 100 | P19: 100 | Q19: =P19 -> 100 | R19: 682.38 | S19: 909.84 | T19: 0 | U19: 0 | V19: 0 | Z19: 209.1 | AA19: 0 | AB19: 75.82 | AC19: =H19-(SUM(I19:P19)+R19+SUM(T19:AA19)) -> 2021.5 | AD19: 9
A20: 10 | H20: =SUM(H19:H19) -> 3791.04 | I20: =SUM(I19:I19) -> 0 | J20: =SUM(J19:J19) -> 0 | K20: =SUM(K19:K19) -> 0 | L20: =SUM(L19:L19) -> 0 | M20: =SUM(M19:M19) -> 0 | N20: =SUM(N19:N19) -> 678.06 | O20: =SUM(O19:O19) -> 100 | ... AC20: =SUM(AC19:AC19) -> 2021.5 | AD20: 10
A21: 11 | B21: 1032 | AD21: 11
A22: 12 | B22: KEVIN MAR MORENO | C22: Admin Aide I | D22: -do- | F22: 11 | G22: =ROUND(7582/22,2) -> 344.64 | H22: =G22*F22 -> 3791.04 | I22: 0 | L22: 0 | N22: 0 | O22: 0 | P22: 100 | Q22: =P22 -> 100 | R22: 682.38 | S22: 909.84 | T22: 0 | U22: 0 | V22: 0 | AB22: 75.82 | AC22: =H22-(SUM(I22:P22)+R22+SUM(T22:AA22)) -> 3008.66 | AD22: 12
A23: 13 | H23: =H22 -> 3791.04 | I23: =I22 -> 0 | J23: =J22 -> 0 | K23: =K22 -> 0 | L23: =L22 -> 0 | M23: =M22 -> 0 | N23: =N22 -> 0 | O23: =O22 -> 0 | ... AC23: =AC22 -> 3008.66 | AD23: 13
A24: 14 | B24: 1071 | AD24: 14
A25: 15 | B25: MICHELLE CASTILLO | C25: Admin Aide I | D25: -do- | F25: 11 | G25: =ROUND(7582/22,2) -> 344.64 | H25: =G25*F25 -> 3791.04 | I25: 0 | P25: 100 | Q25: =P25 -> 100 | R25: 682.38 | S25: 909.84 | Z25: 1493.06 | AB25: 75.82 | AC25: =H25-(SUM(I25:P25)+R25+SUM(T25:AA25)) -> 1515.6 | AD25: 15
A26: 16 | B26: ALVIN VILLANUEVA | C26: Admin Aide I | D26: -do- | F26: 11 | G26: =ROUND(7582/22,2) -> 344.64 | H26: =G26*F26 -> 3791.04 | I26: 0 | L26: 0 | N26: 0 | O26: 0 | P26: 100 | Q26: =P26 -> 100 | R26: 682.38 | S26: 909.84 | T26: 0 | U26: 0 | V26: 0 | AB26: 75.82 | AC26: =H26-(SUM(I26:P26)+R26+SUM(T26:AA26)) -> 3008.66 | AD26: 16
A27: 17 | H27: =SUM(H25:H26) -> 7582.08 | I27: =SUM(I25:I26) -> 0 | J27: =SUM(J25:J26) -> 0 | K27: =SUM(K25:K26) -> 0 | L27: =SUM(L25:L26) -> 0 | M27: =SUM(M25:M26) -> 0 | N27: =SUM(N25:N26) -> 0 | O27: =SUM(O25:O26) -> 0 | ... AC27: =SUM(AC25:AC26) -> 4524.26 | AD27: 17
A28: 18 | B28: 1081 | AD28: 18
A29: 19 | B29: JOANA PATRIZHA MERAMBEL | C29: Admin Aide I | D29: -do- | F29: 11 | G29: =ROUND(7582/22,2) -> 344.64 | H29: =G29*F29 -> 3791.04 | I29: 0 | L29: 327.78 | P29: 100 | Q29: =P29 -> 100 | R29: 682.38 | S29: 909.84 | T29: 0 | U29: 20 | V29: 0 | AB29: 75.82 | AC29: =H29-(SUM(I29:P29)+R29+SUM(T29:AA29)) -> 2660.88 | AD29: 19
A30: 20 | B30: FELVIC Z. QUIZON | C30: Admin Aide I | D30: -do- | F30: 11 | G30: =ROUND(7582/22,2) -> 344.64 | H30: =G30*F30 -> 3791.04 | I30: 0 | P30: 100 | Q30: 100 | R30: 682.38 | S30: 909.84 | T30: 0 | U30: 0 | V30: 0 | Z30: 0 | AA30: 0 | AB30: 75.82 | AC30: =H30-(SUM(I30:P30)+R30+SUM(T30:AA30)) -> 3008.66 | AD30: 20
A31: 21 | B31: TAMMY O. BENELADA | C31: Admin Aide I | D31: -do- | F31: 11 | G31: =ROUND(7582/22,2) -> 344.64 | H31: =G31*F31 -> 3791.04 | P31: 100 | Q31: 100 | R31: 682.38 | S31: 909.84 | AB31: 75.82 | AC31: =H31-(SUM(I31:P31)+R31+SUM(T31:AA31)) -> 3008.66 | AD31: 21
A32: 22 | B32: RIZALINO DE CASTRO | C32: Admin Aide I | D32: -do- | F32: 11 | G32: =ROUND(7582/22,2) -> 344.64 | H32: =G32*F32 -> 3791.04 | I32: 0 | L32: 0 | N32: 0 | O32: 0 | P32: 100 | Q32: =P32 -> 100 | R32: 682.38 | S32: 909.84 | AB32: 75.82 | AC32: =H32-(SUM(I32:P32)+R32+SUM(T32:AA32)) -> 3008.66 | AD32: 22
A33: 23 | B33: FRENZIE GARANTUZA | C33: Admin Aide I | D33: -do- | F33: 11 | G33: =ROUND(7582/22,2) -> 344.64 | H33: =G33*F33 -> 3791.04 | I33: 0 | L33: 0 | N33: 0 | O33: 0 | P33: 100 | Q33: =P33 -> 100 | R33: 682.38 | S33: 909.84 | AB33: 75.82 | AC33: =H33-(SUM(I33:P33)+R33+SUM(T33:AA33)) -> 3008.66 | AD33: 23
A34: 24 | H34: =SUM(H29:H33) -> 18955.2 | I34: =SUM(I29:I33) -> 0 | J34: =SUM(J29:J33) -> 0 | K34: =SUM(K29:K33) -> 0 | L34: =SUM(L29:L33) -> 327.78 | M34: =SUM(M29:M33) -> 0 | N34: =SUM(N29:N33) -> 0 | O34: =SUM(O29:O33) -> 0 | ... AC34: =SUM(AC29:AC33) -> 14695.52 | AD34: 24
A35: 25 | B35: 1091 | AD35: 25
A36: 26 | B36: JACQUILOU DIMARANAN | C36: Admin Aide I | D36: -do- | F36: 11 | G36: =ROUND(7582/22,2) -> 344.64 | H36: =G36*F36 -> 3791.04 | I36: 0 | L36: 327.78 | N36: 0 | O36: 0 | P36: 100 | Q36: =P36 -> 100 | R36: 682.38 | S36: 909.84 | T36: 0 | U36: 0 | V36: 0 | Z36: 0 | AB36: 75.82 | AC36: =H36-(SUM(I36:P36)+R36+SUM(T36:AA36)) -> 2680.88 | AD36: 26
A37: 27 | B37: NIÑO LAGRIMAS | C37: Admin Aide I | D37: -do- | F37: 11 | G37: =ROUND(7582/22,2) -> 344.64 | H37: =G37*F37 -> 3791.04 | I37: 0 | N37: 678.06 | P37: 100 | Q37: =P37 -> 100 | R37: 682.38 | S37: 909.84 | T37: 0 | U37: 0 | V37: 0 | Z37: 192.8 | AA37: 0 | AB37: 75.82 | AC37: =H37-(SUM(I37:P37)+R37+SUM(T37:AA37)) -> 2137.8 | AD37: 27
A38: 28 | B38: CHRISTIAN ABRANTES | C38: Admin Aide I | D38: -do- | F38: 11 | G38: =ROUND(7582/22,2) -> 344.64 | H38: =G38*F38 -> 3791.04 | I38: 0 | O38: 0 | P38: 100 | Q38: =P38 -> 100 | R38: 682.38 | S38: 909.84 | T38: 0 | U38: 0 | V38: 0 | AA38: 0 | AB38: 75.82 | AC38: =H38-(SUM(I38:P38)+R38+SUM(T38:AA38)) -> 3008.66 | AD38: 28
A39: 29 | B39: ARLENE JAVIER | C39: Admin Aide I | D39: -do- | F39: 11 | G39: =ROUND(7582/22,2) -> 344.64 | H39: =G39*F39 -> 3791.04 | I39: 0 | N39: 508.54 | O39: 0 | P39: 100 | Q39: =P39 -> 100 | R39: 682.38 | S39: 909.84 | T39: 0 | U39: 0 | V39: 0 | Z39: 0 | AA39: 0 | AB39: 75.82 | AC39: =H39-(SUM(I39:P39)+R39+SUM(T39:AA39)) -> 2500.12 | AD39: 29
A40: 30 | B40: FLORANTE JOSE | C40: Admin Aide I | D40: -do- | F40: 11 | G40: =ROUND(7582/22,2) -> 344.64 | H40: =G40*F40 -> 3791.04 | I40: 0 | O40: 0 | P40: 100 | Q40: =P40 -> 100 | R40: 682.38 | S40: 909.84 | T40: 0 | U40: 0 | V40: 0 | Z40: 0 | AA40: 0 | AB40: 75.82 | AC40: =H40-(SUM(I40:P40)+R40+SUM(T40:AA40)) -> 3008.66 | AD40: 30
A41: 31 | H41: =SUM(H36:H40) -> 18955.2 | I41: =SUM(I36:I40) -> 0 | J41: =SUM(J36:J40) -> 0 | K41: =SUM(K36:K40) -> 0 | L41: =SUM(L36:L40) -> 327.78 | M41: =SUM(M36:M40) -> 0 | N41: =SUM(N36:N40) -> 1186.6 | O41: =SUM(O36:O40) -> 0 | ... AC41: =SUM(AC36:AC40) -> 13336.12 | AD41: 31
A42: 32 | B42: 1101 | AD42: 32
A43: 33 | B43: ARLENE RIVERA | C43: Admin Aide I | D43: -do- | F43: 11 | G43: =ROUND(7582/22,2) -> 344.64 | H43: =G43*F43 -> 3791.04 | I43: 0 | L43: 0 | O43: 100 | P43: 100 | Q43: =P43 -> 100 | R43: 682.38 | S43: 909.84 | T43: 0 | U43: 20 | V43: 0 | Z43: 0 | AA43: 0 | AB43: 75.82 | AC43: =H43-(SUM(I43:P43)+R43+SUM(T43:AA43)) -> 2888.66 | AD43: 33
A44: 34 | B44: GELSON SAMPANG | C44: Admin Aide I | D44: -do- | F44: 11 | G44: =ROUND(7582/22,2) -> 344.64 | H44: =G44*F44 -> 3791.04 | I44: 0 | N44: 0 | O44: 0 | P44: 100 | Q44: =P44 -> 100 | R44: 682.38 | S44: 909.84 | T44: 0 | U44: 0 | V44: 0 | Z44: 0 | AA44: 0 | AB44: 75.82 | AC44: =H44-(SUM(I44:P44)+R44+SUM(T44:AA44)) -> 3008.66 | AD44: 34
A45: 35 | H45: =SUM(H43:H44) -> 7582.08 | I45: =SUM(I42:I44) -> 0 | J45: =SUM(J42:J44) -> 0 | K45: =SUM(K42:K44) -> 0 | L45: =SUM(L42:L44) -> 0 | M45: =SUM(M42:M44) -> 0 | N45: =SUM(N42:N44) -> 0 | O45: =SUM(O42:O44) -> 100 | P45: =SUM(P42:P44) -> 200 | ... AB45: =SUM(AB42:AB44) -> 151.64 | AC45: =SUM(AC43:AC44) -> 5897.32 | AD45: 35
A46: 36 | AD46: 36
A47: 37 | B47: 6531 | AD47: 37
A48: 38 | B48: RONALD FULLEROS | C48: Admin Aide I | D48: -do- | F48: 11 | G48: =ROUND(7582/22,2) -> 344.64 | H48: =G48*F48 -> 3791.04 | I48: 0 | N48: 1186.6 | O48: 0 | P48: 100 | Q48: =P48 -> 100 | R48: 682.38 | S48: 909.84 | T48: 0 | U48: 0 | V48: 0 | Z48: 373.34 | AA48: 0 | AB48: 75.82 | AC48: =H48-(SUM(I48:P48)+R48+SUM(T48:AA48)) -> 1448.72 | AD48: 38
A49: 39 | H49: =H48 -> 3791.04 | I49: 0 | J49: =J48 -> 0 | K49: =K48 -> 0 | L49: =L48 -> 0 | M49: =M48 -> 0 | N49: =N48 -> 1186.6 | O49: =O48 -> 0 | P49: =P48 -> 100 | Q49: =Q48 -> 100 | ... S49: =S48 -> 909.84 | T49: 0 | U49: =U48 -> 0 | V49: =V48 -> 0 | W49: 0 | X49: =X48 -> 0 | Y49: 0 | Z49: =Z48 -> 373.34 | AA49: 0 | AB49: =AB48 -> 75.82 | AC49: =AC48 -> 1448.72 | AD49: 39
A50: 40 | B50: 7611 | AD50: 40
A51: 41 | B51: RUTH GRACE WALO | C51: Admin Aide I | D51: -do- | F51: 11 | G51: =ROUND(7582/22,2) -> 344.64 | H51: =G51*F51 -> 3791.04 | I51: 0 | J51: 0 | K51: 0 | L51: 0 | N51: 0 | O51: 0 | P51: 100 | Q51: =P51 -> 100 | R51: 682.38 | S51: 909.84 | T51: 0 | U51: 0 | V51: 0 | Z51: 0 | AA51: 0 | AB51: 75.82 | AC51: =H51-(SUM(I51:P51)+R51+SUM(T51:AA51)) -> 3008.66 | AD51: 41
A52: 42 | B52: ARGELYN DAVAC | C52: Admin Aide I | D52: -do- | F52: 11 | G52: =ROUND(7582/22,2) -> 344.64 | H52: =G52*F52 -> 3791.04 | I52: 0 | J52: 0 | K52: 0 | L52: 0 | N52: 0 | O52: 0 | P52: 100 | Q52: =P52 -> 100 | R52: 682.38 | S52: 909.84 | T52: 0 | U52: 0 | V52: 0 | Z52: 0 | AA52: 0 | AB52: 75.82 | AC52: =H52-(SUM(I52:P52)+R52+SUM(T52:AA52)) -> 3008.66 | AD52: 42
A53: 43 | H53: =SUM(H51:H52) -> 7582.08 | I53: =SUM(I51:I52) -> 0 | J53: =SUM(J51:J52) -> 0 | K53: =SUM(K51:K52) -> 0 | L53: =SUM(L51:L52) -> 0 | M53: =SUM(M51:M52) -> 0 | N53: =SUM(N51:N52) -> 0 | O53: =SUM(O51:O52) -> 0 | ... AC53: =SUM(AC51:AC52) -> 6017.32 | AD53: 43
A54: 44 | B54: 8711 | AD54: 44
A55: 45 | B55: JOSEPH WARREN COLADILLA | C55: Admin Aide I | D55: -do- | F55: 11 | G55: =ROUND(7582/22,2) -> 344.64 | H55: =G55*F55 -> 3791.04 | L55: 0 | N55: 0 | O55: 0 | P55: 100 | Q55: =P55 -> 100 | R55: 682.38 | S55: 909.84 | T55: 0 | U55: 0 | V55: 0 | Z55: 0 | AA55: 0 | AB55: 75.82 | AC55: =H55-(SUM(I55:P55)+R55+SUM(T55:AA55)) -> 3008.66 | AD55: 45
A56: 46 | B56: LANIE VILLA | C56: Admin Aide I | D56: -do- | F56: 11 | G56: =ROUND(7582/22,2) -> 344.64 | H56: =G56*F56 -> 3791.04 | L56: 327.78 | N56: 0 | O56: 0 | P56: 100 | Q56: =P56 -> 100 | R56: 682.38 | S56: 909.84 | T56: 0 | U56: 0 | V56: 0 | Z56: 0 | AA56: 0 | AB56: 75.82 | AC56: =H56-(SUM(I56:P56)+R56+SUM(T56:AA56)) -> 2680.88 | AD56: 46
A57: 47 | H57: =SUM(H55:H56) -> 7582.08 | I57: =SUM(I55:I56) -> 0 | J57: =SUM(J55:J56) -> 0 | K57: =SUM(K55:K56) -> 0 | L57: =SUM(L55:L56) -> 327.78 | M57: =SUM(M55:M56) -> 0 | N57: =SUM(N55:N56) -> 0 | O57: =SUM(O55:O56) -> 0 | ... AC57: =SUM(AC55:AC56) -> 5689.54 | AD57: 47
A58: 48 | B58: 9940 | AD58: 48
A59: 49 | B59: JAYRALD CABREGA | C59: Admin Aide I | D59: -do- | F59: 12 | G59: =ROUND(7582/22,2) -> 344.64 | H59: =G59*F59 -> 4135.68 | I59: 0 | O59: 0 | P59: 100 | Q59: =P59 -> 100 | R59: 682.38 | S59: 909.84 | T59: 0 | U59: 0 | V59: 0 | Z59: 364.91 | AA59: 0 | AB59: 75.82 | AC59: =H59-(SUM(I59:P59)+R59+SUM(T59:AA59)) -> 2988.39 | AD59: 49
A60: 50 | H60: =H59 -> 4135.68 | N60: =N59 -> 0 | P60: =P59 -> 100 | Q60: =Q59 -> 100 | R60: =R59 -> 682.38 | S60: =S59 -> 909.84 | Z60: =Z59 -> 364.91 | AA60: =AA59 -> 0 | AB60: =AB59 -> 75.82 | AC60: =AC59 -> 2988.39 | AD60: 50
A61: 51 | B61: 8731 | AD61: 51
A62: 52 | B62: KELVIN ABAQUIN | C62: Admin Aide I | D62: -do- | F62: 13 | G62: =ROUND(7582/22,2) -> 344.64 | H62: =G62*F62 -> 4480.32 | I62: 0 | O62: 0 | P62: 100 | Q62: =P62 -> 100 | R62: 682.38 | S62: 909.84 | T62: 0 | U62: 0 | V62: 0 | Z62: 364.91 | AA62: 0 | AB62: 75.82 | AC62: =H62-(SUM(I62:P62)+R62+SUM(T62:AA62)) -> 3333.03 | AD62: 52
A63: 53 | H63: =H62 -> 4480.32 | I63: =I62 -> 0 | J63: =J62 -> 0 | K63: =K62 -> 0 | L63: =L62 -> 0 | M63: =M62 | N63: =N62 -> 0 | O63: =O62 -> 0 | ... AC63: =AC62 -> 3333.03 | AD63: 53
A64: 54 | B64: 8751 | AD64: 54
A65: 55 | B65: MARK JOSEPH BALOTA | C65: Admin Aide I | D65: -do- | F65: 11 | G65: =ROUND(7582/22,2) -> 344.64 | H65: =G65*F65 -> 3791.04 | I65: 0 | L65: 0 | N65: 0 | O65: 0 | P65: 100 | Q65: =P65 -> 100 | R65: 682.38 | S65: 909.84 | T65: 0 | U65: 0 | V65: 0 | Z65: 0 | AA65: 0 | AB65: 75.82 | AC65: =H65-(SUM(I65:P65)+R65+SUM(T65:AA65)) -> 3008.66 | AD65: 55
A66: 56 | B66: MARLON PAMATMAT | C66: Admin Aide I | D66: -do- | F66: 11 | G66: =ROUND(7582/22,2) -> 344.64 | H66: =G66*F66 -> 3791.04 | I66: 0 | L66: 0 | N66: 0 | O66: 0 | P66: 100 | Q66: =P66 -> 100 | R66: 682.37 | S66: 909.84 | T66: 0 | U66: 0 | V66: 0 | Z66: 0 | AA66: 0 | AB66: 75.82 | AC66: =H66-(SUM(I66:P66)+R66+SUM(T66:AA66)) -> 3008.67 | AD66: 56
A67: 57 | H67: =SUM(H65:H66) -> 7582.08 | I67: =SUM(I66:I66) -> 0 | J67: =SUM(J66:J66) -> 0 | K67: =SUM(K66:K66) -> 0 | L67: =SUM(L66:L66) -> 0 | M67: =SUM(M66:M66) -> 0 | N67: =SUM(N66:N66) -> 0 | O67: =SUM(O66:O66) -> 0 | P67: =SUM(P65:P66) -> 200 | Q67: =SUM(Q65:Q66) -> 200 | R67: =SUM(R65:R66) -> 1364.75 | S67: =SUM(S65:S66) -> 1819.68 | T67: =SUM(T65:T66) -> 0 | U67: =SUM(U65:U66) -> 0 | V67: =SUM(V65:V66) -> 0 | W67: =SUM(W65:W66) -> 0 | ... AC67: =SUM(AC65:AC66) -> 6017.33 | AD67: 57
A68: 58 | B68: 8841 | AD68: 58
A69: 59 | B69: FRANCISCO TOBIAS | C69: Admin Aide I | D69: -do- | F69: 11 | G69: =ROUND(7582/22,2) -> 344.64 | H69: =G69*F69 -> 3791.04 | I69: 0 | N69: 1220.49 | P69: 100 | Q69: =P69 -> 100 | R69: 682.37 | S69: 909.84 | T69: 0 | U69: 20 | V69: 0 | AB69: 75.82 | AC69: =H69-(SUM(I69:P69)+R69+SUM(T69:AA69)) -> 1768.18 | AD69: 59
A70: 60 | H70: =SUM(H69) -> 3791.04 | I70: =SUM(I69) -> 0 | J70: =SUM(J69) -> 0 | K70: =SUM(K69) -> 0 | L70: =SUM(L69) -> 0 | M70: =SUM(M69) -> 0 | N70: =SUM(N69) -> 1220.49 | O70: =SUM(O69) -> 0 | ... AC70: =SUM(AC69) -> 1768.18 | AD70: 60
A71: 61 | B71: 8852 | AD71: 61
A72: 62 | B72: JAY- ARR MANALO | C72: Admin Aide I | D72: -do- | F72: 11 | G72: =ROUND(7582/22,2) -> 344.64 | H72: =G72*F72 -> 3791.04 | I72: 0 | N72: 0 | P72: 100 | Q72: =P72 -> 100 | R72: 682.37 | S72: 909.84 | T72: 0 | V72: 0 | AA72: 0 | AB72: 75.82 | AC72: =H72-(SUM(I72:P72)+R72+SUM(T72:AA72)) -> 3008.67 | AD72: 62
A73: 63 | B73: REGIE MANALO | C73: Admin Aide I | D73: -do- | F73: 11 | G73: =ROUND(7582/22,2) -> 344.64 | H73: =G73*F73 -> 3791.04 | I73: 0 | L73: 0 | N73: 0 | O73: 0 | P73: 100 | Q73: =P73 -> 100 | R73: 682.37 | S73: 909.84 | T73: 0 | U73: 0 | V73: 0 | Z73: 0 | AA73: 0 | AB73: 75.82 | AC73: =H73-(SUM(I73:P73)+R73+SUM(T73:AA73)) -> 3008.67 | AD73: 63
A74: 64 | H74: =SUM(H72:H73) -> 7582.08 | I74: =SUM(I72:I73) -> 0 | J74: =SUM(J72:J73) -> 0 | K74: =SUM(K72:K73) -> 0 | L74: =SUM(L72:L73) -> 0 | M74: =SUM(M72:M73) -> 0 | N74: =SUM(N72:N73) -> 0 | O74: =SUM(O72:O73) -> 0 | ... AC74: =SUM(AC72:AC73) -> 6017.34 | AD74: 64
A75: 65 | H75: =H74+H70+H67+H63+H60+H57+H53+H49+H45+H41+H34+H27+H23+H20+H17 -> 126482.88 | I75: =I74+I70+I67+I63+I60+I57+I53+I49+I45+I41+I34+I27+I23+I20+I17 -> 0 | J75: =J74+J70+J67+J63+J60+J57+J53+J49+J45+J41+J34+J27+J23+J20+J17 -> 0 | K75: =K74+K70+K67+K63+K60+K57+K53+K49+K45+K41+K34+K27+K23+K20+K17 -> 0 | L75: =L74+L70+L67+L63+L60+L57+L53+L49+L45+L41+L34+L27+L23+L20+L17 -> 1638.9 | M75: =M74+M70+M67+M63+M60+M57+M53+M49+M45+M41+M34+M27+M23+M20+M17 -> #VALUE! | N75: =N74+N70+N67+N63+N60+N57+N53+N49+N45+N41+N34+N27+N23+N20+N17 -> 4271.75 | O75: =O74+O70+O67+O63+O60+O57+O53+O49+O45+O41+O34+O27+O23+O20+O17 -> 200 | ... AC75: =AC74+AC70+AC67+AC63+AC60+AC57+AC53+AC49+AC45+AC41+AC34+AC27+AC23+AC20+AC17 -> 90528.78 | AD75: 65
AB77: (5) I HEREBY CERTIFY on my official oath that I have paid in cash to each official and employee whose name appears on the above roll the amount set opposite his name, under column 28, he having signed or marked his name under column 30 above, in my presence and at the time that payment was made to him, in acknowledgement of receipt of the money paid him.
A78: (1) I HEREBY CERTIFY on my official oath that the above PAYROLL is correct, and that services above stated have been duly rendered. Payment for such services is also hereby approved from the appropriation indicated. | I78: (4) APPROVED
J80: GIRLIE JAVIER EJERCITO
J81: Municipal Mayor
D82: GIRLIE JAVIER EJERCITO | J82: Chief of Office
D83: Municipal Mayor | AB83: (6) I HEREBY CERTIFY on my official oath that each employee whose name appears on the above roll has been paid in cash or in check, and in no other mode, the amount shown under column 21 above, opposite his name. The total of the payments made by means this payroll amount to
A85: (2) APPROVED for payment subject to preaudit:
E86: Treasurer
A88: (3) Preaudited and approved for payment in the month of | AF88: Treasurer
C89: (P ) | E89: pesos only.

Sheet Casual 16-31
A1: Municipal P A Y R O L L
A2: WE HEREBY ACKNOWLEDGE TO HAVE RECEIVED FROM MINERVA L. BOONGALING, TREASURER OF PAGSANJAN, LAGUNA THE SUMS HEREIN SPECIFIED OPPOSITES OUR RESPECTIVE NAMES, THE SAME BEING FULL COMPENSATION FOR OUR SERVICES RENDERED DURING THE PERIOD STATED BELOW, TO THE CORRECTNESS OF WHICH WE HEREBY SEVERALLY
A4: NO. | B4: NAME | C4: DESIGNATION | D4: PERIOD OF SERVICE (INCLUSIVE DATES) | H4: AMOUNT ACCRUED FOR THE PERIOD | I4: D E D U C T I O N S
D5: FROM | E5: TO | I5: Withholding Tax | J5: SOS | K5: ESL | L5: EL | N5: GOVERNMENT SERVICE INSURANCE SYSTEM | AA5: PAG-IBIG | AE5: GSIS | AF5: AMOUNT PAID IN CASH (CR.A-1) | AG5: N U M B E R
G6: MONTLY RATE OF PAY | N6: CONSOL | O6: POLICY LOAN | R6: PAG-IBIG CONTRIBUTION | T6: LIFE/RETIREMENT | AH6: SIGNATURE OF PAYEE | AI6: REMARKS
R7: PERSONAL SHARE | S7: GOV'T. SHARE | T7: INSURANCE PREMIUM | Z7: EDUC
P8: GSIS contribution | T8: PERSONAL SHARE | U8: GOVERNMENT SHARE | V8: Philhleath Cont | X8: UOLI | AB8: CAL | AC8: MPL | AE8: STATE. INSURANCE
P9: PS | Q9: GS | V9: PS | W9: GS | Y9: Optional
A10: 1 | B10: 2 | C10: 3 | D10: 4 | E10: 5 | G10: 6 | H10: 7 | I10: 8 | J10: 9 | K10: 10 | L10: 9 | M10: 10 | N10: 11 | O10: 12 | R10: 13 | S10: 14 | T10: 15 | U10: 17 | X10: 18 | Y10: 19 | Z10: 20 | AA10: 21 | AB10: 22 | AC10: 22 | AD10: 26 | AF10: 24 | AG10: 25 | AH10: 26 | AI10: 27
A11: 1 | B11: 1011 | AG11: 1
A12: 2 | B12: LORELIE G. LAZARO | C12: Admin Aide I | D12: Jan. 16-31, 2017 | F12: 12 | G12: =ROUND(7582/22,2) -> 344.64 | H12: =G12*F12 -> 4135.68 | L12: 327.78 | O12: 800 | R12: =ROUND(G12*22*0.02,2) -> 151.64 | S12: =R12 -> 151.64 | X12: 157.74 | Y12: 346.56 | Z12: 20 | AC12: 0 | AF12: =H12-(SUM(I12:R12)+T12+SUM(V12:AD12)) -> 2331.96 | AG12: 2 | AK12: for deduction Oct. 16-30, 2016 PL Reg. 800
A13: 3 | B13: MICHAEL FRANCIS PAILAN | C13: Admin Aide I | D13: -do- | F13: 11 | G13: =ROUND(7582/22,2) -> 344.64 | H13: =G13*F13 -> 3791.04 | I13: 209.55 | L13: 327.78 | O13: 0 | R13: =ROUND(G13*22*0.02,2) -> 151.64 | S13: =R13 -> 151.64 | X13: 0 | Z13: 0 | AB13: 0 | AC13: 141.88 | AF13: =H13-(SUM(I13:R13)+T13+SUM(V13:AD13)) -> 2960.19 | AG13: 3
A14: 4 | B14: DANIEL BUNGABONG | C14: Admin Aide I | D14: -do- | F14: 12 | G14: =ROUND(7582/22,2) -> 344.64 | H14: =G14*F14 -> 4135.68 | I14: 209.55 | L14: 0 | N14: 508.55 | O14: 0 | R14: =ROUND(G14*22*0.02,2) -> 151.64 | S14: =R14 -> 151.64 | X14: 0 | Z14: 0 | AB14: 0 | AC14: 0 | AF14: =H14-(SUM(I14:R14)+T14+SUM(V14:AD14)) -> 3265.94 | AG14: 4
A15: 5 | B15: JUVY GRACE ABARQUEZ | C15: Admin Aide I | D15: -do- | F15: 11 | G15: =ROUND(7582/22,2) -> 344.64 | H15: =G15*F15 -> 3791.04 | L15: 0 | N15: 508.55 | O15: 0 | R15: =ROUND(G15*22*0.02,2) -> 151.64 | S15: =R15 -> 151.64 | X15: 0 | Z15: 0 | AC15: 458.37 | AF15: =H15-(SUM(I15:R15)+T15+SUM(V15:AD15)) -> 2672.48 | AG15: 5
A16: 6 | H16: =SUM(H12:H15) -> 15853.44 | I16: =SUM(I12:I15) -> 419.1 | J16: =SUM(J12:J15) -> 0 | K16: =SUM(K12:K15) -> 0 | L16: =SUM(L12:L15) -> 655.56 | M16: =SUM(M12:M15) -> 0 | N16: =SUM(N12:N15) -> 1017.1 | O16: =SUM(O12:O15) -> 800 | R16: =SUM(R12:R15) -> 606.56 | S16: =SUM(S12:S15) -> 606.56 | T16: =SUM(T12:T15) -> 0 | U16: =SUM(U12:U15) -> 0 | X16: =SUM(X12:X15) -> 157.74 | Y16: =SUM(Y12:Y15) -> 346.56 | Z16: =SUM(Z12:Z15) -> 20 | AA16: =SUM(AA12:AA15) -> 0 | AB16: =SUM(AB12:AB15) -> 0 | AC16: =SUM(AC12:AC15) -> 600.25 | AD16: =SUM(AD12:AD15) -> 0 | AE16: =SUM(AE12:AE15) -> 0 | AF16: =SUM(AF12:AF15) -> 11230.57 | AG16: 6
A17: 7 | B17: 1031 | AG17: 7
A18: 8 | B18: MELAROSE PABILONIA | C18: Admin Aide I | D18: -do- | F18: 11 | G18: =ROUND(7582/22,2) -> 344.64 | H18: =G18*F18 -> 3791.04 | I18: 0 | L18: 0 | O18: 0 | R18: =ROUND(G18*22*0.02,2) -> 151.64 | S18: =R18 -> 151.64 | T18: 0 | U18: 0 | X18: 0 | Y18: 0 | Z18: 0 | AB18: 0 | AC18: 209.09 | AF18: =H18-(SUM(I18:R18)+T18+SUM(V18:AD18)) -> 3430.31 | AG18: 8
A19: 9 | H19: =SUM(H18:H18) -> 3791.04 | I19: =SUM(I18:I18) -> 0 | J19: =SUM(J18:J18) -> 0 | K19: =SUM(K18:K18) -> 0 | L19: =SUM(L18:L18) -> 0 | M19: =SUM(M18:M18) -> 0 | N19: =SUM(N18:N18) -> 0 | O19: =SUM(O18:O18) -> 0 | R19: =SUM(R18:R18) -> 151.64 | S19: =SUM(S18:S18) -> 151.64 | T19: =SUM(T18:T18) -> 0 | U19: =SUM(U18:U18) -> 0 | X19: =SUM(X18:X18) -> 0 | Y19: =SUM(Y18:Y18) -> 0 | Z19: =SUM(Z18:Z18) -> 0 | AA19: =SUM(AA18:AA18) -> 0 | AB19: =SUM(AB18:AB18) -> 0 | AC19: =SUM(AC18:AC18) -> 209.09 | AD19: =SUM(AD18:AD18) -> 0 | AE19: =SUM(AE18:AE18) -> 0 | AF19: =SUM(AF18:AF18) -> 3430.31 | AG19: 9
A20: 10 | B20: 1030 | AG20: 10
A21: 11 | B21: KEVIN MAR MORENO | C21: Admin Aide I | D21: -do- | F21: 11 | G21: =ROUND(7582/22,2) -> 344.64 | H21: =G21*F21 -> 3791.04 | I21: 198.35 | R21: =ROUND(G21*22*0.02,2) -> 151.64 | S21: =R21 -> 151.64 | T21: 382.38 | U21: 909.84 | V21: 100 | W21: 100 | Y21: 0 | Z21: 0 | AB21: 0 | AC21: 0 | AE21: 75.82 | AF21: =H21-(SUM(I21:R21)+T21+SUM(W21:AD21)) -> 2958.67 | AG21: 11
A22: 12 | H22: =SUM(H21:H21) -> 3791.04 | I22: =SUM(I21:I21) -> 198.35 | J22: =SUM(J21:J21) -> 0 | K22: =SUM(K21:K21) -> 0 | L22: =SUM(L21:L21) -> 0 | M22: =SUM(M21:M21) -> 0 | N22: =SUM(N21:N21) -> 0 | O22: =SUM(O21:O21) -> 0 | ... AF22: =SUM(AF21:AF21) -> 2958.67 | AG22: 12
A23: 13 | B23: 1071 | AG23: 13
A24: 14 | B24: MICHELLE CASTILLO | C24: Admin Aide I | D24: -do- | F24: 12 | G24: =ROUND(7582/22,2) -> 344.64 | H24: =G24*F24 -> 4135.68 | L24: 0 | O24: 0 | R24: =ROUND(G24*22*0.02,2) -> 151.64 | S24: =R24 -> 151.64 | X24: 0 | Z24: 0 | AC24: 1493.05 | AF24: =H24-(SUM(I24:R24)+T24+SUM(V24:AD24)) -> 2490.99 | AG24: 14
A25: 15 | B25: ALVIN VILLANUEVA | C25: Admin Aide I | D25: -do- | F25: 12 | G25: =ROUND(7582/22,2) -> 344.64 | H25: =G25*F25 -> 4135.68 | I25: 209.355 | L25: 0 | O25: 0 | R25: =ROUND(G25*22*0.02,2) -> 151.64 | S25: =R25 -> 151.64 | X25: 0 | Z25: 0 | AF25: =H25-(SUM(I25:R25)+T25+SUM(V25:AD25)) -> 3774.685 | AG25: 15
A26: 16 | H26: =SUM(H24:H25) -> 8271.36 | I26: =SUM(I24:I25) -> 209.355 | J26: =SUM(J24:J25) -> 0 | K26: =SUM(K24:K25) -> 0 | L26: =SUM(L24:L25) -> 0 | M26: =SUM(M24:M25) -> 0 | N26: =SUM(N24:N25) -> 0 | O26: =SUM(O24:O25) -> 0 | R26: =SUM(R24:R25) -> 303.28 | S26: =SUM(S24:S25) -> 303.28 | T26: =SUM(T24:T25) -> 0 | U26: =SUM(U24:U25) -> 0 | X26: =SUM(X24:X25) -> 0 | Y26: =SUM(Y24:Y25) -> 0 | Z26: =SUM(Z24:Z25) -> 0 | AA26: =SUM(AA24:AA25) -> 0 | AB26: =SUM(AB24:AB25) -> 0 | AC26: =SUM(AC24:AC25) -> 1493.05 | AD26: =SUM(AD24:AD25) -> 0 | AE26: =SUM(AE24:AE25) -> 0 | AF26: =SUM(AF24:AF25) -> 6265.675 | AG26: 16
A27: 17 | B27: 1081 | AG27: 17
A28: 18 | B28: JOANNA PATRIZHA MERAMBEL | C28: Admin Aide I | D28: -do- | F28: 12 | G28: =ROUND(7582/22,2) -> 344.64 | H28: =G28*F28 -> 4135.68 | I28: 0 | L28: 327.78 | O28: 0 | R28: 300 | S28: 151.64 | T28: 0 | U28: 0 | X28: 0 | Y28: 0 | Z28: 0 | AF28: =H28-(SUM(I28:R28)+T28+SUM(V28:AD28)) -> 3507.9 | AG28: 18
A29: 19 | B29: FELVIC QUIZON | C29: Admin Aide I | D29: -do- | F29: 12 | G29: =ROUND(7582/22,2) -> 344.64 | H29: =G29*F29 -> 4135.68 | I29: 0 | O29: 0 | R29: =ROUND(G29*22*0.02,2) -> 151.64 | S29: 151.64 | T29: 0 | U29: 0 | X29: 0 | Y29: 0 | Z29: 0 | AB29: 0 | AC29: 0 | AF29: =H29-(SUM(I29:R29)+T29+SUM(V29:AD29)) -> 3984.04 | AG29: 19
A30: 20 | B30: TAMMY O. BENELADA | C30: Admin Aide I | D30: -do- | F30: 12 | G30: =ROUND(7582/22,2) -> 344.64 | H30: =G30*F30 -> 4135.68 | I30: 209.55 | O30: 0 | R30: =ROUND(G30*22*0.02,2) -> 151.64 | S30: =R30 -> 151.64 | T30: 0 | U30: 0 | X30: 0 | Y30: 0 | Z30: 0 | AB30: 0 | AC30: 0 | AF30: =H30-(SUM(I30:R30)+T30+SUM(V30:AD30)) -> 3774.49 | AG30: 20
A31: 21 | B31: RIZALINO DE CASTRO | C31: Admin Aide I | D31: -do- | F31: 12 | G31: =ROUND(7582/22,2) -> 344.64 | H31: =G31*F31 -> 4135.68 | L31: 0 | O31: 0 | R31: =ROUND(G31*22*0.02,2) -> 151.64 | S31: =R31 -> 151.64 | X31: 0 | Z31: 0 | AF31: =H31-(SUM(I31:R31)+T31+SUM(V31:AD31)) -> 3984.04 | AG31: 21
A32: 22 | B32: FRENZIE GARANTUZA | C32: Admin Aide I | D32: -do- | F32: 12 | G32: =ROUND(7582/22,2) -> 344.64 | H32: =G32*F32 -> 4135.68 | I32: 209.55 | L32: 0 | O32: 0 | R32: =ROUND(G32*22*0.02,2) -> 151.64 | S32: =R32 -> 151.64 | X32: 0 | Z32: 0 | AF32: =H32-(SUM(I32:R32)+T32+SUM(V32:AD32)) -> 3774.49 | AG32: 22
A33: 23 | H33: =SUM(H28:H32) -> 20678.4 | I33: =SUM(I28:I32) -> 419.1 | J33: =SUM(J28:J32) -> 0 | K33: =SUM(K28:K32) -> 0 | L33: =SUM(L28:L32) -> 327.78 | M33: =SUM(M28:M32) -> 0 | N33: =SUM(N28:N32) -> 0 | O33: =SUM(O28:O32) -> 0 | R33: =SUM(R28:R32) -> 906.56 | S33: =SUM(S28:S32) -> 758.2 | T33: =SUM(T28:T32) -> 0 | U33: =SUM(U28:U32) -> 0 | X33: =SUM(X28:X32) -> 0 | Y33: =SUM(Y28:Y32) -> 0 | Z33: =SUM(Z28:Z32) -> 0 | AA33: =SUM(AA28:AA32) -> 0 | AB33: =SUM(AB28:AB32) -> 0 | AC33: =SUM(AC28:AC32) -> 0 | AD33: =SUM(AD28:AD32) -> 0 | AE33: =SUM(AE28:AE32) -> 0 | AF33: =SUM(AF28:AF32) -> 19024.96 | AG33: 23
A34: 24 | B34: 1091 | AG34: 24
A35: 25 | B35: JACQUILOU DIMARANAN | C35: Admin Aide I | D35: -do- | F35: 12 | G35: =ROUND(7582/22,2) -> 344.64 | H35: =G35*F35 -> 4135.68 | L35: 327.78 | M35: 0 | N35: 0 | R35: =ROUND(G35*22*0.02,2) -> 151.64 | S35: =R35 -> 151.64 | T35: 0 | U35: 0 | X35: 0 | Y35: 0 | Z35: 20 | AC35: 0 | AF35: =H35-(SUM(I35:R35)+T35+SUM(V35:AD35)) -> 3636.26 | AG35: 25
A36: 26 | B36: NIÑO LAGRIMAS | C36: Admin Aide I | D36: -do- | F36: 12 | G36: =ROUND(7582/22,2) -> 344.64 | H36: =G36*F36 -> 4135.68 | I36: 209.55 | N36: 678.06 | O36: 300 | R36: =ROUND(G36*22*0.02,2) -> 151.64 | S36: =R36 -> 151.64 | T36: 0 | U36: 0 | X36: 0 | Y36: 0 | Z36: 0 | AB36: 0 | AC36: 192.8 | AF36: =H36-(SUM(I36:R36)+T36+SUM(V36:AD36)) -> 2603.63 | AG36: 26
A37: 27 | B37: CHRISTIAN ABRANTES | C37: Admin Aide I | D37: -do- | F37: 12 | G37: =ROUND(7582/22,2) -> 344.64 | H37: =G37*F37 -> 4135.68 | I37: 209.55 | O37: 0 | R37: =ROUND(G37*22*0.02,2) -> 151.64 | S37: =R37 -> 151.64 | T37: 0 | U37: 0 | X37: 0 | Y37: 0 | Z37: 0 | AB37: 0 | AF37: =H37-(SUM(I37:R37)+T37+SUM(V37:AD37)) -> 3774.49 | AG37: 27
A38: 28 | B38: ARLENE JAVIER | C38: Admin Aide I | D38: -do- | F38: 12 | G38: =ROUND(7582/22,2) -> 344.64 | H38: =G38*F38 -> 4135.68 | I38: 0 | L38: 0 | N38: 508.55 | O38: 0 | R38: =ROUND(G38*22*0.02,2) -> 151.64 | S38: =R38 -> 151.64 | T38: 0 | X38: 0 | Y38: 0 | Z38: 0 | AB38: 0 | AC38: 0 | AF38: =H38-(SUM(I38:R38)+T38+SUM(V38:AD38)) -> 3475.49 | AG38: 28
A39: 29 | H39: =SUM(H35:H38) -> 16542.72 | I39: =SUM(I35:I38) -> 419.1 | J39: =SUM(J35:J38) -> 0 | K39: =SUM(K35:K38) -> 0 | L39: =SUM(L35:L38) -> 327.78 | M39: =SUM(M35:M38) -> 0 | N39: =SUM(N35:N38) -> 1186.61 | O39: =SUM(O35:O38) -> 300 | R39: =SUM(R35:R38) -> 606.56 | S39: =SUM(S35:S38) -> 606.56 | T39: =SUM(T35:T38) -> 0 | U39: =SUM(U35:U38) -> 0 | X39: =SUM(X35:X38) -> 0 | Y39: =SUM(Y35:Y38) -> 0 | Z39: =SUM(Z35:Z38) -> 20 | AA39: =SUM(AA35:AA38) -> 0 | AB39: =SUM(AB35:AB38) -> 0 | AC39: =SUM(AC35:AC38) -> 192.8 | AD39: =SUM(AD35:AD38) -> 0 | AE39: =SUM(AE35:AE38) -> 0 | AF39: =SUM(AF35:AF38) -> 13489.87 | AG39: 29
A40: 30 | B40: 1101 | AG40: 30
A41: 31 | B41: ARLENE RIVERA | C41: Admin Aide I | D41: -do- | F41: 12 | G41: =ROUND(7582/22,2) -> 344.64 | H41: =G41*F41 -> 4135.68 | I41: 209.55 | O41: 0 | R41: =ROUND(G41*22*0.02,2) -> 151.64 | S41: =R41 -> 151.64 | T41: 0 | U41: 0 | X41: 0 | Y41: 0 | Z41: 0 | AB41: 0 | AC41: 0 | AF41: =H41-(SUM(I41:R41)+T41+SUM(V41:AD41)) -> 3774.49 | AG41: 31
A42: 32 | B42: GELSON SAMPANG | C42: Admin Aide I | D42: -do- | F42: 12 | G42: =ROUND(7582/22,2) -> 344.64 | H42: =G42*F42 -> 4135.68 | I42: 209.55 | N42: 0 | O42: 0 | R42: =ROUND(G42*22*0.02,2) -> 151.64 | S42: =R42 -> 151.64 | T42: 0 | U42: 0 | X42: 0 | Y42: 0 | Z42: 0 | AB42: 0 | AC42: 0 | AF42: =H42-(SUM(I42:R42)+T42+SUM(V42:AD42)) -> 3774.49 | AG42: 32
A43: 33 | H43: =SUM(H41:H42) -> 8271.36 | I43: =SUM(I41:I42) -> 419.1 | J43: =SUM(J41:J42) -> 0 | K43: =SUM(K41:K42) -> 0 | L43: =SUM(L41:L42) -> 0 | M43: =SUM(M41:M42) -> 0 | N43: =SUM(N41:N42) -> 0 | O43: =SUM(O41:O42) -> 0 | R43: =SUM(R41:R42) -> 303.28 | S43: =SUM(S41:S42) -> 303.28 | T43: =SUM(T41:T42) -> 0 | U43: =SUM(U41:U42) -> 0 | X43: =SUM(X41:X42) -> 0 | Y43: =SUM(Y41:Y42) -> 0 | Z43: =SUM(Z41:Z42) -> 0 | AA43: =SUM(AA41:AA42) -> 0 | AB43: =SUM(AB41:AB42) -> 0 | AC43: =SUM(AC41:AC42) -> 0 | AD43: =SUM(AD41:AD42) -> 0 | AE43: =SUM(AE41:AE42) -> 0 | AF43: =SUM(AF41:AF42) -> 7548.98 | AG43: 33
A44: 34 | B44: 6531 | AG44: 34
A45: 35 | B45: RONALD FULLEROS | C45: Admin Aide I | D45: -do- | F45: 13 | G45: =ROUND(7582/22,2) -> 344.64 | H45: =G45*F45 -> 4480.32 | I45: 209.55 | N45: 1186.61 | O45: 0 | R45: =ROUND(G45*22*0.02,2) -> 151.64 | S45: =R45 -> 151.64 | Z45: 0 | AB45: 0 | AC45: 373.33 | AF45: =H45-(SUM(I45:R45)+T45+SUM(V45:AD45)) -> 2559.19 | AG45: 35
A46: 36 | H46: =H45 -> 4480.32 | I46: =I45 -> 209.55 | J46: =J45 -> 0 | K46: =K45 -> 0 | L46: =L45 -> 0 | M46: =M45 | N46: =N45 -> 1186.61 | O46: =O45 -> 0 | R46: =R45 -> 151.64 | S46: =S45 -> 151.64 | T46: =T45 -> 0 | U46: =U45 -> 0 | X46: =X45 -> 0 | Y46: =Y45 -> 0 | Z46: =Z45 -> 0 | AA46: =AA45 -> 0 | AB46: =AB45 -> 0 | AC46: =AC45 -> 373.33 | AD46: =AD45 | AE46: =AE45 -> 0 | AF46: =AF45 -> 2559.19 | AG46: 36
A47: 37 | B47: 7611 | AG47: 37
A48: 38 | B48: LORELYN SAGALES | C48: Admin Aide I | D48: -do- | F48: 12 | G48: =ROUND(7582/22,2) -> 344.64 | H48: =G48*F48 -> 4135.68 | R48: =ROUND(G48*22*0.02,2) -> 151.64 | S48: =R48 -> 151.64 | X48: 0 | Y48: 0 | Z48: 0 | AB48: 0 | AC48: 0 | AF48: =H48-(SUM(I48:R48)+T48+SUM(V48:AD48)) -> 3984.04 | AG48: 38
A49: 39 | B49: RUTH GRACE WALO | C49: Admin Aide I | D49: -do- | F49: 12 | G49: =ROUND(7582/22,2) -> 344.64 | H49: =G49*F49 -> 4135.68 | I49: 0 | L49: 0 | N49: 0 | O49: 0 | R49: =ROUND(G49*22*0.02,2) -> 151.64 | S49: =R49 -> 151.64 | T49: 0 | U49: 0 | X49: 0 | Y49: 0 | Z49: 0 | AB49: 0 | AC49: 0 | AF49: =H49-(SUM(I49:R49)+T49+SUM(V49:AD49))+AA49 -> 3984.04 | AG49: 39
A50: 40 | B50: ARGELYN DAVAC | C50: Admin Aide I | D50: -do- | F50: 12 | G50: =ROUND(7582/22,2) -> 344.64 | H50: =G50*F50 -> 4135.68 | I50: 209.55 | L50: 0 | N50: 0 | O50: 0 | R50: =ROUND(G50*22*0.02,2) -> 151.64 | S50: =R50 -> 151.64 | T50: 0 | U50: 0 | X50: 0 | Y50: 0 | Z50: 0 | AB50: 0 | AC50: 0 | AF50: =H50-(SUM(I50:R50)+T50+SUM(V50:AD50))+AA50 -> 3774.49 | AG50: 40
A51: 41 | H51: =SUM(H48:H50) -> 12407.04 | I51: =SUM(I49:I50) -> 209.55 | J51: =SUM(J49:J50) -> 0 | K51: =SUM(K49:K50) -> 0 | L51: =SUM(L49:L50) -> 0 | M51: =SUM(M49:M50) -> 0 | N51: =SUM(N49:N50) -> 0 | O51: =SUM(O49:O50) -> 0 | R51: =SUM(R48:R50) -> 454.92 | S51: =SUM(S48:S50) -> 454.92 | T51: =SUM(T49:T50) -> 0 | U51: =SUM(U49:U50) -> 0 | X51: =SUM(X49:X50) -> 0 | Y51: =SUM(Y49:Y50) -> 0 | Z51: =SUM(Z49:Z50) -> 0 | AA51: =SUM(AA49:AA50) -> 0 | AB51: =SUM(AB49:AB50) -> 0 | AC51: =SUM(AC49:AC50) -> 0 | AD51: =SUM(AD49:AD50) -> 0 | AE51: =SUM(AE49:AE50) -> 0 | AF51: =SUM(AF48:AF50) -> 11742.57 | AG51: 41
A52: 42 | B52: 8711 | AG52: 42
A53: 43 | B53: JOSEPH WARREN COLADILLA | C53: Admin Aide I | D53: -do- | F53: 12 | G53: =ROUND(7582/22,2) -> 344.64 | H53: =G53*F53 -> 4135.68 | I53: 0 | L53: 0 | N53: 1412.11 | O53: 0 | R53: =ROUND(G53*22*0.02,2) -> 151.64 | S53: =R53 -> 151.64 | T53: 0 | U53: 0 | X53: 0 | Y53: 0 | Z53: 0 | AB53: 0 | AC53: 0 | AF53: =H53-(SUM(I53:R53)+T53+SUM(V53:AD53)) -> 2571.93 | AG53: 43
A54: 44 | B54: LANIE VILLA | C54: Admin Aide I | D54: -do- | F54: 12 | G54: =ROUND(7582/22,2) -> 344.64 | H54: =G54*F54 -> 4135.68 | I54: 0 | L54: 327.78 | O54: 0 | R54: =ROUND(G54*22*0.02,2) -> 151.64 | S54: =R54 -> 151.64 | T54: 0 | U54: 0 | X54: 0 | Y54: 0 | Z54: 0 | AB54: 0 | AC54: 0 | AF54: =H54-(SUM(I54:R54)+T54+SUM(V54:AD54)) -> 3656.26 | AG54: 44
A55: 45 | H55: =SUM(H53:H54) -> 8271.36 | I55: =SUM(I53:I54) -> 0 | J55: =SUM(J53:J54) -> 0 | K55: =SUM(K53:K54) -> 0 | L55: =SUM(L53:L54) -> 327.78 | M55: =SUM(M53:M54) -> 0 | N55: =SUM(N53:N54) -> 1412.11 | O55: =SUM(O53:O54) -> 0 | R55: =SUM(R53:R54) -> 303.28 | S55: =SUM(S53:S54) -> 303.28 | T55: =SUM(T53:T54) -> 0 | U55: =SUM(U53:U54) -> 0 | X55: =SUM(X53:X54) -> 0 | Y55: =SUM(Y53:Y54) -> 0 | Z55: =SUM(Z53:Z54) -> 0 | AA55: =SUM(AA53:AA54) -> 0 | AB55: =SUM(AB53:AB54) -> 0 | AC55: =SUM(AC53:AC54) -> 0 | AD55: =SUM(AD53:AD54) -> 0 | AE55: =SUM(AE53:AE54) -> 0 | AF55: =SUM(AF53:AF54) -> 6228.19 | AG55: 45
A56: 46 | B56: 8731 | AG56: 46
A57: 47 | B57: JAY ALMONTERO | C57: Admin Aide I | D57: -do- | F57: 12 | G57: =ROUND(7582/22,2) -> 344.64 | H57: =G57*F57 -> 4135.68 | N57: 678.06 | R57: =ROUND(G57*22*0.02,2) -> 151.64 | S57: =R57 -> 151.64 | Z57: 20 | AB57: 0 | AC57: 0 | AF57: =H57-(SUM(I57:R57)+T57+SUM(V57:AD57)) -> 3285.98 | AG57: 47
A58: 48 | B58: JAYRALD CABREGA | C58: Admin Aide I | D58: -do- | F58: 12 | G58: =ROUND(7582/22,2) -> 344.64 | H58: =G58*F58 -> 4135.68 | I58: 209.55 | R58: =ROUND(G58*22*0.02,2) -> 151.64 | S58: =R58 -> 151.64 | AF58: =H58-(SUM(I58:R58)+T58+SUM(V58:AD58)) -> 3774.49 | AG58: 48
A59: 49 | B59: KELVIN ABAQUIN | C59: Admin Aide I | D59: -do- | F59: 11 | G59: =ROUND(7582/22,2) -> 344.64 | H59: =G59*F59 -> 3791.04 | L59: 0 | O59: 0 | R59: =ROUND(G59*22*0.02,2) -> 151.64 | S59: =R59 -> 151.64 | T59: 0 | U59: 0 | X59: 0 | Y59: 0 | Z59: 0 | AB59: 0 | AC59: 0 | AF59: =H59-(SUM(I59:R59)+T59+SUM(V59:AD59)) -> 3639.4 | AG59: 49
A60: 50 | H60: =SUM(H57:H59) -> 12062.4 | I60: =SUM(I57:I59) -> 209.55 | J60: =SUM(J57:J57) -> 0 | K60: =SUM(K57:K57) -> 0 | L60: =SUM(L57:L57) -> 0 | M60: =SUM(M57:M57) -> 0 | N60: =SUM(N57:N57) -> 678.06 | O60: =SUM(O57:O57) -> 0 | R60: =SUM(R57:R59) -> 454.92 | S60: =SUM(S57:S59) -> 454.92 | T60: =SUM(T57:T57) -> 0 | U60: =SUM(U57:U57) -> 0 | X60: =SUM(X57:X57) -> 0 | Y60: =SUM(Y57:Y57) -> 0 | Z60: =SUM(Z57:Z57) -> 20 | AA60: =SUM(AA57:AA57) -> 0 | AB60: =SUM(AB57:AB57) -> 0 | AC60: =SUM(AC57:AC57) -> 0 | AD60: =SUM(AD57:AD57) -> 0 | AE60: =SUM(AE57:AE57) -> 0 | AF60: =SUM(AF57:AF59) -> 10699.87 | AG60: 50
A61: 51 | B61: 8751 | AG61: 51
A62: 52 | B62: MARK JOSEPH BALOTA | C62: Admin Aide I | D62: -do- | F62: 11 | G62: =ROUND(7582/22,2) -> 344.64 | H62: =G62*F62 -> 3791.04 | I62: 0 | L62: 0 | N62: 0 | O62: 0 | R62: =ROUND(G62*22*0.02,2) -> 151.64 | S62: =R62 -> 151.64 | X62: 0 | Y62: 0 | Z62: 0 | AB62: 0 | AC62: 0 | AF62: =H62-(SUM(I62:R62)+T62+SUM(V62:AD62)) -> 3639.4 | AG62: 52
A63: 53 | B63: MARLON PAMATMAT | C63: Admin Aide I | D63: -do- | F63: 12 | G63: =ROUND(7582/22,2) -> 344.64 | H63: =G63*F63 -> 4135.68 | I63: 0 | L63: 0 | N63: 0 | O63: 0 | R63: =ROUND(G63*22*0.02,2) -> 151.64 | S63: =R63 -> 151.64 | X63: 0 | Y63: 0 | Z63: 0 | AB63: 0 | AC63: 0 | AF63: =H63-(SUM(I63:R63)+T63+SUM(V63:AD63)) -> 3984.04 | AG63: 53
A64: 54 | H64: =SUM(H62:H63) -> 7926.72 | I64: =SUM(I62:I63) -> 0 | J64: =SUM(J62:J63) -> 0 | K64: =SUM(K62:K63) -> 0 | L64: =SUM(L62:L63) -> 0 | M64: =SUM(M62:M63) -> 0 | N64: =SUM(N62:N63) -> 0 | O64: =SUM(O62:O63) -> 0 | R64: =SUM(R62:R63) -> 303.28 | S64: =SUM(S62:S63) -> 303.28 | T64: =SUM(T62:T63) -> 0 | U64: =SUM(U62:U63) -> 0 | X64: =SUM(X62:X63) -> 0 | Y64: =SUM(Y62:Y63) -> 0 | Z64: =SUM(Z62:Z63) -> 0 | AA64: =SUM(AA62:AA63) -> 0 | AB64: =SUM(AB62:AB63) -> 0 | AC64: =SUM(AC62:AC63) -> 0 | AD64: =SUM(AD62:AD63) -> 0 | AE64: =SUM(AE62:AE63) -> 0 | AF64: =SUM(AF62:AF63) -> 7623.44 | AG64: 54
A65: 55 | B65: 8841 | AG65: 55
A66: 56 | B66: FRANCISCO TOBIAS | C66: Admin Aide I | D66: -do- | F66: 12 | G66: =ROUND(7582/22,2) -> 344.64 | H66: =G66*F66 -> 4135.68 | I66: 0 | N66: 1152.72 | R66: =ROUND(G66*22*0.02,2) -> 151.64 | S66: =R66 -> 151.64 | T66: 0 | U66: 0 | X66: 0 | Y66: 0 | Z66: 0 | AF66: =H66-(SUM(I66:R66)+T66+SUM(V66:AD66)) -> 2831.32 | AG66: 56
A67: 57 | H67: =SUM(H66) -> 4135.68 | I67: =I66 -> 0 | J67: =J66 -> 0 | K67: =K66 -> 0 | L67: =L66 -> 0 | M67: 0 | N67: =N66 -> 1152.72 | O67: =O66 -> 0 | R67: =R66 -> 151.64 | S67: =S66 -> 151.64 | X67: 0 | Y67: =Y66 -> 0 | Z67: =Z66 -> 0 | AA67: =AA66 -> 0 | AB67: =AB66 -> 0 | AC67: =AC66 -> 0 | AD67: =AD66 -> 0 | AF67: =AF66 -> 2831.32 | AG67: 57
A68: 58 | B68: 8852 | AG68: 58
A69: 59 | B69: JAY - AR MANALO | C69: Admin Aide I | D69: -do- | F69: 11 | G69: =ROUND(7582/22,2) -> 344.64 | H69: =G69*F69 -> 3791.04 | R69: =ROUND(G69*22*0.02,2) -> 151.64 | S69: =R69 -> 151.64 | AF69: =H69-(SUM(I69:R69)+T69+SUM(V69:AD69)) -> 3639.4 | AG69: 59
A70: 60 | B70: REGIE MANALO | C70: Admin Aide I | D70: -do- | F70: 11 | G70: =ROUND(7582/22,2) -> 344.64 | H70: =G70*F70 -> 3791.04 | I70: 209.55 | L70: 0 | N70: 0 | O70: 0 | R70: =ROUND(G70*22*0.02,2) -> 151.64 | S70: =R70 -> 151.64 | T70: 0 | U70: 0 | X70: 0 | Y70: 0 | Z70: 0 | AB70: 0 | AC70: 0 | AF70: =H70-(SUM(I70:R70)+T70+SUM(V70:AD70)) -> 3429.85 | AG70: 60
A71: 61 | H71: =SUM(H69:H70) -> 7582.08 | I71: =SUM(I69:I70) -> 209.55 | J71: =SUM(J69:J70) -> 0 | K71: =SUM(K69:K70) -> 0 | L71: =SUM(L69:L70) -> 0 | M71: =SUM(M69:M70) -> 0 | N71: =SUM(N69:N70) -> 0 | O71: =SUM(O69:O70) -> 0 | R71: =SUM(R69:R70) -> 303.28 | S71: =SUM(S69:S70) -> 303.28 | T71: =SUM(T69:T70) -> 0 | U71: =SUM(U69:U70) -> 0 | X71: =SUM(X69:X70) -> 0 | Y71: =SUM(Y69:Y70) -> 0 | Z71: =SUM(Z69:Z70) -> 0 | AA71: =SUM(AA69:AA70) -> 0 | AB71: =SUM(AB69:AB70) -> 0 | AC71: =SUM(AC69:AC70) -> 0 | AD71: =SUM(AD69:AD70) -> 0 | AE71: =SUM(AE69:AE70) -> 0 | AF71: =SUM(AF69:AF70) -> 7069.25 | AG71: 61
A72: 62 | H72: =H71+H67+H64+H60+H55+H51+H46+H43+H39+H33+H26+H22+H19+H16 -> 134064.96 | I72: =I71+I67+I64+I60+I55+I51+I46+I43+I39+I33+I26+I22+I19+I16 -> 2922.305 | J72: =J71+J67+J64+J60+J55+J51+J46+J43+J39+J33+J26+J22+J19+J16 -> 0 | K72: =K71+K67+K64+K60+K55+K51+K46+K43+K39+K33+K26+K22+K19+K16 -> 0 | L72: =L71+L67+L64+L60+L55+L51+L46+L43+L39+L33+L26+L22+L19+L16 -> 1638.9 | M72: =M71+M67+M64+M60+M55+M51+M46+M43+M39+M33+M26+M22+M19+M16 -> #VALUE! | N72: =N71+N67+N64+N60+N55+N51+N46+N43+N39+N33+N26+N22+N19+N16 -> 6633.21 | O72: =O71+O67+O64+O60+O55+O51+O46+O43+O39+O33+O26+O22+O19+O16 -> 1100 | ... AF72: =AF71+AF67+AF64+AF60+AF55+AF51+AF46+AF43+AF39+AF33+AF26+AF22+AF19+AF16 -> 112702.87 | AG72: 62
A74: (1) I HEREBY CERTIFY on my official oath that the above PAYROLL is correct, and that services above stated have been duly rendered. Payment for such services is also hereby approved from the appropriation indicated. | R74: APPROVED:
AC75: (5) I HEREBY CERTIFY on my official oath that I have paid in cash to each official and employee whose name appears on the above roll the amount set opposite his name, under column 22, he having signed or marked his name under column 24 above, in my presence and at the time that payment was made to him, in acknowledgement of receipt of the money paid him.
R76: GIRLIE JAVIER EJERCITO
R77: Municipal Mayor
D78: GIRLIE JAVIER EJERCITO | R78: Chief of Office
D79: Municipal Mayor
A81: (2) APPROVED for payment subject to preaudit:
AC82: (6) I HEREBY CERTIFY on my official oath that each employee whose name appears on the above roll has been paid in cash or in check, and in no other mode, the amount shown under column 22 above, opposite his name. The total of the payments made by means this payroll amount to
E83: Treasurer
A84: (3) Preaudited and approved for payment in the month of
C85: (P ) | E85: pesos only. | AI85: Treasurer

Sheet Reg1(1-15)
A1: Municipal P A Y R O L L
A2: WE HEREBY ACKNOWLEDGE TO HAVE RECEIVED FROM MINERVA L. BOONGALING, TREASURER OF PAGSANJAN, LAGUNA THE SUMS HEREIN SPECIFIED OPPOSITES OUR RESPECTIVE NAMES, THE SAME BEING FULL COMPENSATION FOR OUR SERVICES RENDERED DURING THE PERIOD STATED BELOW, TO THE CORRECTNESS OF WHICH WE HEREBY SEVERALLY
A4: NO. | B4: NAME | C4: DESIGNATION | D4: PERIOD OF SERVICE (INCLUSIVE DATES) | G4: AMOUNT ACCRUED FOR THE PERIOD | H4: PERA (SEPT.)
D5: FROM | E5: TO | T5: PHILHEALTH | W5: GSIS | Y5: LBP | Z5: UCPB | AA5: Pag - ibig | AC5: GSIS | AD5: AMOUNT PAID IN CASH (CR.A-1) | AE5: N U M B E R
F6: MONTHLY RATE OF PAY | I6: MPL Lite | J6: Emergency Loan | K6: Educational Loan | L6: Policy Loan (Regular) | M6: Ploicy Loan (Optional) | N6: UOLI | O6: COMPUTER LOAN | P6: MPLOAN | Q6: W/holding Tax | W6: LIFE/RETIREMENT INSURANCE PREMIUM | AC6: STATE INSURANCE | AF6: SIGNATURE OF PAYEE | AG6: REMARKS
R7: Adjustmnt (6mos) | T7: PERSONAL SHARE | U7: GOV'T. SHARE | V7: ACCTS PAYBLE | AA7: CAL | AB7: MPL
R8: PS | S8: GS | W8: PERSONAL SHARE | X8: GOVERNMENT SHARE
A10: 1 | B10: 2 | C10: 3 | D10: 4 | E10: 5 | F10: 6 | G10: 7 | J10: 9 | K10: 10 | L10: 11 | M10: 18 | N10: 12 | O10: 13 | P10: 14 | Q10: 15 | T10: 16 | U10: 17 | W10: 18 | X10: 19 | Y10: 20 | Z10: 21 | AB10: 22 | AC10: 24 | AD10: 25 | AE10: 26 | AF10: 27 | AG10: 28
B11: 1011- OM
A12: 1 | C12: Municipal Mayor | D12: Feb. 1-15, 2026 | F12: 121264 | G12: =F12/2 -> 60632 | T12: 2500 | U12: 2500 | W12: =F12*0.09 -> 10913.76 | X12: =F12*0.12 -> 14551.68 | AC12: 100 | AD12: =G12-SUM(I12:Q12)-T12-W12-SUM(Y12:AB12)-R12 -> 47218.24 | AE12: 1
A13: 2 | C13: Executive Asst. II | D13: -d | E13: o- | F13: 40160 | G13: =F13/2 -> 20080 | T13: 1004 | U13: 1004 | W13: =F13*0.09 -> 3614.4 | X13: =F13*0.12 -> 4819.2 | AC13: 100 | AD13: =G13-SUM(I13:Q13)-T13-W13-SUM(Y13:AB13)-R13 -> 15461.6 | AE13: 2
A14: 3 | C14: Private Sec. II | D14: -d | E14: o- | F14: 34177 | G14: =F14/2 -> 17088.5 | T14: 854.42 | U14: 854.43 | W14: =F14*0.09 -> 3075.93 | X14: =F14*0.12 -> 4101.24 | AC14: 100 | AD14: =G14-SUM(I14:Q14)-T14-W14-SUM(Y14:AB14)-R14 -> 13158.15 | AE14: 3
A15: 4 | C15: Bookbinder IV | D15: -d | E15: o- | F15: 21922 | G15: =F15/2 -> 10961 | J15: 605.72 | T15: 548.05 | U15: 548.05 | W15: =F15*0.09 -> 1972.98 | X15: =F15*0.12 -> 2630.64 | Z15: 1826.79 | AC15: 100 | AD15: =G15-SUM(I15:Q15)-T15-W15-SUM(Y15:AB15)-R15 -> 6007.46 | AE15: 4
A16: 5 | C16: Admin. Aide IV | D16: -d | E16: o- | F16: ='[1]Reg1(1-15)'!$G$14 -> 14308 | G16: =F16/2 -> 7154 | J16: 900 | P16: 924.28 | T16: 357.7 | U16: 357.7 | W16: =F16*0.09 -> 1287.72 | X16: =F16*0.12 -> 1716.96 | Z16: 448.89 | AB16: 200 | AC16: 100 | AD16: =G16-SUM(I16:Q16)-T16-W16-SUM(Y16:AB16)-R16 -> 3035.41 | AE16: 5
A17: 6 | C17: Personal Driver | D17: -d | E17: o- | F17: 13474 | G17: =F17/2 -> 6737 | T17: 336.85 | U17: 336.85 | W17: =F17*0.09 -> 1212.66 | X17: =F17*0.12 -> 1616.88 | AC17: 100 | AD17: =G17-SUM(I17:Q17)-T17-W17-SUM(Y17:AB17)-R17 -> 5187.49 | AE17: 6
A18: 7 | C18: Personal Driver | D18: -d | E18: o- | F18: 13474 | G18: =F18/2 -> 6737 | T18: 336.85 | U18: 336.85 | W18: =F18*0.09 -> 1212.66 | X18: =F18*0.12 -> 1616.88 | AC18: 100 | AD18: =G18-SUM(I18:Q18)-T18-W18-SUM(Y18:AB18)-R18 -> 5187.49 | AE18: 7
A19: 8 | F19: =SUM(F12:F18) -> 258779 | G19: =SUM(G12:G18) -> 129389.5 | H19: =SUM(H12:H18) -> 0 | I19: =SUM(I12:I18) -> 0 | J19: =SUM(J12:J18) -> 1505.72 | K19: =SUM(K12:K18) -> 0 | L19: =SUM(L12:L18) -> 0 | M19: =SUM(M12:M18) -> 0 | ... AD19: =SUM(AD12:AD18) -> 95255.84 | AE19: 8
A20: 9 | B20: 1011-BAC | AE20: 9
A21: 10 | C21: BAC Sec./ Admin Officer IV | D21: Feb. 1-15, 2026 | F21: ='[1]Reg1(1-15)'!$G$18 -> 34177 | G21: =F21/2 -> 17088.5 | T21: 854.42 | U21: 854.43 | W21: =F21*0.09 -> 3075.93 | X21: =F21*0.12 -> 4101.24 | Y21: 3126.98 | AC21: 100 | AD21: =G21-SUM(I21:Q21)-T21-W21-SUM(Y21:AB21)-R21 -> 10031.17 | AE21: 10
A22: 11 | F22: =F21 -> 34177 | G22: =G21 -> 17088.5 | I22: =I21 -> 0 | J22: =J21 -> 0 | K22: =K21 -> 0 | L22: =L21 -> 0 | M22: =M21 -> 0 | N22: =N21 -> 0 | O22: =O21 -> 0 | P22: =P21 -> 0 | ... AD22: =AD21 -> 10031.17 | AE22: 11
A23: 12 | B23: 1031- ADMIN | AE23: 12
A24: 13 | C24: Mun. Administrator | D24: Feb. 1-15, 2026 | F24: 83457 | G24: =F24/2 -> 41728.5 | T24: 2086.42 | U24: 2086.43 | AD24: =G24-SUM(I24:Q24)-T24-W24-SUM(Y24:AB24)-R24 -> 39642.08 | AE24: 13
A25: 14 | F25: =F24 -> 83457 | G25: =G24 -> 41728.5 | I25: =I24 -> 0 | J25: =J24 -> 0 | K25: =K24 -> 0 | L25: =L24 -> 0 | M25: =M24 -> 0 | N25: =N24 -> 0 | O25: =O24 -> 0 | P25: =P24 -> 0 | ... AD25: =AD24 -> 39642.08 | AE25: 14
A26: 15 | B26: 1032 - HRMO | AE26: 15
A27: 16 | C27: MGDH I | D27: Feb. 1-15, 2026 | F27: ='[1]Reg1(1-15)'!$G$24 -> 86091 | G27: =F27/2 -> 43045.5 | I27: 1166.67 | L27: 150 | P27: 5705.08 | T27: 2152.27 | U27: 2152.28 | W27: =F27*0.09 -> 7748.19 | X27: =F27*0.12 -> 10330.92 | Y27: 18119.84 | Z27: 4757.98 | AB27: 885.23 | AC27: 100 | AD27: =G27-SUM(I27:Q27)-T27-W27-SUM(Y27:AB27)-R27 -> 2360.24 | AE27: 16
A28: 17 | C28: Bookbinder IV | D28: -d | E28: o- | F28: 21922 | G28: =F28/2 -> 10961 | L28: 100 | O28: 983.33 | T28: 548.05 | U28: 548.05 | W28: =F28*0.09 -> 1972.98 | X28: =F28*0.12 -> 2630.64 | AB28: 2907.74 | AC28: 100 | AD28: =G28-SUM(I28:Q28)-T28-W28-SUM(Y28:AB28)-R28 -> 4448.9 | AE28: 17
A29: 18 | C29: Admin. Aide IV | D29: -d | E29: o- | F29: 14308 | G29: =F29/2 -> 7154 | M29: 0 | T29: 357.7 | U29: 357.7 | W29: =F29*0.09 -> 1287.72 | X29: =F29*0.12 -> 1716.96 | Y29: 3380.76 | AC29: 100 | AD29: =G29-SUM(I29:Q29)-T29-W29-SUM(Y29:AB29)-R29 -> 2127.82 | AE29: 18
A30: 19 | C30: Admin. Aide III | D30: -d | E30: o- | F30: 13474 | G30: =F30/2 -> 6737 | T30: 336.85 | U30: 336.85 | W30: =F30*0.09 -> 1212.66 | X30: =F30*0.12 -> 1616.88 | Y30: 3500 | AB30: 239.97 | AC30: 100 | AD30: =G30-SUM(I30:Q30)-T30-W30-SUM(Y30:AB30)-R30 -> 1447.52 | AE30: 19
A31: 20 | F31: =SUM(F27:F30) -> 135795 | G31: =SUM(G27:G30) -> 67897.5 | H31: =SUM(H27:H30) -> 0 | I31: =SUM(I27:I30) -> 1166.67 | J31: =SUM(J27:J30) -> 0 | K31: =SUM(K27:K30) -> 0 | L31: =SUM(L27:L30) -> 250 | M31: =SUM(M27:M30) -> 0 | ... AD31: =SUM(AD27:AD30) -> 10384.48 | AE31: 20
A32: 21 | B32: 1041- MPDC | AE32: 21
A33: 22 | C33: Proj. Dev't. Officer III | D33: Feb. 1-15, 2026 | F33: ='[1]Reg1(1-15)'!$G$30 -> 43608 | G33: =F33/2 -> 21804 | I33: 1166.67 | J33: 655.56 | T33: 1090.2 | U33: 1090.2 | W33: =F33*0.09 -> 3924.72 | X33: =F33*0.12 -> 5232.96 | Y33: 3204.28 | Z33: 1773.53 | AB33: 2430.51 | AC33: 100 | AD33: =G33-SUM(I33:Q33)-T33-W33-SUM(Y33:AB33)-R33 -> 7558.53 | AE33: 22
A34: 23 | C34: Zoning Officer I | D34: -d | E34: o- | F34: ='[1]Reg1(1-15)'!$G$31 -> 25520 | G34: =F34/2 -> 12760 | J34: 522.82 | T34: 638 | U34: 638 | W34: =F34*0.09 -> 2296.8 | X34: =F34*0.12 -> 3062.4 | Y34: 3377.73 | AC34: 100 | AD34: =G34-SUM(I34:Q34)-T34-W34-SUM(Y34:AB34)-R34 -> 5924.65 | AE34: 23
A35: 24 | C35: Bookbinder IV | D35: -d | E35: o- | F35: 21748 | G35: =F35/2 -> 10874 | T35: 543.7 | U35: 543.7 | W35: =F35*0.09 -> 1957.32 | X35: =F35*0.12 -> 2609.76 | Y35: 3000 | Z35: 2973.74 | AC35: 100 | AD35: =G35-SUM(I35:Q35)-T35-W35-SUM(Y35:AB35)-R35 -> 2399.24 | AE35: 24
A36: 25 | C36: Admin. Aide IV | D36: -d | E36: o- | F36: 14308 | G36: =F36/2 -> 7154 | T36: 357.7 | U36: 357.7 | W36: =F36*0.09 -> 1287.72 | X36: =F36*0.12 -> 1716.96 | AB36: 594.1 | AC36: 100 | AD36: =G36-SUM(I36:Q36)-T36-W36-SUM(Y36:AB36)-R36 -> 4914.48 | AE36: 25
A37: 26 | F37: =SUM(F33:F36) -> 105184 | G37: =SUM(G33:G36) -> 52592 | I37: =SUM(I33:I36) -> 1166.67 | J37: =SUM(J33:J36) -> 1178.38 | K37: =SUM(K33:K36) -> 0 | L37: =SUM(L33:L36) -> 0 | M37: =SUM(M33:M36) -> 0 | N37: =SUM(N33:N36) -> 0 | O37: =SUM(O33:O36) -> 0 | P37: =SUM(P33:P36) -> 0 | ... AD37: =SUM(AD33:AD36) -> 20796.9 | AE37: 26
A38: 27 | B38: 1051 - MCR | AE38: 27
A39: 28 | C39: Admin. Asst. IV | D39: Feb. 1-15, 2026 | F39: ='[1]Reg1(1-15)'!$G$36 -> 21922 | G39: =F39/2 -> 10961 | I39: 1166.66 | P39: 3397.29 | T39: 548.05 | U39: 548.05 | W39: =F39*0.09 -> 1972.98 | X39: =F39*0.12 -> 2630.64 | AB39: 2994.82 | AC39: 100 | AD39: =G39-SUM(I39:Q39)-T39-W39-SUM(Y39:AB39)-R39 -> 881.2 | AE39: 28
A40: 29 | C40: Clerk IV | D40: -d | E40: o- | F40: ='[1]Reg1(1-15)'!$G$37 -> 18563 | G40: =F40/2 -> 9281.5 | T40: 464.07 | U40: 464.08 | W40: =F40*0.09 -> 1670.67 | X40: =F40*0.12 -> 2227.56 | AC40: 100 | AD40: =G40-SUM(I40:Q40)-T40-W40-SUM(Y40:AB40)-R40 -> 7146.76 | AE40: 29
A41: 30 | F41: =SUM(F39:F40) -> 40485 | G41: =SUM(G39:G40) -> 20242.5 | H41: =SUM(H39:H40) -> 0 | I41: =SUM(I39:I40) -> 1166.66 | J41: =SUM(J39:J40) -> 0 | K41: =SUM(K39:K40) -> 0 | L41: =SUM(L39:L40) -> 0 | M41: =SUM(M39:M40) -> 0 | ... AD41: =SUM(AD39:AD40) -> 8027.96 | AE41: 30
A42: 31 | B42: 1061 - General Service Office | AE42: 31
A43: 32 | C43: Supply Officer I | D43: Feb. 1-15, 2026 | F43: ='[1]Reg1(1-15)'!$G$40 -> 21748 | G43: =F43/2 -> 10874 | J43: 400.02 | T43: 543.7 | U43: 543.7 | W43: =F43*0.09 -> 1957.32 | X43: =F43*0.12 -> 2609.76 | Y43: 4378.04 | AC43: 100 | AD43: =G43-SUM(I43:Q43)-T43-W43-SUM(Y43:AB43)-R43 -> 3594.92 | AE43: 32
A44: 33 | C44: Admin. Asst. IV | D44: -d | E44: o- | F44: ='[1]Reg1(1-15)'!$G$41 -> 21748 | G44: =F44/2 -> 10874 | T44: 543.7 | U44: 543.7 | W44: =F44*0.09 -> 1957.32 | X44: =F44*0.12 -> 2609.76 | Z44: 2521.73 | AC44: 100 | AD44: =G44-SUM(I44:Q44)-T44-W44-SUM(Y44:AB44)-R44 -> 5851.25 | AE44: 33
A45: 34 | C45: Laborer II | D45: -d | E45: o- | F45: ='[1]Reg1(1-15)'!$G$42 -> 14189 | G45: =F45/2 -> 7094.5 | P45: 928.7 | T45: 354.72 | U45: 354.73 | W45: =F45*0.09 -> 1277.01 | X45: =F45*0.12 -> 1702.68 | AC45: 100 | AD45: =G45-SUM(I45:Q45)-T45-W45-SUM(Y45:AB45)-R45 -> 4534.07 | AE45: 34
A46: 35 | C46: Admin. Aide III | D46: -d | E46: o- | F46: ='[1]Reg1(1-15)'!$G$43 -> 13675 | G46: =F46/2 -> 6837.5 | I46: =583.33+583.34 -> 1166.67 | J46: 655.56 | P46: 887.02 | T46: 341.87 | U46: 341.88 | W46: =F46*0.09 -> 1230.75 | X46: =F46*0.12 -> 1641 | AC46: 100 | AD46: =G46-SUM(I46:Q46)-T46-W46-SUM(Y46:AB46)-R46 -> 2555.63 | AE46: 35
A47: 36 | C47: Admin. Aide III | D47: -d | E47: o- | F47: ='[1]Reg1(1-15)'!$G$44 -> 13675 | G47: =F47/2 -> 6837.5 | T47: 341.87 | U47: 341.88 | W47: =F47*0.09 -> 1230.75 | X47: =F47*0.12 -> 1641 | Y47: 3156.75 | AC47: 100 | AD47: =G47-SUM(I47:Q47)-T47-W47-SUM(Y47:AB47)-R47 -> 2108.13 | AE47: 36
A48: 37 | C48: Admin. Aide III | D48: -d | E48: o- | F48: ='[1]Reg1(1-15)'!$G$45 -> 13575 | G48: =F48/2 -> 6787.5 | P48: 591.34 | T48: 339.37 | U48: 339.38 | W48: =F48*0.09 -> 1221.75 | X48: =F48*0.12 -> 1629 | Y48: 1139.73 | AC48: 100 | AD48: =G48-SUM(I48:Q48)-T48-W48-SUM(Y48:AB48)-R48 -> 3495.31 | AE48: 37
A49: 38 | F49: =SUM(F43:F48) -> 98610 | G49: =SUM(G43:G48) -> 49305 | I49: =SUM(I43:I48) -> 1166.67 | J49: =SUM(J43:J48) -> 1055.58 | K49: =SUM(K43:K48) -> 0 | L49: =SUM(L43:L48) -> 0 | M49: =SUM(M43:M48) -> 0 | N49: =SUM(N43:N48) -> 0 | O49: =SUM(O43:O48) -> 0 | P49: =SUM(P43:P48) -> 2407.06 | ... AD49: =SUM(AD43:AD48) -> 22139.31 | AE49: 38
A50: 39 | B50: 1071 - BUDGET | AE50: 39
A51: 40 | C51: Mun. Budget Officer | D51: Feb. 1-15, 2026 | F51: ='[1]Reg1(1-15)'!$G$48 -> 83457 | G51: =F51/2 -> 41728.5 | J51: =1311.12 -> 1311.12 | L51: 300 | O51: 1966.67 | T51: 2086.42 | U51: 2086.43 | W51: =F51*0.09 -> 7511.13 | X51: =F51*0.12 -> 10014.84 | Y51: 11999.84 | AA51: 2244.51 | AC51: 100 | AD51: =G51-SUM(I51:Q51)-T51-W51-SUM(Y51:AB51)-R51 -> 14308.81 | AE51: 40
A52: 41 | C52: Admin Asst.V | D52: -d | E52: o- | F52: ='[1]Reg1(1-15)'!$G$49 -> 25520 | G52: =F52/2 -> 12760 | P52: 1757.71 | T52: 638 | U52: 638 | W52: =F52*0.09 -> 2296.8 | X52: =F52*0.12 -> 3062.4 | AB52: 947.09 | AC52: 100 | AD52: =G52-SUM(I52:Q52)-T52-W52-SUM(Y52:AB52)-R52 -> 7120.4 | AE52: 41 | AI52: =F59+'Reg.2(1-15)'!F55+'Reg.3(1-15)'!F69+#REF!+'SB(1-15)'!F44 -> #REF!
A53: 42 | C53: Budget Officer I | D53: -d | E53: o- | F53: ='[1]Reg1(1-15)'!$G$50 -> 25762 | G53: =F53/2 -> 12881 | I53: 700 | J53: 512.49 | P53: 1568.86 | T53: 644.05 | U53: 644.05 | W53: =F53*0.09 -> 2318.58 | X53: =F53*0.12 -> 3091.44 | Y53: 3077.48 | AC53: 100 | AD53: =G53-SUM(I53:Q53)-T53-W53-SUM(Y53:AB53)-R53 -> 4059.54 | AE53: 42
A54: 43 | C54: Bookbinder IV | D54: -d | E54: o- | F54: 21922 | G54: =F54/2 -> 10961 | P54: 1211.41 | T54: 548.05 | U54: 548.05 | W54: =F54*0.09 -> 1972.98 | X54: =F54*0.12 -> 2630.64 | AC54: 100 | AD54: =G54-SUM(I54:Q54)-T54-W54-SUM(Y54:AB54)-R54 -> 7228.56 | AE54: 43
A55: 44 | C55: Admin. Aide IV | D55: -d | E55: o- | F55: ='[1]Reg1(1-15)'!$G$52 -> 14414 | G55: =F55/2 -> 7207 | T55: 360.35 | U55: 360.35 | W55: =F55*0.09 -> 1297.26 | X55: =F55*0.12 -> 1729.68 | Y55: 4600 | AC55: 100 | AD55: =G55-SUM(I55:Q55)-T55-W55-SUM(Y55:AB55)-R55 -> 949.39 | AE55: 44 | AI55: =AI52*0.02 -> #REF!
A56: 45 | C56: Admin. Aide IV | D56: -d | E56: o- | F56: 14308 | G56: =F56/2 -> 7154 | T56: 357.7 | U56: 357.7 | W56: =F56*0.09 -> 1287.72 | X56: =F56*0.12 -> 1716.96 | AC56: 100 | AD56: =G56-SUM(I56:Q56)-T56-W56-SUM(Y56:AB56)-R56 -> 5508.58 | AE56: 45
A57: 46 | C57: Admin. Aide IV | D57: -d | E57: o- | F57: ='[1]Reg1(1-15)'!$G$54 -> 14308 | G57: =F57/2 -> 7154 | I57: 475 | O57: 983.33 | T57: 357.7 | U57: 357.7 | W57: =F57*0.09 -> 1287.72 | X57: =F57*0.12 -> 1716.96 | Y57: 2842.16 | AC57: 100 | AD57: =G57-SUM(I57:Q57)-T57-W57-SUM(Y57:AB57)-R57 -> 1208.09 | AE57: 46
A58: 47 | F58: =SUM(F51:F57) -> 199691 | G58: =SUM(G51:G57) -> 99845.5 | H58: =SUM(H51:H57) -> 0 | I58: =SUM(I51:I57) -> 1175 | J58: =SUM(J51:J57) -> 1823.61 | K58: =SUM(K51:K57) -> 0 | L58: =SUM(L51:L57) -> 300 | M58: =SUM(M51:M57) -> 0 | ... AD58: =SUM(AD51:AD57) -> 40383.37 | AE58: 47
A59: 48 | B59: TOTAL | F59: =F58+F49+F41+F19+F37+F31+F22+F25 -> 956178 | G59: =G58+G49+G41+G19+G37+G31+G22+G25 -> 478089 | H59: =H58+H49+H41+H19+H37+H31+H22+H25 -> 0 | I59: =I58+I49+I41+I19+I37+I31+I22+I25 -> 5841.67 | J59: =J58+J49+J41+J19+J37+J31+J22+J25 -> 5563.29 | K59: =K58+K49+K41+K19+K37+K31+K22+K25 -> 0 | L59: =L58+L49+L41+L19+L37+L31+L22+L25 -> 550 | M59: =M58+M49+M41+M19+M37+M31+M22+M25 -> 0 | ... AD59: =AD58+AD49+AD41+AD19+AD37+AD31+AD22+AD25 -> 246661.11 | AE59: 48
A60: (1) I HEREBY CERTIFY on my official oath that the above PAYROLL is correct, and that services above stated have been duly rendered. Payment for such services is also hereby approved from the appropriation indicated. | AC60: (5) I HEREBY CERTIFY on my official oath that I have paid in cash to each official and employee whose name appears on the above roll the amount set opposite his name, under column 28, he having signed or marked his name under column 30 above, in my presence and at the time that payment was made to him, in acknowledgement of receipt of the money paid him.
T61: (4) APPROVED
F64: HON. JANUARIO FERRY G. GARCIA | T64: HON. JANUARIO FERRY G. GARCIA
F65: Municipal Mayor | T65: Municipal Mayor
T66: Chief of Office
A68: (2) APPROVED for payment subject to preaudit: | AD68: IRENE A. TAMONDONG
AD69: LRCO III
E70: Treasurer
AC71: (6) I HEREBY CERTIFY on my official oath that each employee whose name appears on the above roll has been paid in cash or in check, and in no other mode, the amount shown under column 21 above, opposite his name. The total of the payments made by means this payroll amount to
A72: (3) Preaudited and approved for payment in the month of
C74: (P ) | E74: pesos only.
C75: Provincial Auditor
AD77: MINERVA L. BOONGALING
AD78: Mun. Treasurer

Sheet Reg.2(1-15)
A1: Municipal P A Y R O L L
A2: WE HEREBY ACKNOWLEDGE TO HAVE RECEIVED FROM MINERVA L. BOONGALING, TREASURER OF PAGSANJAN, LAGUNA THE SUMS HEREIN SPECIFIED OPPOSITES OUR RESPECTIVE NAMES, THE SAME BEING FULL COMPENSATION FOR OUR SERVICES RENDERED DURING THE PERIOD STATED BELOW, TO THE CORRECTNESS OF WHICH WE HEREBY SEVERALLY
A4: NO. | B4: NAME | C4: DESIGNATION | D4: PERIOD OF SERVICE (INCLUSIVE DATES) | G4: AMOUNT ACCRUED FOR THE PERIOD | H4: SALARY DIFFERENTIAL Jan. & February 2021 | J4: D E D U C T I O N S
D5: FROM | E5: TO | J5: GOVERNMENT SERVICE INSURANCE SYSTEM | V5: PHILHEALTH | X5: GSIS | Z5: LBP | AA5: UCPB | AB5: Pag - ibig | AD5: GSIS | AE5: AMOUNT PAID IN CASH (CR.A-1) | AF5: N U M B E R
F6: MONTHLY RATE OF PAY | I6: DIFFERENTIAL SAL. (JAN.-SEPT., 2022) | J6: HOUSING LOAN | K6: CONSOLOAN | L6: Emergency Loan | M6: MPL Lite | N6: OPTIONAL | O6: UOLI | P6: POLICY LOAN REGULAR | Q6: COMPUTER LOAN | R6: MPL | S6: GFAL | X6: LIFE/RETIREMENT INSURANCE PREMIUM | AD6: STATE. INSURANCE | AG6: SIGNATURE OF PAYEE | AH6: REMARKS
T7: Adjustmnt (6mos) | V7: PERSONAL SHARE | W7: GOVT SHARE | AB7: MPL | AC7: CAL
T8: PS | U8: GS | X8: PERSONAL SHARE | Y8: GOVERNMENT SHARE
A10: 1 | B10: 2 | C10: 3 | D10: 4 | E10: 5 | F10: 6 | G10: 7 | J10: 8 | K10: 10 | L10: 13 | M10: 12 | N10: 14 | O10: 15 | P10: 16 | S10: 17 | V10: 18 | W10: 19 | X10: 21 | Y10: 22 | Z10: 23 | AA10: 24 | AB10: 27 | AC10: 28 | AD10: 29 | AE10: 30 | AF10: 31 | AG10: 32 | AH10: 33
B11: 1081 - Accounting
A12: 1 | C12: Mun. Accountant | D12: Feb. 1-15, 2026 | F12: ='[1]Reg.2(1-15)'!$G$12 -> 93016 | G12: =F12/2 -> 46508 | V12: 2325.4 | W12: 2325.4 | X12: =F12*0.09 -> 8371.44 | Y12: =F12*0.12 -> 11161.92 | Z12: 29897.61 | AD12: 100 | AE12: =G12-SUM(J12:S12)-V12-X12-SUM(Z12:AB12)-T12 -> 5913.55 | AF12: 1
A13: 2 | C13: Computer Operator IV | D13: -d | E13: o- | F13: 31776 | G13: =F13/2 -> 15888 | M13: 1200 | Q13: 983.33 | R13: 2647.41 | V13: 794.4 | W13: 794.4 | X13: =F13*0.09 -> 2859.84 | Y13: =F13*0.12 -> 3813.12 | Z13: 4334.3 | AA13: 1300 | AB13: 1220.3 | AD13: 100 | AE13: =G13-SUM(J13:S13)-V13-X13-SUM(Z13:AB13)-T13 -> 548.42 | AF13: 2
A14: 3 | C14: Mgt. and Audit Analyst | D14: -d | E14: o- | F14: ='[1]Reg.2(1-15)'!$G$14 -> 25520 | G14: =F14/2 -> 12760 | V14: 638 | W14: 638 | X14: =F14*0.09 -> 2296.8 | Y14: =F14*0.12 -> 3062.4 | AD14: 100 | AE14: =G14-SUM(J14:S14)-V14-X14-SUM(Z14:AB14)-T14 -> 9825.2 | AF14: 3 | AK14: =582.67*2 -> 1165.34
A15: 4 | C15: Bookkeeper III | D15: -d | E15: o- | F15: ='[1]Reg.2(1-15)'!$G$15 -> 22810 | G15: =F15/2 -> 11405 | V15: 570.25 | W15: 570.25 | X15: =F15*0.09 -> 2052.9 | Y15: =F15*0.12 -> 2737.2 | AB15: 835 | AD15: 100 | AE15: =G15-SUM(J15:S15)-V15-X15-SUM(Z15:AB15)-T15+I15 -> 7946.85 | AF15: 4
A16: 5 | C16: Bookkeeper III | D16: -d | E16: o- | F16: 21748 | G16: =F16/2 -> 10874 | V16: 543.7 | W16: =V16 -> 543.7 | X16: =F16*0.09 -> 1957.32 | Y16: =F16*0.12 -> 2609.76 | AA16: 6673 | AD16: 100 | AE16: =G16-SUM(J16:S16)-V16-X16-SUM(Z16:AB16)-T16 -> 1699.98 | AF16: 5
A17: 6 | C17: Bookbinder IV | D17: -d | E17: o- | F17: ='[1]Reg.2(1-15)'!$G$17 -> 21748 | G17: =F17/2 -> 10874 | L17: 655.56 | R17: 2342.74 | V17: 543.7 | W17: =V17 -> 543.7 | X17: =F17*0.09 -> 1957.32 | Y17: =F17*0.12 -> 2609.76 | AA17: 2379.99 | AD17: 100 | AE17: =G17-SUM(J17:S17)-V17-X17-SUM(Z17:AB17)-T17 -> 2994.69 | AF17: 6
A18: 7 | C18: Bookbinder IV | D18: -d | E18: o- | F18: 21748 | G18: =F18/2 -> 10874 | R18: 1010 | V18: 543.7 | W18: =V18 -> 543.7 | X18: =F18*0.09 -> 1957.32 | Y18: =F18*0.12 -> 2609.76 | AD18: 100 | AE18: =G18-SUM(J18:S18)-V18-X18-SUM(Z18:AB18)-T18 -> 7362.98 | AF18: 7
A19: 8 | C19: Acctg. Clerk II | D19: -d | E19: o- | F19: ='[1]Reg.2(1-15)'!$G$19 -> 16113 | G19: =F19/2 -> 8056.5 | V19: 402.82 | W19: 402.83 | X19: =F19*0.09 -> 1450.17 | Y19: =F19*0.12 -> 1933.56 | Z19: 2300 | AD19: 100 | AE19: =G19-SUM(J19:S19)-V19-X19-SUM(Z19:AB19)-T19 -> 3903.51 | AF19: 8
A20: 9 | C20: Admin. Aide IV | D20: -d | E20: o- | F20: ='[1]Reg.2(1-15)'!$G$20 -> 14521 | G20: =F20/2 -> 7260.5 | V20: =363.02 -> 363.02 | W20: =363.03 -> 363.03 | X20: =F20*0.09 -> 1306.89 | Y20: =F20*0.12 -> 1742.52 | AD20: 100 | AE20: =G20-SUM(J20:S20)-V20-X20-SUM(Z20:AB20)-T20 -> 5590.59 | AF20: 9
A21: 10 | C21: Admin. Aide IV | D21: -d | E21: o- | F21: ='[1]Reg.2(1-15)'!$G$21 -> 14308 | G21: =F21/2 -> 7154 | V21: 357.7 | W21: 357.7 | X21: =F21*0.09 -> 1287.72 | Y21: =F21*0.12 -> 1716.96 | AD21: 100 | AE21: =G21-SUM(J21:S21)-V21-X21-SUM(Z21:AB21)-T21 -> 5508.58 | AF21: 10
A22: 11 | C22: Admin. Aide IV | D22: -d | E22: o- | F22: ='[1]Reg.2(1-15)'!$G$22 -> 14308 | G22: =F22/2 -> 7154 | N22: 0 | O22: 0 | V22: 357.7 | W22: 357.7 | X22: =F22*0.09 -> 1287.72 | Y22: =F22*0.12 -> 1716.96 | Z22: 1573.17 | AA22: 2081.62 | AD22: 100 | AE22: =G22-SUM(J22:S22)-V22-X22-SUM(Z22:AB22)-T22 -> 1853.79 | AF22: 11
A23: 12 | C23: Admin. Aide III | D23: -d | E23: o- | F23: ='[1]Reg.2(1-15)'!$G$23 -> 13474 | G23: =F23/2 -> 6737 | M23: 475 | V23: 336.85 | W23: 336.85 | X23: =F23*0.09 -> 1212.66 | Y23: =F23*0.12 -> 1616.88 | AB23: =582.67 -> 582.67 | AD23: 100 | AE23: =G23-SUM(J23:S23)-V23-X23-SUM(Z23:AC23)-T23 -> 4129.82 | AF23: 12
A24: 13 | C24: Admin. Aide III | D24: -d | E24: o- | F24: ='[1]Reg.2(1-15)'!$G$24 -> 13474 | G24: =F24/2 -> 6737 | V24: 336.85 | W24: 336.85 | X24: =F24*0.09 -> 1212.66 | Y24: =F24*0.12 -> 1616.88 | AD24: 100 | AE24: =G24-SUM(J24:S24)-V24-X24-SUM(Z24:AB24)-T24 -> 5187.49 | AF24: 13
A25: 14 | C25: Admin. Aide III | D25: -d | E25: o- | F25: ='[1]Reg.2(1-15)'!$G$25 -> 13474 | G25: =F25/2 -> 6737 | V25: 336.85 | W25: 336.85 | X25: =F25*0.09 -> 1212.66 | Y25: =F25*0.12 -> 1616.88 | AD25: 100 | AE25: =G25-SUM(J25:S25)-V25-X25-SUM(Z25:AB25)-T25 -> 5187.49 | AF25: 14
A26: 15 | F26: =SUM(F12:F25) -> 338038 | G26: =SUM(G12:G25) -> 169019 | H26: =SUM(H12:H25) -> 0 | I26: =SUM(I12:I25) -> 0 | J26: =SUM(J12:J25) -> 0 | K26: =SUM(K12:K25) -> 0 | L26: =SUM(L12:L25) -> 655.56 | M26: =SUM(M12:M25) -> 1675 | ... AE26: =SUM(AE12:AE25) -> 67652.94 | AF26: 15
A27: 16 | B27: 1091-MTO | AF27: 16
A28: 17 | C28: Mun. Treasurer | D28: Feb. 1-15, 2026 | F28: 90205 | G28: =F28/2 -> 45102.5 | L28: 655.56 | R28: 7580.3 | S28: 4817.22 | V28: 2255.12 | W28: 2255.13 | X28: =F28*0.09 -> 8118.45 | Y28: =F28*0.12 -> 10824.6 | AB28: 2968.1 | AC28: 2119.82 | AD28: 100 | AE28: =G28-SUM(J28:S28)-V28-X28-SUM(Z28:AC28)-T28 -> 16587.93 | AF28: 17
A29: 18 | C29: Asst. Mun. Treasurer | D29: -d | E29: o- | F29: ='[1]Reg.2(1-15)'!$G$29 -> 67385 | G29: =F29/2 -> 33692.5 | L29: 1175.11 | V29: 1684.62 | W29: 1684.63 | X29: =F29*0.09 -> 6064.65 | Y29: =F29*0.12 -> 8086.2 | Z29: 11048.64 | AD29: 100 | AE29: =G29-SUM(J29:S29)-V29-X29-SUM(Z29:AB29)-T29 -> 13719.48 | AF29: 18
A30: 19 | C30: LRCO III | D30: -d | E30: o- | F30: 44057 | G30: =F30/2 -> 22028.5 | V30: 1101.42 | W30: 1101.43 | X30: =F30*0.09 -> 3965.13 | Y30: =F30*0.12 -> 5286.84 | Z30: 0 | AA30: 0 | AB30: 0 | AD30: 100 | AE30: =G30-SUM(J30:S30)-V30-X30-SUM(Z30:AB30)-T30 -> 16961.95 | AF30: 19
A31: 20 | C31: Cashier II | D31: -d | E31: o- | F31: ='[1]Reg.2(1-15)'!$G$31 -> 31470 | G31: =F31/2 -> 15735 | V31: 786.75 | W31: 786.75 | X31: =F31*0.09 -> 2832.3 | Y31: =F31*0.12 -> 3776.4 | Z31: 7891.88 | AD31: 100 | AE31: =G31-SUM(J31:S31)-V31-X31-SUM(Z31:AB31)-T31 -> 4224.07 | AF31: 20
A32: 21 | C32: Bookbinder IV | D32: -d | E32: o- | F32: 21922 | G32: =F32/2 -> 10961 | L32: 589.44 | V32: 548.05 | W32: 548.05 | X32: =F32*0.09 -> 1972.98 | Y32: =F32*0.12 -> 2630.64 | Z32: 4735.13 | AD32: 100 | AE32: =G32-SUM(J32:S32)-V32-X32-SUM(Z32:AB32)-T32 -> 3115.4 | AF32: 21
A33: 22 | C33: RCC II | D33: -d | E33: o- | F33: ='[1]Reg.2(1-15)'!$G$33 -> 17735 | G33: =F33/2 -> 8867.5 | M33: 1166.66 | P33: 100 | Q33: 983.34 | R33: 1150.08 | V33: 443.37 | W33: 443.38 | X33: =F33*0.09 -> 1596.15 | Y33: =F33*0.12 -> 2128.2 | Z33: 2000 | AA33: 0 | AD33: 100 | AE33: =G33-SUM(J33:S33)-V33-X33-SUM(Z33:AC33)-T33 -> 1427.9 | AF33: 22
A34: 23 | C34: RCC II | D34: -d | E34: o- | F34: 17219 | G34: =F34/2 -> 8609.5 | V34: 430.47 | W34: 430.48 | X34: =F34*0.09 -> 1549.71 | Y34: =F34*0.12 -> 2066.28 | Z34: 2525.4 | AB34: 738.01 | AD34: 100 | AE34: =G34-SUM(J34:S34)-V34-X34-SUM(Z34:AB34)-T34 -> 3365.91 | AF34: 23 | AK34: 2 | AL34: =#REF! -> #REF!
A35: 24 | C35: RCC II | D35: -d | E35: o- | F35: 17219 | G35: =F35/2 -> 8609.5 | V35: 430.47 | W35: 430.48 | X35: =F35*0.09 -> 1549.71 | Y35: =F35*0.12 -> 2066.28 | AD35: 100 | AE35: =G35-SUM(J35:S35)-V35-X35-SUM(Z35:AB35)-T35 -> 6629.32 | AF35: 24 | AK35: 1 | AL35: ='Reg1(16-31)'!AD59 -> 261985.45
A36: 25 | C36: RCC II | D36: -d | E36: o- | F36: 17094 | G36: =F36/2 -> 8547 | M36: 475 | Q36: 983.34 | V36: 427.35 | W36: 427.35 | X36: =F36*0.09 -> 1538.46 | Y36: =F36*0.12 -> 2051.28 | AD36: 100 | AE36: =G36-SUM(J36:S36)-V36-X36-SUM(Z36:AB36)-T36 -> 5122.85 | AF36: 25
A37: 26 | C37: Lic. Inspector | D37: -d | E37: o- | F37: ='[1]Reg.2(1-15)'!$G$37 -> 16113 | G37: =F37/2 -> 8056.5 | V37: 402.82 | W37: 402.83 | X37: =F37*0.09 -> 1450.17 | Y37: =F37*0.12 -> 1933.56 | AA37: 2844.13 | AD37: 100 | AE37: =G37-SUM(J37:S37)-V37-X37-SUM(Z37:AB37)-T37 -> 3359.38 | AF37: 26
A38: 27 | C38: Admin. Aide IV | D38: -d | E38: o- | F38: 14308 | G38: =F38/2 -> 7154 | M38: 1400 | P38: =150+150 -> 300 | Q38: 983.34 | R38: 797.96 | V38: 357.7 | W38: 357.7 | X38: =F38*0.09 -> 1287.72 | Y38: =F38*0.12 -> 1716.96 | Z38: 1892.98 | AD38: 100 | AE38: =G38-SUM(J38:S38)-V38-X38-SUM(Z38:AB38)-T38 -> 134.3 | AF38: 27
A39: 28 | C39: Admin. Aide III | D39: -d | E39: o- | F39: ='[1]Reg.2(1-15)'!$G$39 -> 13575 | G39: =F39/2 -> 6787.5 | L39: 655.56 | M39: 700 | V39: 339.37 | W39: 339.38 | X39: =F39*0.09 -> 1221.75 | Y39: =F39*0.12 -> 1629 | Z39: 2195.27 | AD39: 100 | AE39: =G39-SUM(J39:S39)-V39-X39-SUM(Z39:AB39)-T39 -> 1675.55 | AF39: 28
A40: 29 | C40: Admin. Aide III | D40: -d | E40: o- | F40: ='[1]Reg.2(1-15)'!$G$40 -> 13575 | G40: =F40/2 -> 6787.5 | L40: 655.56 | P40: 300 | V40: 339.37 | W40: 339.38 | X40: =F40*0.09 -> 1221.75 | Y40: =F40*0.12 -> 1629 | AD40: 100 | AE40: =G40-SUM(J40:S40)-V40-X40-SUM(Z40:AB40)-T40 -> 4270.82 | AF40: 29
A41: 30 | C41: Admin. Aide III | D41: -d | E41: o- | F41: 13474 | G41: =F41/2 -> 6737 | L41: 638.73 | M41: 475 | Q41: 983.34 | V41: 336.85 | W41: 336.85 | X41: =F41*0.09 -> 1212.66 | Y41: =F41*0.12 -> 1616.88 | AD41: 100 | AE41: =G41-SUM(J41:S41)-V41-X41-SUM(Z41:AB41)-T41 -> 3090.42 | AF41: 30
A42: 31 | C42: Admin. Aide III | D42: -d | E42: o- | F42: 13474 | G42: =F42/2 -> 6737 | L42: 638.73 | M42: 475 | R42: 398.53 | V42: 336.85 | W42: 336.85 | X42: =F42*0.09 -> 1212.66 | Y42: =F42*0.12 -> 1616.88 | AA42: 2973.74 | AD42: 100 | AE42: =G42-SUM(J42:S42)-V42-X42-SUM(Z42:AB42)-T42 -> 701.49 | AF42: 31
A43: 32 | C43: Admin. Aide III | D43: -d | E43: o- | F43: 13474 | G43: =F43/2 -> 6737 | V43: 336.85 | W43: 336.85 | X43: =F43*0.09 -> 1212.66 | Y43: =F43*0.12 -> 1616.88 | AD43: 100 | AE43: =G43-SUM(J43:S43)-V43-X43-SUM(Z43:AB43)-T43 -> 5187.49 | AF43: 32
A44: 33 | C44: Admin. Aide III | D44: -d | E44: o- | F44: ='[1]Reg.2(1-15)'!$G$44 -> 13474 | G44: =F44/2 -> 6737 | V44: 336.85 | W44: 336.85 | X44: =F44*0.09 -> 1212.66 | Y44: =F44*0.12 -> 1616.88 | AD44: 100 | AE44: =G44-SUM(J44:S44)-V44-X44-SUM(Z44:AB44)-T44 -> 5187.49 | AF44: 33
A45: 34 | F45: =SUM(F28:F44) -> 435773 | G45: =SUM(G28:G44) -> 217886.5 | H45: =SUM(H28:H44) -> 0 | I45: =SUM(I28:I44) -> 0 | J45: =SUM(J28:J44) -> 0 | K45: =SUM(K28:K44) -> 0 | L45: =SUM(L28:L44) -> 5008.69 | M45: =SUM(M28:M44) -> 4691.66 | ... AE45: =SUM(AE28:AE44) -> 94761.75 | AF45: 34 | AK45: 3 | AL45: ='Reg3(16-31)'!AE66 -> 381200.4
A46: 35 | B46: 1101 - Assessor | AF46: 35 | AK46: 4 | AL46: ='Reg4(16-31)'!AA62 -> 209050.96
A47: 36 | C47: Mun. Assessor | D47: Feb. 1-15, 2026 | F47: ='[1]Reg.2(1-15)'!$G$47 -> 88811 | G47: =F47/2 -> 44405.5 | V47: 2220.27 | W47: 2220.28 | X47: =F47*0.09 -> 7992.99 | Y47: =F47*0.12 -> 10657.32 | AD47: 100 | AE47: =G47-SUM(J47:S47)-V47-X47-SUM(Z47:AB47)-T47 -> 34192.24 | AF47: 36 | AK47: 5 | AL47: ='SB (16-31)'!AD44 -> 377608.69
A48: 37 | C48: Local Assessment Operations Officer II | D48: -d | E48: o- | F48: ='[1]Reg.2(1-15)'!$G$48 -> 34513 | G48: =F48/2 -> 17256.5 | P48: 150 | Q48: 983.33 | R48: 2282.25 | S48: 2553.13 | V48: 862.82 | W48: 862.83 | X48: =F48*0.09 -> 3106.17 | Y48: =F48*0.12 -> 4141.56 | Z48: 3349 | AA48: 2973.74 | AC48: 694.52 | AD48: 100 | AE48: =G48-SUM(J48:S48)-V48-X48-SUM(Z48:AB48)-T48-AC48 -> 301.54 | AF48: 37 | AK48: 6 | AL48: ='new hired co terminus'!AA16 -> 51339.39
A49: 38 | C49: Assessment Clerk III | D49: -d | E49: o- | F49: 19899 | G49: =F49/2 -> 9949.5 | L49: 410.52 | V49: 497.47 | W49: 497.48 | X49: =F49*0.09 -> 1790.91 | Y49: =F49*0.12 -> 2387.88 | AD49: 100 | AE49: =G49-SUM(J49:S49)-V49-X49-SUM(Z49:AB49)-T49 -> 7250.6 | AF49: 38 | AL49: =SUM(AL35:AL48) -> 1281184.9
A50: 39 | C50: Assessment Clerk II | D50: -d | E50: o- | F50: 16113 | G50: =F50/2 -> 8056.5 | V50: 402.82 | W50: 402.83 | X50: =F50*0.09 -> 1450.17 | Y50: =F50*0.12 -> 1933.56 | Z50: 3103.78 | AD50: 100 | AE50: =G50-SUM(J50:S50)-V50-X50-SUM(Z50:AB50)-T50 -> 3099.73 | AF50: 39
A51: 40 | C51: Admin. Aide IV | D51: -d | E51: o- | F51: ='[1]Reg.2(1-15)'!$G$51 -> 14521 | G51: =F51/2 -> 7260.5 | R51: 928.83 | V51: 363.02 | W51: 363.03 | X51: =F51*0.09 -> 1306.89 | Y51: =F51*0.12 -> 1742.52 | AA51: 1189.49 | AD51: 100 | AE51: =G51-SUM(J51:S51)-V51-X51-SUM(Z51:AB51)-T51 -> 3472.27 | AF51: 40
A52: 41 | C52: Admin. Aide III | D52: -d | E52: o- | F52: 13675 | G52: =F52/2 -> 6837.5 | L52: 516.19 | V52: 341.87 | W52: 341.88 | X52: =F52*0.09 -> 1230.75 | Y52: =F52*0.12 -> 1641 | AC52: 1233.49 | AD52: 100 | AE52: =G52-SUM(J52:S52)-V52-X52-SUM(Z52:AB52)-T52-AC52 -> 3515.2 | AF52: 41
A53: 42 | F53: =SUM(F47:F52) -> 187532 | G53: =SUM(G47:G52) -> 93766 | H53: =SUM(H47:H52) -> 0 | I53: =SUM(I47:I52) -> 0 | J53: =SUM(J47:J52) -> 0 | K53: =SUM(K47:K52) -> 0 | L53: =SUM(L47:L52) -> 926.71 | M53: =SUM(M47:M52) -> 0 | ... AE53: =SUM(AE47:AE52) -> 51831.58 | AF53: 42
A54: 43 | AF54: 43
A55: 44 | B55: TOTAL | F55: =F53+F45+F26 -> 961343 | G55: =G53+G45+G26 -> 480671.5 | H55: =H53+H45+H26 -> 0 | I55: =I53+I45+I26 -> 0 | J55: =J53+J45+J26 -> 0 | K55: =K53+K45+K26 -> 0 | L55: =L53+L45+L26 -> 6590.96 | M55: =M53+M45+M26 -> 6366.66 | ... AE55: =AE53+AE45+AE26 -> 214246.27 | AF55: 44
A57: (1) I HEREBY CERTIFY on my official oath that the above PAYROLL is correct, and that services above stated have been duly rendered. Payment for such services is also hereby approved from the appropriation indicated. | V57: (4) APPROVED | AD57: (5) I HEREBY CERTIFY on my official oath that I have paid in cash to each official and employee whose name appears on the above roll the amount set opposite his name, under column 28, he having signed or marked his name under column 30 above, in my presence and at the time that payment was made to him, in acknowledgement of receipt of the money paid him.
W60: HON. JANUARIO FERRY G. GARCIA
E61: HON. JANUARIO FERRY G. GARCIA | W61: Municipal Mayor
D62: Municipal Mayor | W62: Chief of Office
A64: (2) APPROVED for payment subject to preaudit:
E66: Treasurer | AE66: IRENE A. TAMONDONG
AE67: LRCO III
A68: (3) Preaudited and approved for payment in the month of | AD68: (6) I HEREBY CERTIFY on my official oath that each employee whose name appears on the above roll has been paid in cash or in check, and in no other mode, the amount shown under column 21 above, opposite his name. The total of the payments made by means this payroll amount to
C70: (P ) | E70: pesos only.
C73: Provincial Auditor | AE73: MINERVA L. BOONGALING
AE74: Mun. Treasurer

Sheet Reg.3(1-15)
A1: Municipal P A Y R O L L
A2: WE HEREBY ACKNOWLEDGE TO HAVE RECEIVED FROM MINERVA L. BOONGALING, TREASURER OF PAGSANJAN, LAGUNA THE SUMS HEREIN SPECIFIED OPPOSITES OUR RESPECTIVE NAMES, THE SAME BEING FULL COMPENSATION FOR OUR SERVICES RENDERED DURING THE PERIOD STATED BELOW, TO THE CORRECTNESS OF WHICH WE HEREBY SEVERALLY
A4: NO. | B4: NAME | C4: DESIGNATION | D4: PERIOD OF SERVICE (INCLUSIVE DATES) | G4: AMOUNT ACCRUED FOR THE PERIOD | K4: D E D U C T I O N S
D5: FROM | E5: TO | H5: HOUSING LOAN | I5: SOS | K5: GOVERNMENT SERVICE INSURANCE SYSTEM | T5: Adjustmnt (6mos) | U5: W/HOLDING TAX | V5: PHILHEALTH | Y5: GSIS | AA5: LBP | AB5: UCPB | AC5: Pag - ibig | AE5: GSIS | AF5: AMOUNT PAID IN CASH (CR.A-1) | AG5: N U M B E R
F6: MONTHLY RATE OF PAY | J6: ECAL / UMID | K6: CONSOLOAN | L6: EMERGENCY LOAN | M6: Educational Loan | N6: MPL Lite | O6: Policy Loan (Regularl) | P6: Policy Loan (Opitional) | Q6: COMPUTER LOAN | R6: MPLOAN | S6: GFAL | Y6: LIFE/RETIREMENT INSURANCE PREMIUM | AE6: STATE. INSURANCE | AH6: SIGNATURE OF PAYEE | AI6: REMARKS
V7: PERSONAL SHARE | W7: GOV'T. SHARE | X7: ACCTS PAYABLE | AC7: MPL | AD7: CAL
T8: PS | Y8: PERSONAL SHARE | Z8: GOVERNMENT SHARE
A10: 1 | B10: 2 | C10: 3 | D10: 4 | E10: 5 | F10: 6 | G10: 7 | H10: 8 | I10: 9 | J10: 11 | K10: 8 | L10: 9 | M10: 9 | N10: 10 | O10: 11 | P10: 12 | R10: 13 | S10: 14 | V10: 15 | W10: 16 | X10: 19 | Y10: 17 | Z10: 18 | AA10: 19 | AB10: 20 | AC10: 21 | AD10: 22 | AE10: 23 | AF10: 24 | AG10: 25 | AH10: 26 | AI10: 27
B11: 4411 -MHO
A12: 1 | C12: Mun. Health Officer | D12: Feb. 1-15, 2026 | F12: ='[1]Reg.3(1-15)'!$F$12 -> 109431 | G12: =F12/2 -> 54715.5 | R12: 9947.07 | U12: 6111.39 | V12: 2500 | W12: 2500 | Y12: =F12*0.09 -> 9848.79 | Z12: =F12*0.12 -> 13131.72 | AC12: 2257.52 | AE12: 100 | AF12: =G12-SUM(K12:U12)-V12-Y12-SUM(AA12:AC12)-T12 -> 24050.73 | AG12: 1
A13: 2 | C13: Public Health Nurse | D13: -d | E13: o- | F13: ='[1]Reg.3(1-15)'!$F$13 -> 50735 | G13: =F13/2 -> 25367.5 | K13: 2840.09 | L13: 551.06 | U13: 2174.08 | V13: 1268.37 | W13: 1268.38 | Y13: =F13*0.09 -> 4566.15 | Z13: =F13*0.12 -> 6088.2 | AC13: 1280.18 | AE13: 100 | AF13: =G13-SUM(K13:U13)-V13-Y13-SUM(AA13:AC13)-T13 -> 12687.57 | AG13: 2
A14: 3 | C14: Nurse II | D14: -d | E14: o- | F14: 43996 | G14: =F14/2 -> 21998 | U14: 1640.74 | V14: 1099.9 | W14: 1099.9 | Y14: =F14*0.09 -> 3959.64 | Z14: =F14*0.12 -> 5279.52 | AE14: 100 | AF14: =G14-SUM(K14:U14)-V14-Y14-SUM(AA14:AC14)-T14 -> 15297.72 | AG14: 3
A15: 4 | C15: Nurse I | D15: -d | E15: o- | F15: ='[1]Reg.3(1-15)'!$F$15 -> 40604 | G15: =F15/2 -> 20302 | U15: 1421.01 | V15: 1015.1 | W15: 1015.1 | Y15: =F15*0.09 -> 3654.36 | Z15: =F15*0.12 -> 4872.48 | AE15: 100 | AF15: =G15-SUM(K15:U15)-V15-Y15-SUM(AA15:AC15)-T15 -> 14211.53 | AG15: 4
A16: 5 | C16: Nurse I | D16: -d | E16: o- | F16: ='[1]Reg.3(1-15)'!$F$16 -> 40604 | G16: =F16/2 -> 20302 | L16: 785.2 | U16: 1421.01 | V16: 1015.1 | W16: 1015.1 | Y16: =F16*0.09 -> 3654.36 | Z16: =F16*0.12 -> 4872.48 | AE16: 100 | AF16: =G16-SUM(K16:U16)-V16-Y16-SUM(AA16:AC16)-T16 -> 13426.33 | AG16: 5
A17: 6 | C17: Nurse I | D17: -d | E17: o- | F17: ='[1]Reg.3(1-15)'!$F$17 -> 40604 | G17: =F17/2 -> 20302 | U17: 1421.01 | V17: 1015.1 | W17: 1015.1 | Y17: =F17*0.09 -> 3654.36 | Z17: =F17*0.12 -> 4872.48 | AA17: 9470.26 | AE17: 100 | AF17: =G17-SUM(K17:U17)-V17-Y17-SUM(AA17:AC17)-T17 -> 4741.27 | AG17: 6
A18: 7 | C18: MedTech | D18: -d | E18: o- | F18: ='[1]Reg.3(1-15)'!$F$18 -> 40604 | G18: =F18/2 -> 20302 | U18: 1421.01 | V18: 1015.1 | W18: 1015.1 | Y18: =F18*0.09 -> 3654.36 | Z18: =F18*0.12 -> 4872.48 | AE18: 100 | AF18: =G18-SUM(K18:U18)-V18-Y18-SUM(AA18:AC18)-T18 -> 14211.53 | AG18: 7
A19: 8 | C19: Computer Operator IV | D19: -d | E19: o- | F19: 37384 | G19: =F19/2 -> 18692 | U19: 1154.9 | V19: 934.6 | W19: 934.6 | Y19: =F19*0.09 -> 3364.56 | Z19: =F19*0.12 -> 4486.08 | AE19: 100 | AF19: =G19-SUM(K19:U19)-V19-Y19-SUM(AA19:AC19)-T19 -> 13237.94 | AG19: 8
A20: 9 | C20: Midwife IV | D20: -d | E20: o- | F20: ='[1]Reg.3(1-15)'!$F$20 -> 34421 | G20: =F20/2 -> 17210.5 | K20: 1654.52 | U20: 961.4 | V20: 860.75 | W20: 860.75 | Y20: =F20*0.09 -> 3097.89 | Z20: =F20*0.12 -> 4130.52 | AE20: 100 | AF20: =G20-SUM(K20:U20)-V20-Y20-SUM(AA20:AC20)-T20 -> 10635.94 | AG20: 9
A21: 10 | C21: Midwife III | D21: -d | E21: o- | F21: ='[1]Reg.3(1-15)'!$F$21 -> 30308 | G21: =F21/2 -> 15154 | U21: 655.68 | V21: 757.7 | W21: 757.7 | Y21: =F21*0.09 -> 2727.72 | Z21: =F21*0.12 -> 3636.96 | AE21: 100 | AF21: =G21-SUM(K21:U21)-V21-Y21-SUM(AA21:AC21)-T21 -> 11012.9 | AG21: 10
A22: 11 | C22: Midwife III | D22: -d | E22: o- | F22: ='[1]Reg.3(1-15)'!$F$22 -> 30308 | G22: =F22/2 -> 15154 | U22: 655.68 | V22: 757.7 | W22: 757.7 | Y22: =F22*0.09 -> 2727.72 | Z22: =F22*0.12 -> 3636.96 | AE22: 100 | AF22: =G22-SUM(K22:U22)-V22-Y22-SUM(AA22:AC22)-T22 -> 11012.9 | AG22: 11
A23: 12 | C23: Midwife III | D23: -d | E23: o- | F23: ='[1]Reg.3(1-15)'!$F$23 -> 30308 | G23: =F23/2 -> 15154 | U23: 655.68 | V23: 757.7 | W23: 757.7 | Y23: =F23*0.09 -> 2727.72 | Z23: =F23*0.12 -> 3636.96 | AE23: 100 | AF23: =G23-SUM(K23:U23)-V23-Y23-SUM(AA23:AC23)-T23 -> 11012.9 | AG23: 12
A24: 13 | C24: Midwife III | D24: -d | E24: o- | F24: ='[1]Reg.3(1-15)'!$F$24 -> 30024 | G24: =F24/2 -> 15012 | U24: 634.57 | V24: 750.6 | W24: 750.6 | Y24: =F24*0.09 -> 2702.16 | Z24: =F24*0.12 -> 3602.88 | AE24: 100 | AF24: =G24-SUM(K24:U24)-V24-Y24-SUM(AA24:AC24)-T24 -> 10924.67 | AG24: 13
A25: 14 | C25: Data Encoder III | D25: -d | E25: o- | F25: ='[1]Reg.3(1-15)'!$F$25 -> 30308 | G25: =F25/2 -> 15154 | R25: 593.79 | U25: 655.68 | V25: 757.7 | W25: 757.7 | Y25: =F25*0.09 -> 2727.72 | Z25: =F25*0.12 -> 3636.96 | AE25: 100 | AF25: =G25-SUM(K25:U25)-V25-Y25-SUM(AA25:AC25)-T25 -> 10419.11 | AG25: 14
A26: 15 | C26: Sanitary Inspector II | D26: -d | E26: o- | F26: ='[1]Reg.3(1-15)'!$F$26 -> 22035 | G26: =F26/2 -> 11017.5 | V26: 550.87 | W26: 550.88 | Y26: =F26*0.09 -> 1983.15 | Z26: =F26*0.12 -> 2644.2 | AA26: 6060.97 | AE26: 100 | AF26: =G26-SUM(K26:U26)-V26-Y26-SUM(AA26:AC26)-T26 -> 2422.51 | AG26: 15
A27: 16 | C27: Clerk IV | D27: -d | E27: o- | F27: ='[1]Reg.3(1-15)'!$F$27 -> 21642 | G27: =F27/2 -> 10821 | V27: 541.05 | W27: 541.05 | Y27: =F27*0.09 -> 1947.78 | Z27: =F27*0.12 -> 2597.04 | AE27: 100 | AF27: =G27-SUM(K27:S27)-V27-Y27-SUM(AA27:AC27)-T27 -> 8332.17 | AG27: 16
A28: 17 | C28: Nursing Attendant II | D28: -d | E28: o- | F28: 18957 | G28: =F28/2 -> 9478.5 | V28: 473.92 | W28: 473.93 | Y28: =F28*0.09 -> 1706.13 | Z28: =F28*0.12 -> 2274.84 | AE28: 100 | AF28: =G28-SUM(K28:S28)-V28-Y28-SUM(AA28:AC28)-T28 -> 7298.45 | AG28: 17
A29: 18 | C29: Sanitary Inspector I | D29: -d | E29: o- | F29: 18957 | G29: =F29/2 -> 9478.5 | V29: 473.92 | W29: 473.93 | Y29: =F29*0.09 -> 1706.13 | Z29: =F29*0.12 -> 2274.84 | AB29: 4982.14 | AE29: 100 | AF29: =G29-SUM(K29:S29)-V29-Y29-SUM(AA29:AC29)-T29 -> 2316.31 | AG29: 18
A30: 19 | C30: Admin. Aide III | D30: -d | E30: o- | F30: ='[1]Reg.3(1-15)'!$F$30 -> 17209 | G30: =F30/2 -> 8604.5 | L30: 584.69 | R30: 1497.1 | V30: 430.22 | W30: 430.23 | Y30: =F30*0.09 -> 1548.81 | Z30: =F30*0.12 -> 2065.08 | AE30: 100 | AF30: =G30-SUM(K30:S30)-V30-Y30-SUM(AA30:AC30)-T30 -> 4543.68 | AG30: 19
A31: 20 | C31: Driver II | D31: -d | E31: o- | F31: 16833 | G31: =F31/2 -> 8416.5 | L31: 655.56 | V31: 420.82 | W31: 420.83 | Y31: =F31*0.09 -> 1514.97 | Z31: =F31*0.12 -> 2019.96 | AB31: 2973.74 | AE31: 100 | AF31: =G31-SUM(K31:S31)-V31-Y31-SUM(AA31:AC31)-T31 -> 2851.41 | AG31: 20
A32: 21 | C32: Admin. Aide III | D32: -d | E32: o- | F32: ='[1]Reg.3(1-15)'!$F$32 -> 16088 | G32: =F32/2 -> 8044 | V32: 402.2 | W32: 402.2 | Y32: =F32*0.09 -> 1447.92 | Z32: =F32*0.12 -> 1930.56 | AE32: 100 | AF32: =G32-SUM(K32:S32)-V32-Y32-SUM(AA32:AC32)-T32 -> 6193.88 | AG32: 21
A33: 22 | C33: Admin. Aide III | D33: -d | E33: o- | F33: 15852 | G33: =F33/2 -> 7926 | N33: 475 | V33: 396.3 | W33: 396.3 | Y33: =F33*0.09 -> 1426.68 | Z33: =F33*0.12 -> 1902.24 | AE33: 100 | AF33: =G33-SUM(K33:S33)-V33-Y33-SUM(AA33:AC33)-T33 -> 5628.02 | AG33: 22
A34: 23 | F34: =SUM(F12:F33) -> 737212 | G34: =SUM(G12:G33) -> 368606 | H34: =SUM(H12:H33) -> 0 | I34: =SUM(I12:I33) -> 0 | J34: =SUM(J12:J33) -> 0 | K34: =SUM(K12:K33) -> 4494.61 | L34: =SUM(L12:L33) -> 2576.51 | M34: =SUM(M12:M33) -> 0 | ... AF34: =SUM(AF12:AF33) -> 216469.47 | AG34: 23
A35: 24 | B35: 7999 - Local Youth & Sports Devt. Office | AG35: 24
A36: 25 | C36: Admin. Aide III | D36: Feb. 1-15, 2026 | F36: ='[1]Reg.3(1-15)'!$F$36 -> 13575 | G36: =F36/2 -> 6787.5 | V36: 339.37 | W36: =F36*0.025 -> 339.375 | Y36: =F36*0.09 -> 1221.75 | Z36: =F36*0.12 -> 1629 | AA36: 2000 | AE36: 100 | AF36: =G36-SUM(K36:S36)-V36-Y36-SUM(AA36:AC36)-T36 -> 3226.38 | AG36: 25
A37: 26 | F37: =F36 -> 13575 | G37: =G36 -> 6787.5 | H37: =H36 -> 0 | I37: =I36 -> 0 | J37: =J36 -> 0 | K37: =K36 -> 0 | L37: =L36 -> 0 | M37: =M36 -> 0 | ... AF37: =AF36 -> 3226.38 | AG37: 26
A38: 27 | B38: 6531 - GSO Streetlighting | AG38: 27
A39: 28 | C39: Admin. Aide III | D39: Feb. 1-15, 2026 | F39: ='[1]Reg.3(1-15)'!$F$39 -> 13675 | G39: =F39/2 -> 6837.5 | Q39: 1966.67 | R39: 658.45 | V39: 341.87 | W39: 341.88 | Y39: =F39*0.09 -> 1230.75 | Z39: =F39*0.12 -> 1641 | AA39: 1538.74 | AE39: 100 | AF39: =G39-SUM(K39:S39)-V39-Y39-SUM(AA39:AC39)-T39 -> 1101.02 | AG39: 28
A40: 29 | F40: =SUM(F39:F39) -> 13675 | G40: =SUM(G39:G39) -> 6837.5 | H40: =SUM(H39:H39) -> 0 | I40: =SUM(I39:I39) -> 0 | J40: =SUM(J39:J39) -> 0 | K40: =SUM(K39:K39) -> 0 | L40: =SUM(L39:L39) -> 0 | M40: =SUM(M39:M39) -> 0 | ... AF40: =SUM(AF39:AF39) -> 1101.02 | AG40: 29
A41: 30 | B41: 7611 -MSWD | AG41: 30
A42: 31 | C42: SWOII- OIC MSWDO | D42: Feb. 1-15, 2026 | F42: 34855 | G42: =F42/2 -> 17427.5 | V42: 871.37 | W42: 871.38 | Y42: =F42*0.09 -> 3136.95 | Z42: =F42*0.12 -> 4182.6 | AE42: 100 | AF42: =G42-SUM(K42:S42)-V42-Y42-SUM(AA42:AC42)-T42 -> 13419.18 | AG42: 31
A43: 32 | C43: Daycare Worker II | D43: -d | E43: o- | F43: ='[1]Reg.3(1-15)'!$F$43 -> 19417 | G43: =F43/2 -> 9708.5 | L43: 655.56 | N43: 1166.66 | Q43: 983.34 | V43: 485.42 | W43: 485.43 | Y43: =F43*0.09 -> 1747.53 | Z43: =F43*0.12 -> 2330.04 | AA43: 4205.89 | AE43: 100 | AF43: =G43-SUM(K43:S43)-V43-Y43-SUM(AA43:AC43)-T43 -> 464.1 | AG43: 32
A44: 33 | C44: Daycare Worker I | D44: -d | E44: o- | F44: ='[1]Reg.3(1-15)'!$F$44 -> 18563 | G44: =F44/2 -> 9281.5 | K44: 951.67 | V44: 464.07 | W44: 464.08 | Y44: =F44*0.09 -> 1670.67 | Z44: =F44*0.12 -> 2227.56 | AE44: 100 | AF44: =G44-SUM(K44:S44)-V44-Y44-SUM(AA44:AC44)-T44 -> 6195.09 | AG44: 33
A45: 34 | C45: Social Welfare Asst. | D45: -d | E45: o- | F45: ='[1]Reg.3(1-15)'!$F$45 -> 18396 | G45: =F45/2 -> 9198 | V45: 459.9 | W45: 459.9 | Y45: =F45*0.09 -> 1655.64 | Z45: =F45*0.12 -> 2207.52 | AA45: 2998.92 | AB45: 1500 | AE45: 100 | AF45: =G45-SUM(K45:S45)-V45-Y45-SUM(AA45:AC45)-T45 -> 2583.54 | AG45: 34
A46: 36 | C46: Daycare Worker I | D46: -d | E46: o- | F46: ='[1]Reg.3(1-15)'!$F$46 -> 16969 | G46: =F46/2 -> 8484.5 | Q46: 983.33 | R46: 1109.65 | V46: 424.22 | W46: 424.23 | Y46: =F46*0.09 -> 1527.21 | Z46: =F46*0.12 -> 2036.28 | AC46: 1435.8 | AE46: 100 | AF46: =G46-SUM(K46:S46)-V46-Y46-SUM(AA46:AC46)-T46 -> 3004.29 | AG46: 36
A47: 37 | C47: Daycare Worker I | D47: -d | E47: o- | F47: ='[1]Reg.3(1-15)'!$F$47 -> 16233 | G47: =F47/2 -> 8116.5 | V47: 405.82 | W47: 405.83 | Y47: =F47*0.09 -> 1460.97 | Z47: =F47*0.12 -> 1947.96 | AE47: 100 | AF47: =G47-SUM(K47:S47)-V47-Y47-SUM(AA47:AC47)-T47 -> 6249.71 | AG47: 37
A48: 38 | C48: Daycare Worker I | D48: -d | E48: o- | F48: 16113 | G48: =F48/2 -> 8056.5 | N48: 475 | R48: 476.6 | V48: 402.82 | W48: 402.83 | Y48: =F48*0.09 -> 1450.17 | Z48: =F48*0.12 -> 1933.56 | AA48: 2000 | AE48: 100 | AF48: =G48-SUM(K48:S48)-V48-Y48-SUM(AA48:AC48)-T48 -> 3251.91 | AG48: 38
A49: 39 | C49: Social Welfare Aide I | D49: -d | E49: o- | F49: ='[1]Reg.3(1-15)'!$F$49 -> 14521 | G49: =F49/2 -> 7260.5 | V49: 363.02 | W49: 363.03 | Y49: =F49*0.09 -> 1306.89 | Z49: =F49*0.12 -> 1742.52 | AA49: 2535.56 | AE49: 100 | AF49: =G49-SUM(K49:S49)-V49-Y49-SUM(AA49:AC49)-T49 -> 3055.03 | AG49: 39
A50: 40 | C50: Social Welfare Aide I | D50: -d | E50: o- | F50: ='[1]Reg.3(1-15)'!$F$50 -> 14414 | G50: =F50/2 -> 7207 | V50: 360.35 | W50: 360.35 | Y50: =F50*0.09 -> 1297.26 | Z50: =F50*0.12 -> 1729.68 | AA50: 1500 | AE50: 100 | AF50: =G50-SUM(K50:S50)-V50-Y50-SUM(AA50:AC50)-T50 -> 4049.39 | AG50: 40
A51: 41 | C51: Social Welfare Aide I | D51: -d | E51: o- | F51: 14308 | G51: =F51/2 -> 7154 | R51: 423.21 | V51: 357.7 | W51: 357.7 | Y51: =F51*0.09 -> 1287.72 | Z51: =F51*0.12 -> 1716.96 | AA51: 3567.51 | AE51: 100 | AF51: =G51-SUM(K51:S51)-V51-Y51-SUM(AA51:AC51)-T51 -> 1517.86 | AG51: 41
A52: 42 | C52: Social Welfare Aide I | D52: -d | E52: o- | F52: 14308 | G52: =F52/2 -> 7154 | N52: 475 | R52: 423.21 | V52: 357.7 | W52: 357.7 | Y52: =F52*0.09 -> 1287.72 | Z52: =F52*0.12 -> 1716.96 | AA52: 3772.32 | AE52: 100 | AF52: =G52-SUM(K52:S52)-V52-Y52-SUM(AA52:AC52)-T52 -> 838.05 | AG52: 42
A53: 43 | C53: Admin. Aide III | D53: -d | E53: o- | F53: ='[1]Reg.3(1-15)'!$F$53 -> 13675 | G53: =F53/2 -> 6837.5 | R53: 496.43 | V53: 341.87 | W53: 341.88 | Y53: =F53*0.09 -> 1230.75 | Z53: =F53*0.12 -> 1641 | AE53: 100 | AF53: =G53-SUM(K53:S53)-V53-Y53-SUM(AA53:AC53)-T53 -> 4768.45 | AG53: 43
A54: 44 | C54: Admin. Aide III | D54: -d | E54: o- | F54: ='[1]Reg.3(1-15)'!$F$54 -> 13575 | G54: =F54/2 -> 6787.5 | V54: 339.37 | W54: 339.38 | Y54: =F54*0.09 -> 1221.75 | Z54: =F54*0.12 -> 1629 | AA54: 1122.58 | AB54: 2164.88 | AE54: 100 | AF54: =G54-SUM(K54:S54)-V54-Y54-SUM(AA54:AC54)-T54 -> 1938.92 | AG54: 44
A55: 45 | C55: Admin. Aide III | D55: -d | E55: o- | F55: ='[1]Reg.3(1-15)'!$F$55 -> 13575 | G55: =F55/2 -> 6787.5 | V55: 339.37 | W55: 339.38 | Y55: =F55*0.09 -> 1221.75 | Z55: =F55*0.12 -> 1629 | AA55: 1656.75 | AE55: 100 | AF55: =G55-SUM(K55:S55)-V55-Y55-SUM(AA55:AC55)-T55 -> 3569.63 | AG55: 45
A56: 46 | F56: =SUM(F42:F55) -> 238922 | G56: =SUM(G42:G55) -> 119461 | H56: =SUM(H42:H55) -> 0 | I56: =SUM(I42:I55) -> 0 | J56: =SUM(J42:J55) -> 0 | K56: =SUM(K42:K55) -> 951.67 | L56: =SUM(L42:L55) -> 655.56 | M56: =SUM(M42:M55) -> 0 | ... AF56: =SUM(AF42:AF55) -> 54905.15 | AG56: 46
A57: 47 | B57: 7999 - Local Youth & Sports Devt. Office | AG57: 47
A58: 48 | C58: Admin. Aide III | D58: Oct. 1-15, 2021 | F58: 0 | G58: =F58/2 -> 0 | V58: 0 | W58: 0 | Y58: =F58*0.09 -> 0 | Z58: =F58*0.12 -> 0 | AA58: 0 | AB58: 0 | AE58: 0 | AF58: =G58-SUM(K58:S58)-V58-Y58-SUM(AA58:AC58) -> 0 | AG58: 48
A59: 49 | F59: =F58 -> 0 | G59: =G58 -> 0 | H59: =H58 -> 0 | I59: =I58 -> 0 | J59: =J58 -> 0 | K59: =K58 -> 0 | L59: =L58 -> 0 | M59: =M58 -> 0 | ... S59: =S58 -> 0 | V59: =V58 -> 0 | W59: =W58 -> 0 | X59: =X58 -> 0 | Y59: =Y58 -> 0 | Z59: =Z58 -> 0 | AA59: =AA58 -> 0 | AB59: =AB58 -> 0 | AC59: =AC58 -> 0 | ... AF59: =AF58 -> 0 | AG59: 49
A60: 50 | B60: 8711 - Agriculture | AG60: 50
A61: 52 | C61: Agriculturist II- OIC Mun. Agriculturist | D61: Feb. 1-15, 2026 | F61: ='[1]Reg.3(1-15)'!$F$61 -> 34177 | G61: =F61/2 -> 17088.5 | L61: 514.91 | R61: 1816.74 | S61: 4817.22 | V61: 854.42 | W61: 854.43 | Y61: =F61*0.09 -> 3075.93 | Z61: =F61*0.12 -> 4101.24 | AA61: =2258.27 -> 2258.27 | AE61: 100 | AF61: =G61-SUM(K61:S61)-V61-Y61-SUM(AA61:AC61)-T61 -> 3751.01 | AG61: 52
A62: 53 | C62: Agriculturist I | D62: -d | E62: o- | F62: ='[1]Reg.3(1-15)'!$F$62 -> 25520 | G62: =F62/2 -> 12760 | V62: 638 | W62: 638 | Y62: =F62*0.09 -> 2296.8 | Z62: =F62*0.12 -> 3062.4 | AE62: 100 | AF62: =G62-SUM(K62:S62)-V62-Y62-SUM(AA62:AC62)-T62 -> 9825.2 | AG62: 53
A63: 54 | C63: Farm Supervisor | D63: -d | E63: o- | F63: ='[1]Reg.3(1-15)'!$F$63 -> 18563 | G63: =F63/2 -> 9281.5 | V63: 464.07 | W63: 464.08 | Y63: =F63*0.09 -> 1670.67 | Z63: =F63*0.12 -> 2227.56 | AA63: 2626.12 | AE63: 100 | AF63: =G63-SUM(K63:S63)-V63-Y63-SUM(AA63:AC63)-T63 -> 4520.64 | AG63: 54
A64: 55 | C64: Farm Foreman | D64: -d | E64: o- | F64: ='[1]Reg.3(1-15)'!$F$64 -> 16113 | G64: =F64/2 -> 8056.5 | L64: 655.56 | N64: 700 | Q64: 983.34 | R64: 767.81 | V64: 402.82 | W64: 402.83 | Y64: =F64*0.09 -> 1450.17 | Z64: =F64*0.12 -> 1933.56 | AA64: 2461.98 | AE64: 100 | AF64: =G64-SUM(K64:S64)-V64-Y64-SUM(AA64:AC64)-T64 -> 634.82 | AG64: 55
A65: 56 | C65: Admin. Aide III | D65: -d | E65: o- | F65: ='[1]Reg.3(1-15)'!$F$65 -> 13675 | G65: =F65/2 -> 6837.5 | R65: 1120.32 | V65: 341.87 | W65: 341.88 | Y65: =F65*0.09 -> 1230.75 | Z65: =F65*0.12 -> 1641 | AE65: 100 | AF65: =G65-SUM(K65:S65)-V65-Y65-SUM(AA65:AC65)-T65 -> 4144.56 | AG65: 56
A66: 57 | C66: Admin. Aide III | D66: -d | E66: o- | F66: ='[1]Reg.3(1-15)'!$F$66 -> 13675 | G66: =F66/2 -> 6837.5 | L66: 558.12 | R66: 1096.88 | V66: 341.87 | W66: 341.88 | Y66: =F66*0.09 -> 1230.75 | Z66: =F66*0.12 -> 1641 | AC66: 1463.86 | AE66: 100 | AF66: =G66-SUM(K66:S66)-V66-Y66-SUM(AA66:AC66)-T66 -> 2146.02 | AG66: 57
A67: 58 | C67: Admin. Aide III | D67: -d | E67: o- | F67: ='[1]Reg.3(1-15)'!$F$67 -> 13474 | G67: =F67/2 -> 6737 | N67: 475 | V67: 336.85 | W67: 336.85 | Y67: =F67*0.09 -> 1212.66 | Z67: =F67*0.12 -> 1616.88 | AB67: 2844.13 | AE67: 100 | AF67: =G67-SUM(K67:S67)-V67-Y67-SUM(AA67:AC67)-T67 -> 1868.36 | AG67: 58
A68: 59 | F68: =SUM(F61:F67) -> 135197 | G68: =SUM(G61:G67) -> 67598.5 | H68: =SUM(H61:H67) -> 0 | I68: =SUM(I61:I67) -> 0 | J68: =SUM(J61:J67) -> 0 | K68: =SUM(K61:K67) -> 0 | L68: =SUM(L61:L67) -> 1728.59 | M68: =SUM(M61:M67) -> 0 | ... AF68: =SUM(AF61:AF67) -> 26890.61 | AG68: 59
A69: 60 | B69: TOTAL | F69: =F68+F59+F56+F40+F37+F34 -> 1138581 | G69: =G68+G59+G56+G40+G37+G34 -> 569290.5 | H69: =H68+H59+H56+H40+H37+H34 -> 0 | I69: =I68+I59+I56+I40+I37+I34 -> 0 | J69: =J68+J59+J56+J40+J37+J34 -> 0 | K69: =K68+K59+K56+K40+K37+K34 -> 5446.28 | L69: =L68+L59+L56+L40+L37+L34 -> 4960.66 | M69: =M68+M59+M56+M40+M37+M34 -> 0 | ... AF69: =AF68+AF59+AF56+AF40+AF37+AF34 -> 302592.63 | AG69: 60
L70: .
AE71: (5) I HEREBY CERTIFY on my official oath that I have paid in cash to each official and employee whose name appears on the above roll the amount set opposite his name, under column 28, he having signed or marked his name under column 30 above, in my presence and at the time that payment was made to him, in acknowledgement of receipt of the money paid him.
A72: (1) I HEREBY CERTIFY on my official oath that the above PAYROLL is correct, and that services above stated have been duly rendered. Payment for such services is also hereby approved from the appropriation indicated. | H72: (4) APPROVED | S72: (4) APPROVED:
D76: HON. JANUARIO FERRY G. GARCIA | V76: HON. JANUARIO FERRY G. GARCIA
D77: Municipal Mayor | V77: Municipal Mayor
A79: (2) APPROVED for payment subject to preaudit: | AF79: IRENE A. TAMONDONG
AF80: LRCO III
E81: Treasurer | AE81: (6) I HEREBY CERTIFY on my official oath that each employee whose name appears on the above roll has been paid in cash or in check, and in no other mode, the amount shown under column 21 above, opposite his name. The total of the payments made by means this payroll amount to
A82: (3) Preaudited and approved for payment in the month of
C84: (P ) | E84: pesos only.
C86: Provincial Auditor | AF86: MINERVA L. BOONGALING
AF87: Mun. Treasurer

Sheet Reg.4(1-15)
A1: Municipal P A Y R O L L
A2: WE HEREBY ACKNOWLEDGE TO HAVE RECEIVED FROM MINERVA L. BOONGALING, TREASURER OF PAGSANJAN, LAGUNA THE SUMS HEREIN SPECIFIED OPPOSITES OUR RESPECTIVE NAMES, THE SAME BEING FULL COMPENSATION FOR OUR SERVICES RENDERED DURING THE PERIOD STATED BELOW, TO THE CORRECTNESS OF WHICH WE HEREBY SEVERALLY
A4: NO. | B4: NAME | C4: DESIGNATION | D4: PERIOD OF SERVICE (INCLUSIVE DATES) | G4: AMOUNT ACCRUED FOR THE PERIOD | H4: D E D U C T I O N S
D5: FROM | E5: TO | H5: HOUSING LOAN | I5: SOS | M5: PERA (AUG.) | N5: GOVERNMENT SERVICE INSURANCE SYSTEM | W5: PHILHEALTH | Y5: GOVERNMENT SERVICE INSURANCE SYSTEM | AA5: LBP | AB5: UCPB | AC5: Pag - ibig | AE5: GSIS | AF5: AMOUNT PAID IN CASH (CR.A-1) | AG5: N U M B E R
F6: MONTHLY RATE OF PAY | K6: ECAL / UMID | L6: Differential (Jan. 16-31/2022) | N6: CONSOLOAN | O6: EMERGENCY LOAN | P6: MPL Lite | Q6: Policy Loan (Regular) | R6: COMPUTER LOAN | S6: MPL | T6: GFAL | Y6: LIFE/RETIREMENT INSURANCE PREMIUM | AE6: STATE. INSURANCE | AH6: SIGNATURE OF PAYEE | AI6: REMARKS
U7: Adjustmnt (6mos) | W7: PERSONAL SHARE | X7: GOV'T. SHARE | AC7: MPL | AD7: CAL
U8: PS | V8: GS | Y8: PERSONAL SHARE | Z8: GOVERNMENT SHARE
A10: 1 | B10: 2 | C10: 3 | D10: 4 | E10: 5 | F10: 6 | G10: 7 | H10: 8 | I10: 9 | J10: 10 | K10: 8 | N10: 10 | O10: 9 | P10: 16 | Q10: 11 | R10: 12 | S10: 13 | T10: 14 | W10: 15 | X10: 16 | Y10: 17 | Z10: 18 | AA10: 19 | AB10: 20 | AC10: 21 | AD10: 22 | AE10: 23 | AF10: 24 | AG10: 25 | AH10: 26 | AI10: 27
B11: 8731-MENRO
A12: 1 | C12: MGDH I | D12: Feb. 1-15, 2026 | F12: ='[1]Reg.4(1-15)'!$F$12 -> 83457 | G12: =F12/2 -> 41728.5 | O12: 655.56 | P12: 1513.89 | S12: 2590.62 | W12: 2086.42 | X12: 2086.43 | Y12: =F12*0.09 -> 7511.13 | Z12: =F12*0.12 -> 10014.84 | AB12: 3515.97 | AC12: 2620.77 | AE12: 100 | AF12: =G12-SUM(N12:T12)-W12-Y12-SUM(AA12:AC12)-U12 -> 21234.14 | AG12: 1
A13: 2 | C13: Driver II | D13: -d | E13: o- | F13: ='[1]Reg.4(1-15)'!$F$13 -> 14521 | G13: =F13/2 -> 7260.5 | P13: 1100 | S13: 849 | W13: 363.02 | X13: 363.03 | Y13: =F13*0.09 -> 1306.89 | Z13: =F13*0.12 -> 1742.52 | AA13: 2777.29 | AE13: 100 | AF13: =G13-SUM(N13:T13)-W13-Y13-SUM(AA13:AC13)-U13 -> 864.3 | AG13: 2
A14: 3 | C14: Laborer II | D14: -d | E14: o- | F14: ='[1]Reg.4(1-15)'!$F$14 -> 14189 | G14: =F14/2 -> 7094.5 | O14: 501.08 | S14: 965.08 | W14: 354.72 | X14: 354.73 | Y14: =F14*0.09 -> 1277.01 | Z14: =F14*0.12 -> 1702.68 | AA14: 1413.98 | AC14: 1206.43 | AE14: 100 | AF14: =G14-SUM(N14:T14)-W14-Y14-SUM(AA14:AC14)-U14 -> 1376.2 | AG14: 3
A15: 4 | C15: Laborer II | D15: -d | E15: o- | F15: ='[1]Reg.4(1-15)'!$F$15 -> 14189 | G15: =F15/2 -> 7094.5 | O15: 592 | S15: 965.07 | W15: 354.72 | X15: 354.73 | Y15: =F15*0.09 -> 1277.01 | Z15: =F15*0.12 -> 1702.68 | AA15: 1952.12 | AE15: 100 | AF15: =G15-SUM(N15:T15)-W15-Y15-SUM(AA15:AC15)-U15 -> 1953.58 | AG15: 4
A16: 6 | C16: Admin. Aide IV | D16: -d | E16: o- | F16: 14308 | G16: =F16/2 -> 7154 | W16: 357.7 | X16: 357.7 | Y16: =F16*0.09 -> 1287.72 | Z16: =F16*0.12 -> 1716.96 | AA16: 4419.46 | AE16: 100 | AF16: =G16-SUM(N16:T16)-W16-Y16-SUM(AA16:AC16)-U16 -> 1089.12 | AG16: 6
A17: 5 | C17: Laborer II | D17: -d | E17: o- | F17: 13357 | G17: =F17/2 -> 6678.5 | O17: 655.56 | R17: 983.34 | S17: 1105.16 | W17: 333.92 | X17: 333.93 | Y17: =F17*0.09 -> 1202.13 | Z17: =F17*0.12 -> 1602.84 | AC17: 1536.56 | AE17: 100 | AF17: =G17-SUM(N17:T17)-W17-Y17-SUM(AA17:AC17)-U17 -> 861.83 | AG17: 5
A18: 7 | C18: Admin. Aide III | D18: -d | E18: o- | F18: ='[1]Reg.4(1-15)'!$F$18 -> 13675 | G18: =F18/2 -> 6837.5 | R18: 983.33 | S18: 767.82 | W18: 341.87 | X18: 341.88 | Y18: =F18*0.09 -> 1230.75 | Z18: =F18*0.12 -> 1641 | AA18: 1585.95 | AB18: 1784.24 | AE18: 100 | AF18: =G18-SUM(N18:T18)-W18-Y18-SUM(AA18:AC18)-U18 -> 143.54 | AG18: 7
A19: 8 | C19: Admin. Aide III | D19: -d | E19: o- | F19: 13675 | G19: =F19/2 -> 6837.5 | S19: 797.95 | W19: 341.87 | X19: 341.88 | Y19: =F19*0.09 -> 1230.75 | Z19: =F19*0.12 -> 1641 | AA19: 1104.86 | AB19: 2275.3 | AE19: 100 | AF19: =G19-SUM(N19:T19)-W19-Y19-SUM(AA19:AC19)-U19 -> 1086.77 | AG19: 8
A20: 9 | C20: Admin. Aide III | D20: -d | E20: o- | F20: 13575 | G20: =F20/2 -> 6787.5 | O20: 1311.12 | P20: 300 | W20: 339.37 | X20: 339.38 | Y20: =F20*0.09 -> 1221.75 | Z20: =F20*0.12 -> 1629 | AA20: 3103.31 | AE20: 100 | AF20: =G20-SUM(N20:T20)-W20-Y20-SUM(AA20:AC20)-U20 -> 511.95 | AG20: 9
A21: 10 | C21: Admin. Aide III | D21: -d | E21: o- | F21: 13575 | G21: =F21/2 -> 6787.5 | W21: 339.37 | X21: 339.38 | Y21: =F21*0.09 -> 1221.75 | Z21: =F21*0.12 -> 1629 | AA21: 2698.48 | AE21: 100 | AF21: =G21-SUM(N21:T21)-W21-Y21-SUM(AA21:AC21)-U21 -> 2527.9 | AG21: 10
A22: 11 | C22: Admin. Aide III | D22: -d | E22: o- | F22: ='[1]Reg.4(1-15)'!$F$22 -> 13474 | G22: =F22/2 -> 6737 | W22: 336.85 | X22: 336.85 | Y22: =F22*0.09 -> 1212.66 | Z22: =F22*0.12 -> 1616.88 | AA22: 1676.21 | AB22: =1613.36+1613.36 -> 3226.72 | AE22: 100 | AF22: =G22-SUM(N22:T22)-W22-Y22-SUM(AA22:AC22)-U22+M22 -> 284.56 | AG22: 11
A23: 12 | F23: =SUM(F12:F22) -> 221995 | G23: =SUM(G12:G22) -> 110997.5 | H23: =SUM(H12:H22) -> 0 | I23: =SUM(I12:I22) -> 0 | J23: =SUM(J12:J22) -> 0 | K23: =SUM(K12:K22) -> 0 | L23: =SUM(L12:L22) -> 0 | M23: =SUM(M12:M22) -> 0 | ... AF23: =SUM(AF12:AF22) -> 31933.89 | AG23: 12
A24: 13 | B24: 8751 - Engineering | AG24: 13
A25: 14 | C25: Mun. Engr. | D25: Feb. 1-15, 2026 | F25: ='[1]Reg.4(1-15)'!$F$25 -> 90205 | G25: =F25/2 -> 45102.5 | P25: 1166.66 | R25: 1966.67 | S25: =6467.2+1139.66 -> 7606.86 | W25: 2255.12 | X25: 2255.13 | Y25: =F25*0.09 -> 8118.45 | Z25: =F25*0.12 -> 10824.6 | AA25: 9644.22 | AB25: 8000 | AE25: 100 | AF25: =G25-SUM(N25:T25)-W25-Y25-SUM(AA25:AC25)-U25 -> 6344.52 | AG25: 14
A26: 15 | C26: Engr. II | D26: -d | E26: o- | F26: ='[1]Reg.4(1-15)'!$F$26 -> 37026 | G26: =F26/2 -> 18513 | W26: 925.65 | X26: 925.65 | Y26: =F26*0.09 -> 3332.34 | Z26: =F26*0.12 -> 4443.12 | AE26: 100 | AF26: =G26-SUM(N26:T26)-W26-Y26-SUM(AA26:AC26)-U26 -> 14255.01 | AG26: 15
A27: 16 | C27: Eng'g. Aide II | D27: -d | E27: o- | F27: 14308 | G27: =F27/2 -> 7154 | W27: 357.7 | X27: 357.7 | Y27: =F27*0.09 -> 1287.72 | Z27: =F27*0.12 -> 1716.96 | AE27: 100 | AF27: =G27-SUM(N27:T27)-W27-Y27-SUM(AA27:AC27)-U27 -> 5508.58 | AG27: 16
A28: 18 | C28: Admin. Aide III | D28: -d | E28: o- | F28: ='[1]Reg.4(1-15)'!$F$28 -> 13675 | G28: =F28/2 -> 6837.5 | W28: 341.87 | X28: 341.88 | Y28: =F28*0.09 -> 1230.75 | Z28: =F28*0.12 -> 1641 | AA28: 3156.75 | AE28: 100 | AF28: =G28-SUM(N28:T28)-W28-Y28-SUM(AA28:AC28)-U28 -> 2108.13 | AG28: 18
A29: 19 | C29: Admin. Aide III | D29: -d | E29: o- | F29: ='[1]Reg.4(1-15)'!$F$29 -> 13474 | G29: =F29/2 -> 6737 | W29: 336.85 | X29: 336.85 | Y29: =F29*0.09 -> 1212.66 | Z29: =F29*0.12 -> 1616.88 | AE29: 100 | AF29: =G29-SUM(N29:T29)-W29-Y29-SUM(AA29:AC29)-U29 -> 5187.49 | AG29: 19
A30: 20 | C30: Admin. Aide III | D30: -d | E30: o- | F30: ='[1]Reg.4(1-15)'!$F$30 -> 13474 | G30: =F30/2 -> 6737 | W30: 336.85 | X30: 336.85 | Y30: =F30*0.09 -> 1212.66 | Z30: =F30*0.12 -> 1616.88 | AE30: 100 | AF30: =G30-SUM(N30:T30)-W30-Y30-SUM(AA30:AC30)-U30 -> 5187.49 | AG30: 20
A31: 21 | C31: Admin. Aide III | D31: -d | E31: o- | F31: ='[1]Reg.4(1-15)'!$F$31 -> 13474 | G31: =F31/2 -> 6737 | W31: 336.85 | X31: 336.85 | Y31: =F31*0.09 -> 1212.66 | Z31: =F31*0.12 -> 1616.88 | AE31: 100 | AF31: =G31-SUM(N31:T31)-W31-Y31-SUM(AA31:AC31)-U31 -> 5187.49 | AG31: 21
A32: 22 | F32: =SUM(F25:F31) -> 195636 | G32: =SUM(G25:G31) -> 97818 | H32: =SUM(H25:H31) -> 0 | I32: =SUM(I25:I31) -> 0 | J32: =SUM(J25:J31) -> 0 | K32: =SUM(K25:K31) -> 0 | L32: =SUM(L25:L31) -> 0 | N32: =SUM(N25:N31) -> 0 | O32: =SUM(O25:O31) -> 0 | P32: =SUM(P25:P31) -> 1166.66 | Q32: =SUM(Q25:Q31) -> 0 | R32: =SUM(R25:R31) -> 1966.67 | S32: =SUM(S25:S31) -> 7606.86 | T32: =SUM(T25:T31) -> 0 | U32: =SUM(U25:U31) -> 0 | ... AF32: =SUM(AF25:AF31) -> 43778.71 | AG32: 22
A33: 23 | B33: 8852 - Tourism | AF33: =G33-N33-O33-P33-Q33-R33-S33-T33-W33-Y33-AA33-AB33-AC33 -> 0 | AG33: 23
A34: 24 | C34: Mun. Tourism Operations Officer | D34: Feb. 1-15, 2026 | F34: ='[1]Reg.4(1-15)'!$F$34 -> 87440 | G34: =F34/2 -> 43720 | W34: 2186 | X34: 2186 | Y34: =F34*0.09 -> 7869.6 | Z34: =F34*0.12 -> 10492.8 | AE34: 100 | AF34: =G34-SUM(N34:T34)-W34-Y34-SUM(AA34:AC34)-U34 -> 33664.4 | AG34: 24
A35: 25 | C35: Foreman B | D35: -d | E35: o- | F35: ='[1]Reg.4(1-15)'!$F$35 -> 18730 | G35: =F35/2 -> 9365 | W35: 468.25 | X35: 468.25 | Y35: =F35*0.09 -> 1685.7 | Z35: =F35*0.12 -> 2247.6 | AE35: 100 | AF35: =G35-SUM(N35:T35)-W35-Y35-SUM(AA35:AC35)-U35 -> 7211.05 | AG35: 25
A36: 26 | C36: Laborer II | D36: -d | E36: o- | F36: ='[1]Reg.4(1-15)'!$F$36 -> 14189 | G36: =F36/2 -> 7094.5 | W36: 354.72 | X36: 354.73 | Y36: =F36*0.09 -> 1277.01 | Z36: =F36*0.12 -> 1702.68 | AE36: 100 | AF36: =G36-SUM(N36:T36)-W36-Y36-SUM(AA36:AC36)-U36 -> 5462.77 | AG36: 26
A37: 27 | C37: Laborer II | D37: -d | E37: o- | F37: 13675 | G37: =F37/2 -> 6837.5 | O37: 1311.12 | W37: 341.87 | X37: 341.88 | Y37: =F37*0.09 -> 1230.75 | Z37: =F37*0.12 -> 1641 | AA37: 2037.7 | AE37: 100 | AF37: =G37-SUM(N37:T37)-W37-Y37-SUM(AA37:AC37)-U37 -> 1916.06 | AG37: 27
A38: 28 | C38: Admin. Aide III | D38: -d | E38: o- | F38: ='[1]Reg.4(1-15)'!$F$38 -> 13675 | G38: =F38/2 -> 6837.5 | N38: =373.86 -> 373.86 | O38: 655.56 | W38: 341.87 | X38: 341.88 | Y38: =F38*0.09 -> 1230.75 | Z38: =F38*0.12 -> 1641 | AB38: 1305.53 | AE38: 100 | AF38: =G38-SUM(N38:T38)-W38-Y38-SUM(AA38:AC38)-U38 -> 2929.93 | AG38: 28
A39: 29 | C39: Admin. Aide III | D39: -d | E39: o- | F39: ='[1]Reg.4(1-15)'!$F$39 -> 13675 | G39: =F39/2 -> 6837.5 | W39: 341.87 | X39: 341.88 | Y39: =F39*0.09 -> 1230.75 | Z39: =F39*0.12 -> 1641 | AA39: 2664.18 | AE39: 100 | AF39: =G39-SUM(N39:T39)-W39-Y39-SUM(AA39:AC39)-U39 -> 2600.7 | AG39: 29
A40: 30 | C40: Admin. Aide III | D40: -d | E40: o- | F40: ='[1]Reg.4(1-15)'!$F$40 -> 13474 | G40: =F40/2 -> 6737 | W40: 336.85 | X40: 336.85 | Y40: =F40*0.09 -> 1212.66 | Z40: =F40*0.12 -> 1616.88 | AA40: 3700 | AE40: 100 | AF40: =G40-SUM(N40:T40)-W40-Y40-SUM(AA40:AC40)-U40 -> 1487.49 | AG40: 30
A41: 31 | F41: =SUM(F34:F40) -> 174858 | G41: =SUM(G34:G40) -> 87429 | H41: =SUM(H34:H40) -> 0 | I41: =SUM(I34:I40) -> 0 | J41: =SUM(J34:J40) -> 0 | K41: =SUM(K34:K40) -> 0 | L41: =SUM(L34:L40) -> 0 | N41: =SUM(N34:N40) -> 373.86 | O41: =SUM(O34:O40) -> 1966.68 | P41: =SUM(P34:P40) -> 0 | Q41: =SUM(Q34:Q40) -> 0 | R41: =SUM(R34:R40) -> 0 | S41: =SUM(S34:S40) -> 0 | T41: =SUM(T34:T40) -> 0 | U41: =SUM(U34:U40) -> 0 | ... AF41: =SUM(AF34:AF40) -> 55272.4 | AG41: 31
A42: 32 | B42: 8811 - Market (OM) | AG42: 32
A43: 33 | C43: Laborer II | D43: Feb. 1-15, 2026 | F43: ='[1]Reg.4(1-15)'!$F$43 -> 13675 | G43: =F43/2 -> 6837.5 | K43: 0 | P43: 0 | W43: 341.87 | X43: 341.88 | Y43: =F43*0.09 -> 1230.75 | Z43: =F43*0.12 -> 1641 | AA43: 988.75 | AB43: 2275.31 | AD43: 0 | AE43: 100 | AF43: =G43-SUM(N43:T43)-W43-Y43-SUM(AA43:AC43)-U43 -> 2000.82 | AG43: 33
A44: 34 | C44: Laborer II | D44: -d | E44: o- | F44: ='[1]Reg.4(1-15)'!$F$44 -> 13675 | G44: =F44/2 -> 6837.5 | K44: 0 | O44: 655.56 | Q44: 200 | R44: 300 | S44: 500 | W44: 341.87 | X44: 341.88 | Y44: =F44*0.09 -> 1230.75 | Z44: =F44*0.12 -> 1641 | AA44: 1210.91 | AB44: 1763.89 | AD44: 0 | AE44: 100 | AF44: =G44-SUM(N44:T44)-W44-Y44-SUM(AA44:AC44)-U44 -> 634.52 | AG44: 34
A45: 35 | F45: =SUM(F43:F44) -> 27350 | G45: =SUM(G43:G44) -> 13675 | H45: =SUM(H43:H44) -> 0 | I45: =SUM(I43:I44) -> 0 | J45: =SUM(J43:J44) -> 0 | K45: =SUM(K43:K44) -> 0 | L45: =SUM(L43:L44) -> 0 | N45: =SUM(N43:N44) -> 0 | O45: =SUM(O43:O44) -> 655.56 | P45: =SUM(P43:P44) -> 0 | Q45: =SUM(Q43:Q44) -> 200 | R45: =SUM(R43:R44) -> 300 | S45: =SUM(S43:S44) -> 500 | T45: =SUM(T43:T44) -> 0 | U45: =SUM(U43:U44) -> 0 | ... AF45: =SUM(AF43:AF44) -> 2635.34 | AG45: 35
A46: 36 | B46: 8841 - Cemetery (OM) | AG46: 36
A47: 37 | C47: Admin. Aide I | D47: Feb. 1-15, 2026 | F47: ='[1]Reg.4(1-15)'!$F$47 -> 11952 | G47: =F47/2 -> 5976 | O47: 587.17 | W47: 298.8 | X47: 298.8 | Y47: =F47*0.09 -> 1075.68 | Z47: =F47*0.12 -> 1434.24 | AA47: 1761.04 | AB47: 1800 | AE47: 100 | AF47: =G47-SUM(N47:T47)-W47-Y47-SUM(AA47:AC47)-U47 -> 453.31 | AG47: 37
A48: 38 | C48: Laborer II | D48: -d | E48: o- | F48: ='[1]Reg.4(1-15)'!$F$48 -> 13474 | G48: =F48/2 -> 6737 | W48: 336.85 | X48: 336.85 | Y48: =F48*0.09 -> 1212.66 | Z48: =F48*0.12 -> 1616.88 | AA48: 3945.94 | AE48: 100 | AF48: =G48-SUM(N48:T48)-W48-Y48-SUM(AA48:AC48)-U48 -> 1241.55 | AG48: 38
A49: 39 | F49: =SUM(F47:F48) -> 25426 | G49: =SUM(G47:G48) -> 12713 | H49: =SUM(H47:H48) -> 0 | I49: =SUM(I47:I48) -> 0 | J49: =SUM(J47:J48) -> 0 | K49: =SUM(K47:K48) -> 0 | L49: =SUM(L47:L48) -> 0 | N49: =SUM(N47:N48) -> 0 | O49: =SUM(O47:O48) -> 587.17 | P49: =SUM(P47:P48) -> 0 | Q49: =SUM(Q47:Q48) -> 0 | R49: =SUM(R47:R48) -> 0 | S49: =SUM(S47:S48) -> 0 | U49: =SUM(U47:U48) -> 0 | V49: =SUM(V47:V48) -> 0 | W49: =SUM(W47:W48) -> 635.65 | X49: =SUM(X47:X48) -> 635.65 | Y49: =SUM(Y47:Y48) -> 2288.34 | Z49: =SUM(Z47:Z48) -> 3051.12 | AA49: =SUM(AA47:AA48) -> 5706.98 | AB49: =SUM(AB47:AB48) -> 1800 | ... AF49: =SUM(AF47:AF48) -> 1694.86 | AG49: 39
A50: 40 | B50: 9941- MDRRM | AG50: 40
A51: 42 | C51: Bookbinder III | D51: Feb. 1-15, 2026 | F51: ='[1]Reg.4(1-15)'!$F$51 -> 17094 | G51: =F51/2 -> 8547 | O51: 655.36 | S51: 1174.49 | W51: 427.35 | X51: 427.35 | Y51: =F51*0.09 -> 1538.46 | Z51: =F51*0.12 -> 2051.28 | AA51: 3156.75 | AE51: 100 | AF51: =G51-SUM(N51:T51)-W51-Y51-SUM(AA51:AC51)-U51 -> 1594.59 | AG51: 42
A52: 43 | C52: Admin. Aide IV | D52: -d | E52: o- | F52: ='[1]Reg.4(1-15)'!$F$52 -> 14414 | G52: =F52/2 -> 7207 | R52: 983.33 | S52: 840.78 | W52: 360.35 | X52: 360.35 | Y52: =F52*0.09 -> 1297.26 | Z52: =F52*0.12 -> 1729.68 | AB52: 2260.05 | AE52: 100 | AF52: =G52-SUM(N52:T52)-W52-Y52-SUM(AA52:AC52)-U52 -> 1465.23 | AG52: 43
A53: 44 | C53: Admin. Aide IV | D53: -d | E53: o- | F53: ='[1]Reg.4(1-15)'!$F$53 -> 14308 | G53: =F53/2 -> 7154 | P53: 583.33 | W53: 357.7 | X53: 357.7 | Y53: =F53*0.09 -> 1287.72 | Z53: =F53*0.12 -> 1716.96 | AB53: 3336.66 | AC53: 687.32 | AE53: 100 | AF53: =G53-SUM(N53:T53)-W53-Y53-SUM(AA53:AC53)-U53 -> 901.27 | AG53: 44
A54: 45 | C54: Admin. Aide IV | D54: -d | E54: o- | F54: ='[1]Reg.4(1-15)'!$F$54 -> 14308 | G54: =F54/2 -> 7154 | W54: 357.7 | X54: =357.7 -> 357.7 | Y54: =F54*0.09 -> 1287.72 | Z54: =F54*0.12 -> 1716.96 | AE54: 100 | AF54: =G54-SUM(N54:T54)-W54-Y54-SUM(AA54:AC54)-U54 -> 5508.58 | AG54: 45
A55: 46 | C55: Admin. Aide IV | D55: -d | E55: o- | F55: ='[1]Reg.4(1-15)'!$F$55 -> 14308 | G55: =F55/2 -> 7154 | S55: 695.21 | W55: 357.7 | X55: 357.7 | Y55: =F55*0.09 -> 1287.72 | Z55: =F55*0.12 -> 1716.96 | AB55: 2521.73 | AE55: 100 | AF55: =G55-SUM(N55:T55)-W55-Y55-SUM(AA55:AC55)-U55 -> 2291.64 | AG55: 46
A56: 47 | C56: Admin. Aide IV | D56: -d | E56: o- | F56: ='[1]Reg.4(1-15)'!$F$56 -> 14308 | G56: =F56/2 -> 7154 | W56: 357.7 | X56: 357.7 | Y56: =F56*0.09 -> 1287.72 | Z56: =F56*0.12 -> 1716.96 | AE56: 100 | AF56: =G56-SUM(N56:T56)-W56-Y56-SUM(AA56:AC56)-U56 -> 5508.58 | AG56: 47
A57: 48 | C57: Admin. Aide III | D57: -d | E57: o- | F57: ='[1]Reg.4(1-15)'!$F$57 -> 13474 | G57: =F57/2 -> 6737 | W57: 336.85 | X57: =336.85 -> 336.85 | Y57: =F57*0.09 -> 1212.66 | Z57: =F57*0.12 -> 1616.88 | AE57: 100 | AF57: =G57-SUM(N57:T57)-W57-Y57-SUM(AA57:AC57)-U57 -> 5187.49 | AG57: 48
A58: 49 | C58: Admin. Aide III | D58: -d | E58: o- | F58: ='[1]Reg.4(1-15)'!$F$58 -> 13474 | G58: =F58/2 -> 6737 | W58: 336.85 | X58: =336.85 -> 336.85 | Y58: =F58*0.09 -> 1212.66 | Z58: =F58*0.12 -> 1616.88 | AE58: 100 | AF58: =G58-SUM(N58:T58)-W58-Y58-SUM(AA58:AC58)-U58 -> 5187.49 | AG58: 49
A59: 50 | C59: Admin. Aide III | D59: -d | E59: o- | F59: ='[1]Reg.4(1-15)'!$F$59 -> 13474 | G59: =F59/2 -> 6737 | W59: 336.85 | X59: =336.85 -> 336.85 | Y59: =F59*0.09 -> 1212.66 | Z59: =F59*0.12 -> 1616.88 | AE59: 100 | AF59: =G59-SUM(N59:T59)-W59-Y59-SUM(AA59:AC59)-U59 -> 5187.49 | AG59: 50
A60: 51 | C60: Admin. Aide III | D60: -d | E60: o- | F60: ='[1]Reg.4(1-15)'!$F$60 -> 13474 | G60: =F60/2 -> 6737 | W60: 336.85 | X60: =336.85 -> 336.85 | Y60: =F60*0.09 -> 1212.66 | Z60: =F60*0.12 -> 1616.88 | AE60: 100 | AF60: =G60-SUM(N60:T60)-W60-Y60-SUM(AA60:AC60)-U60 -> 5187.49 | AG60: 51
A61: 52 | F61: =SUM(F51:F60) -> 142636 | G61: =SUM(G51:G60) -> 71318 | H61: =SUM(H51:H60) -> 0 | I61: =SUM(I51:I60) -> 0 | J61: =SUM(J51:J60) -> 0 | K61: =SUM(K51:K60) -> 0 | L61: =SUM(L51:L60) -> 0 | M61: =SUM(M51:M60) -> 0 | ... AF61: =SUM(AF51:AF60) -> 38019.85 | AG61: 52
A62: 53 | B62: TOTAL | F62: =F61+F49+F45+F41+F32+F23 -> 787901 | G62: =G61+G49+G45+G41+G32+G23 -> 393950.5 | H62: =H61+H49+H45+H41+H32+H23 -> 0 | I62: =I61+I49+I45+I41+I32+I23 -> 0 | J62: =J61+J49+J45+J41+J32+J23 -> 0 | K62: =K61+K49+K45+K41+K32+K23 -> 0 | L62: =L61+L49+L45+L41+L32+L23 -> 0 | M62: =M61+M49+M45+M41+M32+M23 -> 0 | ... AF62: =AF61+AF49+AF45+AF41+AF32+AF23 -> 173335.05 | AG62: 53
O63: .
AE64: (5) I HEREBY CERTIFY on my official oath that I have paid in cash to each official and employee whose name appears on the above roll the amount set opposite his name, under column 28, he having signed or marked his name under column 30 above, in my presence and at the time that payment was made to him, in acknowledgement of receipt of the money paid him.
A65: (1) I HEREBY CERTIFY on my official oath that the above PAYROLL is correct, and that services above stated have been duly rendered. Payment for such services is also hereby approved from the appropriation indicated. | H65: (4) APPROVED | T65: (4) APPROVED:
D69: HON. JANUARIO FERRY G. GARCIA | W69: HON. JANUARIO FERRY G. GARCIA
D70: Municipal Mayor | W70: Municipal Mayor
A72: (2) APPROVED for payment subject to preaudit: | AF72: IRENE A. TAMONDONG
AF73: LRCO III
E74: Treasurer | AE74: (6) I HEREBY CERTIFY on my official oath that each employee whose name appears on the above roll has been paid in cash or in check, and in no other mode, the amount shown under column 21 above, opposite his name. The total of the payments made by means this payroll amount to
A75: (3) Preaudited and approved for payment in the month of
C77: (P ) | E77: pesos only.
C79: Provincial Auditor | AF79: MINERVA L. BOONGALING
AF80: Mun. Treasurer

Sheet SB(1-15)
A1: Municipal P A Y R O L L
A2: WE HEREBY ACKNOWLEDGE TO HAVE RECEIVED FROM MINERVA L. BOONGALING, TREASURER OF PAGSANJAN, LAGUNA THE SUMS HEREIN SPECIFIED OPPOSITES OUR RESPECTIVE NAMES, THE SAME BEING FULL COMPENSATION FOR OUR SERVICES RENDERED DURING THE PERIOD STATED BELOW, TO THE CORRECTNESS OF WHICH WE HEREBY SEVERALLY
A4: NO. | B4: NAME | C4: DESIGNATION | D4: PERIOD OF SERVICE (INCLUSIVE DATES) | G4: AMOUNT ACCRUED FOR THE PERIOD | H4: D E D U C T I O N S
D5: FROM | E5: TO | H5: PERA (FEB.) | I5: GOVERNMENT SERVICE INSURANCE SYSTEM | W5: PHILHEALTH | Y5: GSIS | AA5: LBP | AB5: UCPB | AC5: Pag-ibig | AE5: GSIS | AF5: AMOUNT PAID IN CASH (CR.A-1) | AG5: N U M B E R
F6: MONTHLY RATE OF PAY | I6: CONSOLOAN | J6: Emergency Loan | K6: Educ. Loan | L6: ECAL/ UMID | M6: POLICY LOAN (Regular) | N6: POLICY LOAN (Optional) | O6: MPL Lite | P6: COMPUTER LOAN | Q6: MPL | R6: LRP | S6: GFAL | Y6: LIFE/RETIREMENT INSURANCE PREMIUM | AE6: STATE. INSURANCE | AH6: SIGNATURE OF PAYEE | AI6: REMARKS
U7: Adjustmnt (6mos) | W7: PERSONAL SHARE | X7: GOV'T. SHARE | AC7: MPL | AD7: CAL.
U8: PS | V8: GS | Y8: PERSONAL SHARE | Z8: GOVERNMENT SHARE
A10: 1 | B10: 2 | C10: 3 | D10: 4 | E10: 5 | F10: 6 | G10: 7 | H10: 9 | I10: 8 | J10: 9 | K10: 10 | L10: 11 | M10: 11 | N10: 12 | O10: 13 | P10: 14 | Q10: 15 | S10: 16 | W10: 17 | X10: 18 | Y10: 19 | Z10: 20 | AA10: 21 | AB10: 22 | AC10: 23 | AD10: 24 | AE10: 25 | AF10: 27 | AG10: 28 | AH10: 29 | AI10: 30
B11: 1016- VM
A12: 1 | C12: Municipal Vice Mayor | D12: Feb. 1-15, 2026 | F12: 94968 | G12: =F12/2 -> 47484 | M12: 127 | W12: 2374.2 | X12: =W12 -> 2374.2 | Y12: =F12*0.09 -> 8547.12 | Z12: =F12*0.12 -> 11396.16 | AA12: 10000 | AE12: 100 | AF12: =G12-SUM(I12:S12)-W12-Y12-SUM(AA12:AD12)-U12 -> 26435.68 | AG12: 1
A13: 2 | C13: Executive Asst. I | D13: -d | E13: o- | F13: 31470 | G13: =F13/2 -> 15735 | H13: 2000 | W13: 786.75 | X13: 786.75 | Y13: =F13*0.09 -> 2832.3 | Z13: =F13*0.12 -> 3776.4 | AE13: 100 | AF13: =G13-SUM(I13:S13)-W13-Y13-SUM(AA13:AD13)-U13+H13 -> 14115.95 | AG13: 2
A14: 3 | C14: Private Sec. I | D14: -d | E14: o- | F14: 25520 | G14: =F14/2 -> 12760 | W14: 638 | X14: 638 | Y14: =F14*0.09 -> 2296.8 | Z14: =F14*0.12 -> 3062.4 | AE14: 100 | AF14: =G14-SUM(I14:S14)-W14-Y14-SUM(AA14:AD14)-U14 -> 9825.2 | AG14: 3
A15: 5 | C15: Personal Driver | D15: -d | E15: o- | F15: 13474 | G15: =F15/2 -> 6737 | H15: 2000 | W15: 336.85 | X15: 336.85 | Y15: =F15*0.09 -> 1212.66 | Z15: =F15*0.12 -> 1616.88 | AE15: 100 | AF15: =G15-SUM(I15:S15)-W15-Y15-SUM(AA15:AD15)-U15+H15 -> 7187.49 | AG15: 5
A16: 4 | C16: Admin. Aide I | D16: -d | E16: o- | F16: 12039 | G16: =F16/2 -> 6019.5 | S16: 0 | W16: 300.97 | X16: 300.98 | Y16: =F16*0.09 -> 1083.51 | Z16: =F16*0.12 -> 1444.68 | AC16: 455 | AE16: 100 | AF16: =G16-SUM(I16:S16)-W16-Y16-SUM(AA16:AD16)-U16 -> 4180.02 | AG16: 4
A17: 6 | F17: =SUM(F12:F16) -> 177471 | G17: =SUM(G12:G16) -> 88735.5 | H17: =SUM(H12:H16) -> 4000 | I17: =SUM(I12:I16) -> 0 | J17: =SUM(J12:J16) -> 0 | K17: =SUM(K12:K16) -> 0 | L17: =SUM(L12:L16) -> 0 | M17: =SUM(M12:M16) -> 127 | ... AF17: =SUM(AF12:AF16) -> 61744.34 | AG17: 6
A18: 7 | B18: 1021 - SB | AG18: 7
A19: 8 | C19: SB Member | D19: Feb. 1-15, 2026 | F19: ='[1]SB(1-15)'!$F$20 -> 84763 | G19: =F19/2 -> 42381.5 | W19: 2119.07 | X19: 2119.08 | Y19: =F19*0.09 -> 7628.67 | Z19: =F19*0.12 -> 10171.56 | AE19: 100 | AF19: =G19-SUM(I19:S19)-W19-Y19-SUM(AA19:AD19)-U19 -> 32633.76 | AG19: 8
A20: 9 | C20: SB Member | D20: -d | E20: o- | F20: ='[1]SB(1-15)'!$F$21 -> 83457 | G20: =F20/2 -> 41728.5 | W20: 2086.42 | X20: 2086.43 | Y20: =F20*0.09 -> 7511.13 | Z20: =F20*0.12 -> 10014.84 | AA20: 10000 | AE20: 100 | AF20: =G20-SUM(I20:S20)-W20-Y20-SUM(AA20:AD20)-U20 -> 22130.95 | AG20: 9
A21: 10 | C21: SB Member | D21: -d | E21: o- | F21: ='[1]SB(1-15)'!$F$22 -> 83457 | G21: =F21/2 -> 41728.5 | W21: 2086.42 | X21: 2086.43 | Y21: =F21*0.09 -> 7511.13 | Z21: =F21*0.12 -> 10014.84 | AE21: 100 | AF21: =G21-SUM(I21:S21)-W21-Y21-SUM(AA21:AD21)-U21 -> 32130.95 | AG21: 10
A22: 11 | C22: SB Member | D22: -d | E22: o- | F22: ='[1]SB(1-15)'!$F$23 -> 87440 | G22: =F22/2 -> 43720 | W22: 2186 | X22: 2186 | Y22: =F22*0.09 -> 7869.6 | Z22: =F22*0.12 -> 10492.8 | AE22: 100 | AF22: =G22-SUM(I22:S22)-W22-Y22-SUM(AA22:AD22)-U22 -> 33664.4 | AG22: 11
A23: 12 | C23: SB Member | D23: -d | E23: o- | F23: ='[1]SB(1-15)'!$F$24 -> 87440 | G23: =F23/2 -> 43720 | R23: 3255.22 | W23: 2186 | X23: 2186 | Y23: =F23*0.09 -> 7869.6 | Z23: =F23*0.12 -> 10492.8 | AE23: 100 | AF23: =G23-SUM(I23:S23)-W23-Y23-SUM(AA23:AD23)-U23 -> 30409.18 | AG23: 12
A24: 13 | C24: SB Member | D24: -d | E24: o- | F24: ='[1]SB(1-15)'!$F$25 -> 83457 | G24: =F24/2 -> 41728.5 | W24: 2086.42 | X24: 2086.43 | Y24: =F24*0.09 -> 7511.13 | Z24: =F24*0.12 -> 10014.84 | AE24: 100 | AF24: =G24-SUM(I24:S24)-W24-Y24-SUM(AA24:AD24)-U24 -> 32130.95 | AG24: 13
A25: 14 | C25: SB Member | D25: -d | E25: o- | F25: ='[1]SB(1-15)'!$F$26 -> 87440 | G25: =F25/2 -> 43720 | AF25: =G25-SUM(I25:S25)-W25-Y25-SUM(AA25:AD25)-U25 -> 43720 | AG25: 14
A26: 15 | C26: SB Member | D26: -d | E26: o- | F26: ='[1]SB(1-15)'!$F$27 -> 83457 | G26: =F26/2 -> 41728.5 | W26: 2086.42 | X26: 2086.43 | Y26: =F26*0.09 -> 7511.13 | Z26: =F26*0.12 -> 10014.84 | AE26: 100 | AF26: =G26-SUM(I26:S26)-W26-Y26-SUM(AA26:AD26)-U26 -> 32130.95 | AG26: 15
A27: 16 | C27: SB Member | D27: -d | E27: o- | F27: ='[1]SB(1-15)'!$F$28 -> 83457 | G27: =F27/2 -> 41728.5 | W27: 2086.42 | X27: 2086.43 | Y27: =F27*0.09 -> 7511.13 | Z27: =F27*0.12 -> 10014.84 | AE27: 100 | AF27: =G27-SUM(I27:S27)-W27-Y27-SUM(AA27:AD27)-U27 -> 32130.95 | AG27: 16
A28: 17 | C28: Admin Officer V | D28: -d | E28: o- | F28: ='[1]SB(1-15)'!$F$29 -> 44057 | G28: =F28/2 -> 22028.5 | J28: 655.56 | O28: 1166.66 | S28: 3853.78 | W28: 1101.42 | X28: 1101.43 | Y28: =F28*0.09 -> 3965.13 | Z28: =F28*0.12 -> 5286.84 | AA28: 4662.08 | AB28: 0 | AC28: 3370.92 | AE28: 100 | AF28: =G28-SUM(I28:S28)-W28-Y28-SUM(AA28:AD28)-U28 -> 3252.95 | AG28: 17
A29: 18 | C29: Bookbinder IV | D29: -d | E29: o- | F29: ='[1]SB(1-15)'!$F$30 -> 22097 | G29: =F29/2 -> 11048.5 | O29: 1166.67 | Q29: 1953.51 | W29: 552.42 | X29: 552.43 | Y29: =F29*0.09 -> 1988.73 | Z29: =F29*0.12 -> 2651.64 | AB29: 0 | AE29: 100 | AF29: =G29-SUM(I29:S29)-W29-Y29-SUM(AA29:AD29)-U29 -> 5387.17 | AG29: 18
A30: 19 | C30: Admin. Aide IV | D30: -d | E30: o- | F30: ='[1]SB(1-15)'!$F$31 -> 14308 | G30: =F30/2 -> 7154 | W30: 357.7 | X30: 357.7 | Y30: =F30*0.09 -> 1287.72 | Z30: =F30*0.12 -> 1716.96 | AB30: 2735.84 | AE30: 100 | AF30: =G30-SUM(I30:S30)-W30-Y30-SUM(AA30:AD30)-U30 -> 2772.74 | AG30: 19
A31: 20 | C31: Admin. Aide IV | D31: -d | E31: o- | F31: ='[1]SB(1-15)'!$F$32 -> 14308 | G31: =F31/2 -> 7154 | W31: 357.7 | X31: 357.7 | Y31: =F31*0.09 -> 1287.72 | Z31: =F31*0.12 -> 1716.96 | AB31: 2844.13 | AE31: 100 | AF31: =G31-SUM(I31:S31)-W31-Y31-SUM(AA31:AD31)-U31 -> 2664.45 | AG31: 20
A32: 21 | C32: Admin. Aide III | D32: -d | E32: o- | F32: ='[1]SB(1-15)'!$F$33 -> 13575 | G32: =F32/2 -> 6787.5 | J32: 311.12 | Q32: 354.89 | W32: 339.37 | X32: 339.38 | Y32: =F32*0.09 -> 1221.75 | Z32: =F32*0.12 -> 1629 | AA32: 1735.42 | AB32: 1300 | AC32: 1000 | AE32: 100 | AF32: =G32-SUM(I32:S32)-W32-Y32-SUM(AA32:AD32)-U32 -> 524.95 | AG32: 21
A33: 22 | C33: Admin. Aide III | D33: -d | E33: o- | F33: ='[1]SB(1-15)'!$F$34 -> 13474 | G33: =F33/2 -> 6737 | W33: 336.85 | X33: 336.85 | Y33: =F33*0.09 -> 1212.66 | Z33: =F33*0.12 -> 1616.88 | AE33: 100 | AF33: =G33-SUM(I33:S33)-W33-Y33-SUM(AA33:AD33)-U33 -> 5187.49 | AG33: 22
A34: 23 | F34: =SUM(F19:F33) -> 886187 | G34: =SUM(G19:G33) -> 443093.5 | H34: =SUM(H19:H33) -> 0 | I34: =SUM(I19:I33) -> 0 | J34: =SUM(J19:J33) -> 966.68 | K34: =SUM(K19:K33) -> 0 | L34: =SUM(L19:L33) -> 0 | M34: =SUM(M19:M33) -> 0 | ... AF34: =SUM(AF19:AF33) -> 310871.84 | AG34: 23
A35: 24 | B35: 1022 - SB Secretariat | X35: =W35 -> 0 | AG35: 24
A36: 25 | C36: SB Secretary | D36: Feb. 1-15, 2026 | F36: ='[1]SB(1-15)'!$F$37 -> 93016 | G36: =F36/2 -> 46508 | Q36: 7957.69 | S36: 4817.22 | W36: 2325.4 | X36: 2325.4 | Y36: =F36*0.09 -> 8371.44 | Z36: =F36*0.12 -> 11161.92 | AB36: 11657.07 | AC36: 2055.82 | AE36: 100 | AF36: =G36-SUM(I36:S36)-W36-Y36-SUM(AA36:AD36)-U36 -> 9323.36 | AG36: 25
A37: 26 | C37: Record Ofcr. I | D37: -d | E37: o- | F37: ='[1]SB(1-15)'!$F$38 -> 22097 | G37: =F37/2 -> 11048.5 | W37: 552.42 | X37: 552.43 | Y37: =F37*0.09 -> 1988.73 | Z37: =F37*0.12 -> 2651.64 | AE37: 100 | AF37: =G37-SUM(I37:S37)-W37-Y37-SUM(AA37:AD37)-U37 -> 8507.35 | AG37: 26
A38: 27 | C38: Bookbinder IV | D38: -d | E38: o- | F38: ='[1]SB(1-15)'!$F$39 -> 21748 | G38: =F38/2 -> 10874 | O38: 1166.67 | W38: 543.7 | X38: 543.7 | Y38: =F38*0.09 -> 1957.32 | Z38: =F38*0.12 -> 2609.76 | AA38: 4103.31 | AD38: 0 | AE38: 100 | AF38: =G38-SUM(I38:S38)-W38-Y38-SUM(AA38:AD38)-U38 -> 3103 | AG38: 27
A39: 28 | C39: Bookbinder IV | D39: -d | E39: o- | F39: ='[1]SB(1-15)'!$F$40 -> 21748 | G39: =F39/2 -> 10874 | I39: 298.27 | O39: 700 | W39: 543.7 | X39: 543.7 | Y39: =F39*0.09 -> 1957.32 | Z39: =F39*0.12 -> 2609.76 | AB39: 0 | AE39: 100 | AF39: =G39-SUM(I39:S39)-W39-Y39-SUM(AA39:AD39)-U39 -> 7374.71 | AG39: 28
A40: 29 | C40: Admin. Asst. II | D40: -d | E40: o- | F40: ='[1]SB(1-15)'!$F$41 -> 18231 | G40: =F40/2 -> 9115.5 | J40: 655.56 | O40: 1166.67 | P40: 600 | Q40: 1139.94 | W40: 455.77 | X40: 455.78 | Y40: =F40*0.09 -> 1640.79 | Z40: =F40*0.12 -> 2187.72 | AA40: 849.17 | AB40: 640.49 | AC40: 908.85 | AD40: 670.3 | AE40: 100 | AF40: =G40-SUM(I40:S40)-W40-Y40-SUM(AA40:AD40)-U40 -> 387.96 | AG40: 29
A41: 30 | C41: Local Legislative Staff I | D41: -d | E41: o- | F41: ='[1]SB(1-15)'!$F$42 -> 16233 | G41: =F41/2 -> 8116.5 | W41: 405.82 | X41: 405.83 | Y41: =F41*0.09 -> 1460.97 | Z41: =F41*0.12 -> 1947.96 | AE41: 100 | AF41: =G41-SUM(I41:S41)-W41-Y41-SUM(AA41:AD41)-U41 -> 6249.71 | AG41: 30
A42: 31 | F42: =SUM(F36:F41) -> 193073 | G42: =SUM(G36:G41) -> 96536.5 | H42: =SUM(H36:H41) -> 0 | I42: =SUM(I36:I41) -> 298.27 | J42: =SUM(J36:J41) -> 655.56 | K42: =SUM(K36:K41) -> 0 | L42: =SUM(L36:L41) -> 0 | M42: =SUM(M36:M41) -> 0 | ... AF42: =SUM(AF36:AF41) -> 34946.09 | AG42: 31
A43: 32 | AG43: 32
A44: 33 | B44: TOTAL | F44: =F42+F34+F17 -> 1256731 | G44: =G42+G34+G17 -> 628365.5 | H44: =H42+H34+H17 -> 4000 | I44: =I42+I34+I17 -> 298.27 | J44: =J42+J34+J17 -> 1622.24 | K44: =K42+K34+K17 -> 0 | L44: =L42+L34+L17 -> 0 | M44: =M42+M34+M17 -> 127 | ... AF44: =AF42+AF34+AF17 -> 407562.27 | AG44: 33
AE46: (5) I HEREBY CERTIFY on my official oath that I have paid in cash to each official and employee whose name appears on the above roll the amount set opposite his name, under column 28, he having signed or marked his name under column 30 above, in my presence and at the time that payment was made to him, in acknowledgement of receipt of the money paid him.
A47: (1) I HEREBY CERTIFY on my official oath that the above PAYROLL is correct, and that services above stated have been duly rendered. Payment for such services is also hereby approved from the appropriation indicated.
S48: (4) APPROVED:
C51: HON. ROD H. FERNANDEZ | W51: HON. ROD H. FERNANDEZ
C52: Municipal Vice Mayor | W52: Municipal Vice Mayor
W53: Chief of Office | AF53: IRENE A. TAMONDONG
A54: (2) APPROVED for payment subject to preaudit: | AF54: LRCO III
E56: Treasurer | AE56: (6) I HEREBY CERTIFY on my official oath that each employee whose name appears on the above roll has been paid in cash or in check, and in no other mode, the amount shown under column 21 above, opposite his name. The total of the payments made by means this payroll amount to
A58: (3) Preaudited and approved for payment in the month of
C60: (P ) | E60: pesos only.
AF62: MINERVA L. BOONGALING
C63: Provincial Auditor | AF63: Mun. Treasurer

Sheet Reg1(16-31)
B1: Municipal P A Y R O L L
B2: WE HEREBY ACKNOWLEDGE TO HAVE RECEIVED FROM MINERVA L. BOONGALING, TREASURER OF PAGSANJAN, LAGUNA THE SUMS HEREIN SPECIFIED OPPOSITES OUR RESPECTIVE NAMES, THE SAME BEING FULL COMPENSATION FOR OUR SERVICES RENDERED DURING THE PERIOD STATED BELOW, TO THE CORRECTNESS OF WHICH WE HEREBY SEVERALLY
B4: NO. | C4: NAME | D4: DESIGNATION | E4: PERIOD OF SERVICE (INCLUSIVE DATES) | H4: AMOUNT ACCRUED FOR THE PERIOD | I4: RA | J4: TA | L4: D E D U C T I O N S
E5: FROM | F5: TO | K5: GOVERNMENT SERVICE INSURANCE SYSTEM | U5: GSIS | W5: W/HOLDING TAX | X5: PAG-IBIG FUND | AB5: LBP | AC5: UCPB | AD5: AMOUNT PAID IN CASH (CR.A-1) | AE5: N U M B E R
G6: MONTHLY RATE OF PAY | K6: MPL Lite | L6: CONSO LOAN | M6: Emergency Loan | N6: Educational Loan | O6: Policy Loan (Regular) | P6: Ploicy Loan (Optional) | Q6: UOLI | R6: COMPUTER LOAN | S6: MPL | T6: GFAL | U6: LIFE/RETIREMENT INSURANCE PREMIUM | AF6: SIGNATURE OF PAYEE | AG6: REMARKS
X7: PERSONAL SHARE | Y7: GOV'T. SHARE | Z7: MPL | AA7: CAL
U8: PERSONAL SHARE | V8: GOVERNMENT SHARE
B10: 1 | C10: 2 | D10: 3 | E10: 4 | F10: 5 | G10: 6 | H10: 7 | L10: 8 | M10: 12 | N10: 9 | O10: 13 | P10: 18 | Q10: 19 | T10: 19 | U10: 16 | V10: 17 | X10: 14 | Y10: 15 | Z10: 22 | AA10: 23 | AB10: 21 | AC10: 20 | AD10: 25 | AE10: 26 | AF10: 27 | AG10: 28
C11: 1011- OM
B12: 1 | D12: Municipal Mayor | E12: Feb.16-28, 2026 | G12: 121264 | H12: =G12/2 -> 60632 | W12: 18231.24 | X12: =G12*0.02 -> 2425.28 | Y12: 2425.28 | AD12: =H12-SUM(L12:X12)-SUM(Z12:AC12) -> 39975.48 | AE12: 1
B13: 2 | D13: Executive Asst. II | E13: -d | F13: o- | G13: 40160 | H13: =G13/2 -> 20080 | W13: 2156.01 | X13: =G13*0.02 -> 803.2 | Y13: 803.2 | AD13: =H13-SUM(L13:X13)-SUM(Z13:AC13) -> 17120.79 | AE13: 2
B14: 3 | D14: Private Sec. II | E14: -d | F14: o- | G14: 34177 | H14: =G14/2 -> 17088.5 | W14: 1309.47 | X14: =G14*0.02 -> 683.54 | Y14: 2425.28 | AD14: =H14-SUM(L14:X14)-SUM(Z14:AC14) -> 15095.49 | AE14: 3
B15: 4 | D15: Bookbinder IV | E15: -d | F15: o- | G15: 21922 | H15: =G15/2 -> 10961 | M15: 605.71 | X15: =G15*0.02 -> 438.44 | Y15: =X15 -> 438.44 | AC15: 1741.7 | AD15: =H15-SUM(L15:X15)-SUM(Z15:AC15) -> 8175.15 | AE15: 4
B16: 5 | D16: Admin. Aide IV | E16: -d | F16: o- | G16: ='[1]Reg1(1-15)'!$G$14 -> 14308 | H16: =G16/2 -> 7154 | K16: =950 -> 950 | M16: 274.33 | X16: =G16*0.02 -> 286.16 | Y16: =X16 -> 286.16 | Z16: 608.13 | AC16: 4000 | AD16: =H16-SUM(K16:X16)-SUM(Z16:AC16) -> 1035.38 | AE16: 5
B17: 6 | D17: Personal Driver | E17: -d | F17: o- | G17: 13474 | H17: =G17/2 -> 6737 | X17: =G17*0.02 -> 269.48 | Y17: =X17 -> 269.48 | AD17: =H17-SUM(K17:X17)-SUM(Z17:AC17) -> 6467.52 | AE17: 6
B18: 7 | D18: Personal Driver | E18: -d | F18: o- | G18: 13474 | H18: =G18/2 -> 6737 | X18: =G18*0.02 -> 269.48 | Y18: =X18 -> 269.48 | AD18: =H18-SUM(K18:X18)-SUM(Z18:AC18) -> 6467.52 | AE18: 7
B19: 9 | G19: =SUM(G12:G18) -> 258779 | H19: =SUM(H12:H18) -> 129389.5 | I19: =SUM(I12:I18) -> 0 | J19: =SUM(J12:J18) -> 0 | K19: =SUM(K12:K18) -> 950 | L19: =SUM(L12:L18) -> 0 | M19: =SUM(M12:M18) -> 880.04 | N19: =SUM(N12:N18) -> 0 | ... AD19: =SUM(AD12:AD18) -> 94337.33 | AE19: 9
B20: 10 | C20: 1011- OM | AE20: 10
B21: 11 | D21: BAC Sec./ Admin Officer IV | E21: Feb.16-28, 2026 | G21: ='[1]Reg1(1-15)'!$G$18 -> 34177 | H21: =G21/2 -> 17088.5 | M21: 1310.72 | W21: 1309.47 | X21: =G21*0.02 -> 683.54 | Y21: =X21 -> 683.54 | AC21: 2616.89 | AD21: =H21-SUM(K21:X21)-SUM(Z21:AC21) -> 11167.88 | AE21: 11 | AK21: =1000-156 -> 844
B22: 12 | G22: =G21 -> 34177 | H22: =H21 -> 17088.5 | K22: =K21 -> 0 | L22: =L21 -> 0 | M22: =M21 -> 1310.72 | N22: =N21 -> 0 | O22: =O21 -> 0 | P22: =P21 -> 0 | Q22: =Q21 -> 0 | R22: =R21 -> 0 | ... AD22: =AD21 -> 11167.88 | AE22: 12
B23: 13 | C23: 1031- ADMIN | AE23: 13
B24: 14 | D24: Mun. Administrator | E24: Feb.16-28, 2026 | G24: 83457 | H24: =G24/2 -> 41728.5 | W24: 11800.36 | X24: =G24*0.02 -> 1669.14 | Y24: 1669.14 | AD24: =H24-SUM(K24:X24)-SUM(Z24:AC24) -> 28259 | AE24: 14
B25: 15 | G25: =G24 -> 83457 | H25: =H24 -> 41728.5 | I25: =I24 -> 0 | J25: =J24 -> 0 | K25: =K24 -> 0 | L25: =L24 -> 0 | M25: =M24 -> 0 | N25: =N24 -> 0 | ... AD25: =AD24 -> 28259 | AE25: 15
B26: 16 | C26: 1032 - HRMO | AE26: 16
B27: 17 | C27: HERMAR E. LIMUACO | D27: MGDH I | E27: Feb.16-28, 2026 | G27: ='[1]Reg1(1-15)'!$G$24 -> 86091 | H27: =G27/2 -> 43045.5 | K27: 1166.66 | O27: 150 | S27: 5705.07 | T27: 9623.94 | W27: 10492.18 | X27: =G27*0.02 -> 1721.82 | Y27: =X27 -> 1721.82 | Z27: 3203.95 | AB27: 2000 | AC27: 4757.99 | AD27: =H27-SUM(K27:X27)-SUM(Z27:AC27) -> 4223.89 | AE27: 17
B28: 18 | D28: Bookbinder IV | E28: -d | F28: o- | G28: 21922 | H28: =G28/2 -> 10961 | K28: 2333.33 | O28: 200 | R28: 983.34 | S28: 2306.21 | T28: 2887.91 | X28: =G28*0.02 -> 438.44 | Y28: =X28 -> 438.44 | AD28: =H28-SUM(K28:X28)-SUM(Z28:AC28) -> 1811.77 | AE28: 18
B29: 19 | D29: Admin. Aide IV | E29: -d | F29: o- | G29: 14308 | H29: =G29/2 -> 7154 | R29: 1966.67 | S29: 1535.63 | X29: =G29*0.02 -> 286.16 | Y29: =X29 -> 286.16 | AD29: =H29-SUM(K29:X29)-SUM(Z29:AC29) -> 3365.54 | AE29: 19
B30: 20 | D30: Admin. Aide III | E30: -d | F30: o- | G30: 13474 | H30: =G30/2 -> 6737 | X30: =G30*0.02 -> 269.48 | Y30: =X30 -> 269.48 | AB30: 4707.56 | AD30: =H30-SUM(K30:X30)-SUM(Z30:AC30) -> 1759.96 | AE30: 20
B31: 21 | G31: =SUM(G27:G30) -> 135795 | H31: =SUM(H27:H30) -> 67897.5 | I31: =SUM(I27:I30) -> 0 | J31: =SUM(J27:J30) -> 0 | K31: =SUM(K27:K30) -> 3499.99 | L31: =SUM(L27:L30) -> 0 | M31: =SUM(M27:M30) -> 0 | N31: =SUM(N27:N30) -> 0 | ... AD31: =SUM(AD27:AD30) -> 11161.16 | AE31: 21
B32: 22 | C32: 1041- MPDC | AE32: 22
B33: 23 | D33: Proj. Dev't. Officer III | E33: Feb.16-28, 2026 | G33: ='[1]Reg1(1-15)'!$G$30 -> 43608 | H33: =G33/2 -> 21804 | K33: 1166.66 | M33: 655.56 | R33: 1966.67 | S33: 2454.66 | W33: 2752.52 | X33: =G33*0.02 -> 872.16 | Y33: =X33 -> 872.16 | Z33: 2430.52 | AC33: 4173.95 | AD33: =H33-SUM(K33:X33)-SUM(Z33:AC33)+I33+J33 -> 5331.3 | AE33: 23
B34: 24 | D34: Zoning Officer I | E34: -d | F34: o- | G34: ='[1]Reg1(1-15)'!$G$31 -> 25520 | H34: =G34/2 -> 12760 | M34: 655.56 | W34: 186.22 | X34: =G34*0.02 -> 510.4 | Y34: =X34 -> 510.4 | AD34: =H34-SUM(K34:X34)-SUM(Z34:AC34) -> 11407.82 | AE34: 24
B35: 25 | D35: Bookbinder IV | E35: -d | F35: o- | G35: 21748 | H35: =G35/2 -> 10874 | X35: =G35*0.02 -> 434.96 | Y35: =X35 -> 434.96 | AB35: 3313.51 | AC35: 2973.74 | AD35: =H35-SUM(K35:X35)-SUM(Z35:AC35) -> 4151.79 | AE35: 25
B36: 26 | D36: Admin. Aide IV | E36: -d | F36: o- | G36: 14308 | H36: =G36/2 -> 7154 | X36: =G36*0.02 -> 286.16 | Y36: =X36 -> 286.16 | AC36: 1660.72 | AD36: =H36-SUM(K36:X36)-SUM(Z36:AC36) -> 5207.12 | AE36: 26
B37: 27 | G37: =SUM(G33:G36) -> 105184 | H37: =SUM(H33:H36) -> 52592 | I37: =SUM(I33:I36) -> 0 | J37: =SUM(J33:J36) -> 0 | K37: =SUM(K33:K36) -> 1166.66 | L37: =SUM(L33:L36) -> 0 | M37: =SUM(M33:M36) -> 1311.12 | N37: =SUM(N33:N36) -> 0 | ... AD37: =SUM(AD33:AD36) -> 26098.03 | AE37: 27
